Workbook

Sheet Lista Itemów
A1: Nazwa | B1: Opis | C1: Main Flaga | D1: Flaga | E1: ItemCategory | F1: ItemType | G1: ItemGroupType | H1: PLIK | I1: Stackowanie | J1: Instancja[OLD] | K1: Instancja [SAGA3] | L1: model nazwa | M1: Waga | N1: hideNick | O1: Liczba użyć | P1: Stamina 1 Hit | Q1: HP 1 hit | R1: Mana 1 Hit | S1: Stamina | T1: HP | U1: MANA | V1: Rodzaj Obrażeń | W1: DMG | X1: Zasięg | Y1: W: Siła | Z1: W: Zręczność | AA1: W: Inteligencja | AB1: W: Krąg | AC1: W: Mana | AD1: Wytrzymałość | AE1: expirationTime | AF1: Obuchowa | AG1: Pociski | AH1: Sieczna | AI1: Magia | AJ1: Ogień | AK1: Upadek | AL1: Tier | AM1: Profesja | AN1: Kategoria
A2: Pieczona ryba | B2: Zwykła pieczona ryba | C2: ITEM_CAT_FOOD | D2: - | E2: Consumable | F2: Food | G2: AdminFood | H2: consumable | I2: TRUE | J2: ITFO_FISH | K2: ITFO_GS_01 | L2: ItFo_Fish.3ds | M2: 0.3 | N2: FALSE | O2: 2 | P2: 2.5 | Q2: 0 | R2: 0 | S2: =O2*P2 -> 5 | T2: =O2*Q2 -> 0 | U2: =O2*R2 -> 0 | V2: BRAK | W2: BRAK | X2: BRAK | Y2: BRAK | Z2: BRAK | AA2: BRAK | AB2: BRAK | AC2: BRAK | AD2: BRAK | AE2: 10800 | AF2: BRAK | AG2: BRAK | AH2: BRAK | AI2: BRAK | AJ2: BRAK | AK2: BRAK | AL2: T0 | AM2: Kucharz | AN2: Kuchenka
A3: Pieczone mięso | B3: Zwykłe pieczone mięso | C3: ITEM_CAT_FOOD | D3: - | E3: Consumable | F3: Food | G3: AdminFood | H3: consumable | I3: TRUE | J3: ITFO_ROASTEDRATMEAT | K3: ITFO_GS_02 | L3: KM_cooked_meat_02.3ds | M3: 0.3 | N3: FALSE | O3: 2 | P3: 2.5 | Q3: 0 | R3: 0 | S3: =O3*P3 -> 5 | T3: =O3*Q3 -> 0 | U3: =O3*R3 -> 0 | V3: BRAK | W3: BRAK | X3: BRAK | Y3: BRAK | Z3: BRAK | AA3: BRAK | AB3: BRAK | AC3: BRAK | AD3: BRAK | AE3: 10800 | AF3: BRAK | AG3: BRAK | AH3: BRAK | AI3: BRAK | AJ3: BRAK | AK3: BRAK | AL3: T0 | AM3: Kucharz | AN3: Kuchenka
A4: Pieczony chwast | B4: Wysuszone i upieczone liście ziela. | C4: ITEM_CAT_FOOD | D4: - | E4: Consumable | F4: Food | G4: AdminFood | H4: consumable | I4: TRUE | J4: ITPL_WEED | K4: ITFO_GS_03 | L4: ItPl_Weed.3ds | M4: 0.3 | N4: FALSE | O4: 1 | P4: 5 | Q4: 0 | R4: 0 | S4: 5 | T4: 0 | U4: 0 | V4: BRAK | W4: BRAK | X4: BRAK | Y4: BRAK | Z4: BRAK | AA4: BRAK | AB4: BRAK | AC4: BRAK | AD4: BRAK | AE4: 43200 | AF4: BRAK | AG4: BRAK | AH4: BRAK | AI4: BRAK | AJ4: BRAK | AK4: BRAK | AL4: T0 | AM4: Kucharz | AN4: Kuchenka
A5: Pasztet z resztek | B5: Idealny sposób, by dać drugie życie temu, co zostało. | C5: ITEM_CAT_FOOD | D5: - | E5: Consumable | F5: Food | G5: AdminFood | H5: consumable | I5: TRUE | J5: ITFO_POORPATE | K5: ITFO_GS_03 | L5: KM_ITFO_oatmeal.3ds | M5: 0.3 | N5: FALSE | O5: 4 | P5: 2.5 | Q5: 0 | R5: 0 | S5: =O5*P5 -> 10 | T5: =O5*Q5 -> 0 | U5: =O5*R5 -> 0 | V5: BRAK | W5: BRAK | X5: BRAK | Y5: BRAK | Z5: BRAK | AA5: BRAK | AB5: BRAK | AC5: BRAK | AD5: BRAK | AE5: 10800 | AF5: BRAK | AG5: BRAK | AH5: BRAK | AI5: BRAK | AJ5: BRAK | AK5: BRAK | AL5: T0 | AM5: Kucharz | AN5: Kuchenka
A6: Pieczone owady | B6: Chrupiemy jak królestwo owadów, no bo czemu nie? | C6: ITEM_CAT_FOOD | D6: - | E6: Consumable | F6: Food | G6: AdminFood | H6: consumable | I6: TRUE | J6: ITFO_ROASTEDINSECTS | K6: ITFO_GS_04 | L6: KM_ITFO_meatbug.3ds | M6: 0.3 | N6: FALSE | O6: 2 | P6: 5 | Q6: 0 | R6: 0 | S6: =O6*P6 -> 10 | T6: =O6*Q6 -> 0 | U6: =O6*R6 -> 0 | V6: BRAK | W6: BRAK | X6: BRAK | Y6: BRAK | Z6: BRAK | AA6: BRAK | AB6: BRAK | AC6: BRAK | AD6: BRAK | AE6: 10800 | AF6: BRAK | AG6: BRAK | AH6: BRAK | AI6: BRAK | AJ6: BRAK | AK6: BRAK | AL6: T0 | AM6: Kucharz | AN6: Kuchenka
A7: Chrupkie łuski rybne | B7: Jeśli ryba ma skórę, to czemu nie wziąć jej do pieca? | C7: ITEM_CAT_FOOD | D7: - | E7: Consumable | F7: Food | G7: AdminFood | H7: consumable | I7: TRUE | J7: ITFO_FRIEDFISHSKINS | K7: ITFO_GS_05 | L7: ItFo_FriedFishSkins.3ds | M7: 0.3 | N7: FALSE | O7: 1 | P7: 10 | Q7: 0 | R7: 0 | S7: =O7*P7 -> 10 | T7: =O7*Q7 -> 0 | U7: =O7*R7 -> 0 | V7: BRAK | W7: BRAK | X7: BRAK | Y7: BRAK | Z7: BRAK | AA7: BRAK | AB7: BRAK | AC7: BRAK | AD7: BRAK | AE7: 10800 | AF7: BRAK | AG7: BRAK | AH7: BRAK | AI7: BRAK | AJ7: BRAK | AK7: BRAK | AL7: T0 | AM7: Kucharz | AN7: Kuchenka
A8: Wiejska jajecznica | B8: Prosta, jak życie na wsi, ale smak ma wyjątkowy! | C8: ITEM_CAT_FOOD | D8: - | E8: Consumable | F8: Food | G8: AdminFood | H8: consumable | I8: TRUE | J8: ITFO_POOREGGS | K8: ITFO_GS_06 | L8: KM_ITFO_ScrambledEggs.3ds | M8: 0.4 | N8: FALSE | O8: 4 | P8: 5 | Q8: 0 | R8: 0 | S8: =O8*P8 -> 20 | T8: =O8*Q8 -> 0 | U8: =O8*R8 -> 0 | V8: BRAK | W8: BRAK | X8: BRAK | Y8: BRAK | Z8: BRAK | AA8: BRAK | AB8: BRAK | AC8: BRAK | AD8: BRAK | AE8: 10800 | AF8: BRAK | AG8: BRAK | AH8: BRAK | AI8: BRAK | AJ8: BRAK | AK8: BRAK | AL8: T1 | AM8: Kucharz | AN8: Kuchenka
A9: =HYPERLINK("https://imgur.com/eJ3CxWA","Szczur na patyku") -> Szczur na patyku | B9: Bo czasem egzotyczne smaki to najlepsza przygoda! | C9: ITEM_CAT_FOOD | D9: - | E9: Consumable | F9: Food | G9: AdminFood | H9: consumable | I9: TRUE | J9: ITFO_RATSTICK | K9: ITFO_GS_07 | L9: KM_ITFO_shashlik.3ds | M9: 0.4 | N9: FALSE | O9: 2 | P9: 7.5 | Q9: 0 | R9: 0 | S9: =O9*P9 -> 15 | T9: =O9*Q9 -> 0 | U9: =O9*R9 -> 0 | V9: BRAK | W9: BRAK | X9: BRAK | Y9: BRAK | Z9: BRAK | AA9: BRAK | AB9: BRAK | AC9: BRAK | AD9: BRAK | AE9: 10800 | AF9: BRAK | AG9: BRAK | AH9: BRAK | AI9: BRAK | AJ9: BRAK | AK9: BRAK | AL9: T1 | AM9: Kucharz | AN9: Kuchenka
A10: Ryba w cieście piwnym | B10: Smażona ryba, z odrobiną złocistego piwa – idealna równowaga! | C10: ITEM_CAT_FOOD | D10: - | E10: Consumable | F10: Food | G10: AdminFood | H10: consumable | I10: TRUE | J10: ITFO_BEERFISH | K10: ITFO_GS_08 | L10: ItFo_BeerFish.3ds | M10: 0.4 | N10: FALSE | O10: 2 | P10: 10 | Q10: 0 | R10: 0 | S10: =O10*P10 -> 20 | T10: =O10*Q10 -> 0 | U10: =O10*R10 -> 0 | V10: BRAK | W10: BRAK | X10: BRAK | Y10: BRAK | Z10: BRAK | AA10: BRAK | AB10: BRAK | AC10: BRAK | AD10: BRAK | AE10: 10800 | AF10: BRAK | AG10: BRAK | AH10: BRAK | AI10: BRAK | AJ10: BRAK | AK10: BRAK | AL10: T1 | AM10: Kucharz | AN10: Kuchenka
A11: Bigos z ochłapów | B11: Gdy mięso wędruje w towarzystwie kapusty na wesele smaku! | C11: ITEM_CAT_FOOD | D11: - | E11: Consumable | F11: Food | G11: AdminFood | H11: consumable | I11: TRUE | J11: ITFO_MEATMISHMASH | K11: ITFO_GS_09 | L11: ITFO_STEW_02.3ds | M11: 0.4 | N11: FALSE | O11: 4 | P11: 5 | Q11: 0 | R11: 0 | S11: =O11*P11 -> 20 | T11: =O11*Q11 -> 0 | U11: =O11*R11 -> 0 | V11: BRAK | W11: BRAK | X11: BRAK | Y11: BRAK | Z11: BRAK | AA11: BRAK | AB11: BRAK | AC11: BRAK | AD11: BRAK | AE11: 10800 | AF11: BRAK | AG11: BRAK | AH11: BRAK | AI11: BRAK | AJ11: BRAK | AK11: BRAK | AL11: T1 | AM11: Kucharz | AN11: Kuchenka
A12: Kiszone grzyby | B12: Grzybki, które tak szybko nie zapomną, jak się kisiły! | C12: ITEM_CAT_FOOD | D12: - | E12: Consumable | F12: Food | G12: AdminFood | H12: consumable | I12: TRUE | J12: ITFO_PICKLEDMUSHROOMS | K12: ITFO_GS_10 | L12: KM_ITFO_mushrooms.3ds | M12: 0.4 | N12: FALSE | O12: 2 | P12: 5 | Q12: 0 | R12: 0 | S12: =O12*P12 -> 10 | T12: =O12*Q12 -> 0 | U12: =O12*R12 -> 0 | V12: BRAK | W12: BRAK | X12: BRAK | Y12: BRAK | Z12: BRAK | AA12: BRAK | AB12: BRAK | AC12: BRAK | AD12: BRAK | AE12: 10800 | AF12: BRAK | AG12: BRAK | AH12: BRAK | AI12: BRAK | AJ12: BRAK | AK12: BRAK | AL12: T1 | AM12: Kucharz | AN12: Kuchenka
A13: Kwaśna rzepa | B13: Właśnie odkrywasz nowy sposób, by pokochać rzepę! | C13: ITEM_CAT_FOOD | D13: - | E13: Consumable | F13: Food | G13: AdminFood | H13: consumable | I13: TRUE | J13: ITFO_PICKLEDBEET | K13: ITFO_GS_11 | L13: KM_ITFO_PickledTurnips.3ds | M13: 0.4 | N13: FALSE | O13: 4 | P13: 2.5 | Q13: 0 | R13: 0 | S13: =O13*P13 -> 10 | T13: =O13*Q13 -> 0 | U13: =O13*R13 -> 0 | V13: BRAK | W13: BRAK | X13: BRAK | Y13: BRAK | Z13: BRAK | AA13: BRAK | AB13: BRAK | AC13: BRAK | AD13: BRAK | AE13: 10800 | AF13: BRAK | AG13: BRAK | AH13: BRAK | AI13: BRAK | AJ13: BRAK | AK13: BRAK | AL13: T1 | AM13: Kucharz | AN13: Kuchenka
A14: Szaszłyk ze ścierwojada i dyni | B14: A na grillu zawsze coś nowego do spróbowania! | C14: ITEM_CAT_FOOD | D14: - | E14: Consumable | F14: Food | G14: AdminFood | H14: consumable | I14: TRUE | J14: ITFO_RATSTICK | K14: ITFO_GS_12 | L14: KM_ITFO_shashlik.3ds | M14: 0.5 | N14: FALSE | O14: 5 | P14: 5 | Q14: 0 | R14: 0 | S14: =O14*P14 -> 25 | T14: =O14*Q14 -> 0 | U14: =O14*R14 -> 0 | V14: BRAK | W14: BRAK | X14: BRAK | Y14: BRAK | Z14: BRAK | AA14: BRAK | AB14: BRAK | AC14: BRAK | AD14: BRAK | AE14: 10800 | AF14: BRAK | AG14: BRAK | AH14: BRAK | AI14: BRAK | AJ14: BRAK | AK14: BRAK | AL14: T2 | AM14: Kucharz | AN14: Kuchenka
A15: Ryba w occie z ognistym zielem | B15: Gdzie kwaśno, gorąco, i jeszcze gorzej! (Ale smacznie) | C15: ITEM_CAT_FOOD | D15: - | E15: Consumable | F15: Food | G15: AdminFood | H15: consumable | I15: TRUE | J15: ITFO_FISHVINEGAR | K15: ITFO_GS_13 | L15: ItFo_FishSoup.3ds | M15: 0.5 | N15: FALSE | O15: 2 | P15: 12.5 | Q15: 0 | R15: 0 | S15: =O15*P15 -> 25 | T15: =O15*Q15 -> 0 | U15: =O15*R15 -> 0 | V15: BRAK | W15: BRAK | X15: BRAK | Y15: BRAK | Z15: BRAK | AA15: BRAK | AB15: BRAK | AC15: BRAK | AD15: BRAK | AE15: 10800 | AF15: BRAK | AG15: BRAK | AH15: BRAK | AI15: BRAK | AJ15: BRAK | AK15: BRAK | AL15: T2 | AM15: Kucharz | AN15: Kuchenka
A16: Wędzona ryba ziołowa | B16: Dym i zioła – jak szef kuchni w lesie! | C16: ITEM_CAT_FOOD | D16: - | E16: Consumable | F16: Food | G16: AdminFood | H16: consumable | I16: TRUE | J16: ITFO_SMOKEDHERBFISH | K16: ITFO_GS_14 | L16: KM_ITFO_Fish01.3ds | M16: 0.5 | N16: FALSE | O16: 1 | P16: 25 | Q16: 0 | R16: 0 | S16: =O16*P16 -> 25 | T16: =O16*Q16 -> 0 | U16: =O16*R16 -> 0 | V16: BRAK | W16: BRAK | X16: BRAK | Y16: BRAK | Z16: BRAK | AA16: BRAK | AB16: BRAK | AC16: BRAK | AD16: BRAK | AE16: 10800 | AF16: BRAK | AG16: BRAK | AH16: BRAK | AI16: BRAK | AJ16: BRAK | AK16: BRAK | AL16: T2 | AM16: Kucharz | AN16: Kuchenka
A17: Garnek mięsny | B17: Gar, który ma więcej tłuszczu niż twoje plany na dietę. | C17: ITEM_CAT_FOOD | D17: - | E17: Consumable | F17: Food | G17: AdminFood | H17: consumable | I17: TRUE | J17: ITFO_MARTHSOUP3 | K17: ITFO_GS_15 | L17: KM_ITFO_FoodPot.3ds | M17: 0.5 | N17: FALSE | O17: 1 | P17: 25 | Q17: 0 | R17: 0 | S17: =O17*P17 -> 25 | T17: =O17*Q17 -> 0 | U17: =O17*R17 -> 0 | V17: BRAK | W17: BRAK | X17: BRAK | Y17: BRAK | Z17: BRAK | AA17: BRAK | AB17: BRAK | AC17: BRAK | AD17: BRAK | AE17: 10800 | AF17: BRAK | AG17: BRAK | AH17: BRAK | AI17: BRAK | AJ17: BRAK | AK17: BRAK | AL17: T2 | AM17: Kucharz | AN17: Kuchenka
A18: Pieczone ostrygi | B18: Na szybko, i na ostro! | C18: ITEM_CAT_FOOD | D18: - | E18: Consumable | F18: Food | G18: AdminFood | H18: consumable | I18: TRUE | J18: ITFO_SIMPLEOYSTERS | K18: ITFO_GS_16 | L18: KM_ITFO_SeaFruit.3ds | M18: 0.5 | N18: FALSE | O18: 2 | P18: 12.5 | Q18: 0 | R18: 0 | S18: =O18*P18 -> 25 | T18: =O18*Q18 -> 0 | U18: =O18*R18 -> 0 | V18: BRAK | W18: BRAK | X18: BRAK | Y18: BRAK | Z18: BRAK | AA18: BRAK | AB18: BRAK | AC18: BRAK | AD18: BRAK | AE18: 10800 | AF18: BRAK | AG18: BRAK | AH18: BRAK | AI18: BRAK | AJ18: BRAK | AK18: BRAK | AL18: T2 | AM18: Kucharz | AN18: Kuchenka
A19: Mięsne paczuszki | B19: W środku niespodzianka: mięso! A na zewnątrz chrupiąca przyjemność. | C19: ITEM_CAT_FOOD | D19: - | E19: Consumable | F19: Food | G19: AdminFood | H19: consumable | I19: TRUE | J19: ITFO_MEATPACKS | K19: ITFO_GS_17 | L19: KM_ITFO_BreadMeatVegies.3ds | M19: 0.5 | N19: FALSE | O19: 1 | P19: 25 | Q19: 0 | R19: 0 | S19: =O19*P19 -> 25 | T19: =O19*Q19 -> 0 | U19: =O19*R19 -> 0 | V19: BRAK | W19: BRAK | X19: BRAK | Y19: BRAK | Z19: BRAK | AA19: BRAK | AB19: BRAK | AC19: BRAK | AD19: BRAK | AE19: 10800 | AF19: BRAK | AG19: BRAK | AH19: BRAK | AI19: BRAK | AJ19: BRAK | AK19: BRAK | AL19: T2 | AM19: Kucharz | AN19: Kuchenka
A20: Zapiekanka farmerska | B20: Mieszanka wszystkiego, co rośnie na farmie, i co można zapiec. | C20: ITEM_CAT_FOOD | D20: - | E20: Consumable | F20: Food | G20: AdminFood | H20: consumable | I20: TRUE | J20: ITFO_MEATANDCHEESE | K20: ITFO_GS_18 | L20: ItFo_MeatAndBread.3ds | M20: 0.6 | N20: FALSE | O20: 5 | P20: 7 | Q20: 0 | R20: 0 | S20: =O20*P20 -> 35 | T20: =O20*Q20 -> 0 | U20: =O20*R20 -> 0 | V20: BRAK | W20: BRAK | X20: BRAK | Y20: BRAK | Z20: BRAK | AA20: BRAK | AB20: BRAK | AC20: BRAK | AD20: BRAK | AE20: 14400 | AF20: BRAK | AG20: BRAK | AH20: BRAK | AI20: BRAK | AJ20: BRAK | AK20: BRAK | AL20: T3 | AM20: Kucharz | AN20: Kuchenka
A21: Pieczeń pasterska w miodzie | B21: Pasterski przysmak, który zasługuje na złote medale. | C21: ITEM_CAT_FOOD | D21: - | E21: Consumable | F21: Food | G21: AdminFood | H21: consumable | I21: TRUE | J21: ITFO_SHEPARDROAST | K21: ITFO_GS_19 | L21: ItFo_ShepardRoast.3ds | M21: 0.6 | N21: FALSE | O21: 2 | P21: 17.5 | Q21: 0 | R21: 0 | S21: =O21*P21 -> 35 | T21: =O21*Q21 -> 0 | U21: =O21*R21 -> 0 | V21: BRAK | W21: BRAK | X21: BRAK | Y21: BRAK | Z21: BRAK | AA21: BRAK | AB21: BRAK | AC21: BRAK | AD21: BRAK | AE21: 14400 | AF21: BRAK | AG21: BRAK | AH21: BRAK | AI21: BRAK | AJ21: BRAK | AK21: BRAK | AL21: T3 | AM21: Kucharz | AN21: Kuchenka
... A48: Drożówka cynamonowa | B48: Cynamonowy zapach, który czujesz z kilometra! | C48: ITEM_CAT_FOOD | D48: - | E48: Consumable | F48: Food | G48: AdminFood | H48: consumable | I48: TRUE | J48: ITFO_POORAPPLEPIE | K48: ITFO_GS_46 | L48: KM_ITFO_Pie01.3ds | M48: 0.6 | N48: FALSE | O48: 2 | P48: 17.5 | Q48: 0 | R48: 0 | S48: =O48*P48 -> 35 | T48: =O48*Q48 -> 0 | U48: =O48*R48 -> 0 | V48: BRAK | W48: BRAK | X48: BRAK | Y48: BRAK | Z48: BRAK | AA48: BRAK | AB48: BRAK | AC48: BRAK | AD48: BRAK | AE48: 14400 | AF48: BRAK | AG48: BRAK | AH48: BRAK | AI48: BRAK | AJ48: BRAK | AK48: BRAK | AL48: T3 | AM48: Kucharz | AN48: Piec
A49: Rzepa | B49: Popularne warzywo, do dodania do zup i potraw | C49: ITEM_CAT_FOOD | D49: - | E49: Consumable | F49: Food | G49: AdminFood | H49: consumable | I49: TRUE | J49: ITPL_BEET | K49: ITFO_GS_47 | L49: ItPl_Beet.3ds | M49: 0.3 | N49: FALSE | O49: 1 | P49: 1 | Q49: 0 | R49: 0 | S49: =O49*P49 -> 1 | T49: =O49*Q49 -> 0 | U49: =O49*R49 -> 0 | V49: BRAK | W49: BRAK | X49: BRAK | Y49: BRAK | Z49: BRAK | AA49: BRAK | AB49: BRAK | AC49: BRAK | AD49: BRAK | AE49: 21600 | AF49: BRAK | AG49: BRAK | AH49: BRAK | AI49: BRAK | AJ49: BRAK | AK49: BRAK | AL49: BRAK | AM49: Rolnik
A50: Marchew | B50: Słodkie i soczyste, idealne do dodania smaku potrawom. | C50: ITEM_CAT_FOOD | D50: - | E50: Consumable | F50: Food | G50: AdminFood | H50: consumable | I50: TRUE | J50: itfo_SDRP_food_21 | K50: ITFO_GS_48 | L50: ITFO_CARROT.3ds | M50: 0.3 | N50: FALSE | O50: 1 | P50: 1 | Q50: 0 | R50: 0 | S50: =O50*P50 -> 1 | T50: =O50*Q50 -> 0 | U50: =O50*R50 -> 0 | V50: BRAK | W50: BRAK | X50: BRAK | Y50: BRAK | Z50: BRAK | AA50: BRAK | AB50: BRAK | AC50: BRAK | AD50: BRAK | AE50: 21600 | AF50: BRAK | AG50: BRAK | AH50: BRAK | AI50: BRAK | AJ50: BRAK | AK50: BRAK | AL50: BRAK | AM50: Rolnik
A51: Len | B51: Używany do wytwarzania tkanin, z których można szyć ubrania | C51: ITEM_CAT_NONE | D51: - | E51: Materials | F51: Materials | G51: AdminMaterials | H51: materials | I51: TRUE | J51: GS_NATURE_FLAX_03_GALI | K51: ITMI_GS_MAT_03 | L51: GS_NATURE_FLAX_03_GALI.3ds | M51: 0.3 | N51: FALSE | O51: BRAK | P51: BRAK | Q51: BRAK | R51: BRAK | S51: BRAK | T51: BRAK | U51: BRAK | V51: BRAK | W51: BRAK | X51: BRAK | Y51: BRAK | Z51: BRAK | AA51: BRAK | AB51: BRAK | AC51: BRAK | AD51: BRAK | AE51: 21600 | AF51: BRAK | AG51: BRAK | AH51: BRAK | AI51: BRAK | AJ51: BRAK | AK51: BRAK | AL51: BRAK | AM51: Rolnik
A52: Pszenica | B52: Podstawowy składnik mąki. | C52: ITEM_CAT_NONE | D52: - | E52: Materials | F52: Materials | G52: AdminMaterials | H52: materials | I52: TRUE | J52: GS_NATURE_WHEAT_03_GALI | K52: ITMI_GS_MAT_04 | L52: GS_NATURE_WHEAT_03_GALI.3ds | M52: 0.3 | N52: FALSE | O52: BRAK | P52: BRAK | Q52: BRAK | R52: BRAK | S52: BRAK | T52: BRAK | U52: BRAK | V52: BRAK | W52: BRAK | X52: BRAK | Y52: BRAK | Z52: BRAK | AA52: BRAK | AB52: BRAK | AC52: BRAK | AD52: BRAK | AE52: 21600 | AF52: BRAK | AG52: BRAK | AH52: BRAK | AI52: BRAK | AJ52: BRAK | AK52: BRAK | AL52: BRAK | AM52: Rolnik
A53: Dynia | B53: Słodka i sycąca, idealna do zup, ciast i deserów. | C53: ITEM_CAT_FOOD | D53: - | E53: Consumable | F53: Food | G53: AdminFood | H53: consumable | I53: TRUE | J53: ITFO_SDRP_KM_09 | K53: ITFO_GS_49 | L53: KM_vob_pumpkin_01.3ds | M53: 0.6 | N53: FALSE | O53: 2 | P53: 1 | Q53: 0 | R53: 0 | S53: =O53*P53 -> 2 | T53: =O53*Q53 -> 0 | U53: =O53*R53 -> 0 | V53: BRAK | W53: BRAK | X53: BRAK | Y53: BRAK | Z53: BRAK | AA53: BRAK | AB53: BRAK | AC53: BRAK | AD53: BRAK | AE53: 21600 | AF53: BRAK | AG53: BRAK | AH53: BRAK | AI53: BRAK | AJ53: BRAK | AK53: BRAK | AL53: BRAK | AM53: Rolnik
A54: Kapusta | B54: Niezastąpiony składnik wielu sałatek. | C54: ITEM_CAT_FOOD | D54: - | E54: Consumable | F54: Food | G54: AdminFood | H54: consumable | I54: TRUE | J54: ITFO_GS_Kapusta | K54: ITFO_GS_50 | L54: Kapusta.3ds | M54: 0.6 | N54: FALSE | O54: 3 | P54: 1 | Q54: 0 | R54: 0 | S54: =O54*P54 -> 3 | T54: =O54*Q54 -> 0 | U54: =O54*R54 -> 0 | V54: BRAK | W54: BRAK | X54: BRAK | Y54: BRAK | Z54: BRAK | AA54: BRAK | AB54: BRAK | AC54: BRAK | AD54: BRAK | AE54: 21600 | AF54: BRAK | AG54: BRAK | AH54: BRAK | AI54: BRAK | AJ54: BRAK | AK54: BRAK | AL54: BRAK | AM54: Rolnik
A55: Ziarno pszenicy | B55: Suchą rośline dalikatnie zmiel, a następnie odseperuj ziarenka | C55: ITEM_CAT_NONE | D55: - | E55: Common | F55: Common | G55: AdminCommon | H55: common | I55: TRUE | J55: itpl_SDRP_herb_37 | K55: ITMI_GS_COM_01 | L55: NASIONO18.3ds | M55: 0.05 | N55: FALSE | O55: BRAK | P55: BRAK | Q55: BRAK | R55: BRAK | S55: BRAK | T55: BRAK | U55: BRAK | V55: BRAK | W55: BRAK | X55: BRAK | Y55: BRAK | Z55: BRAK | AA55: BRAK | AB55: BRAK | AC55: BRAK | AD55: BRAK | AE55: BRAK | AF55: BRAK | AG55: BRAK | AH55: BRAK | AI55: BRAK | AJ55: BRAK | AK55: BRAK | AL55: T1 | AM55: Rolnik
A56: Nasiono marchwi | B56: Suchą rośline dalikatnie zmiel, a następnie odseperuj ziarenka | C56: ITEM_CAT_NONE | D56: - | E56: Common | F56: Common | G56: AdminCommon | H56: common | I56: TRUE | J56: itpl_SDRP_herb_48 | K56: ITMI_GS_COM_02 | L56: NASIONO29.3ds | M56: 0.05 | N56: FALSE | O56: BRAK | P56: BRAK | Q56: BRAK | R56: BRAK | S56: BRAK | T56: BRAK | U56: BRAK | V56: BRAK | W56: BRAK | X56: BRAK | Y56: BRAK | Z56: BRAK | AA56: BRAK | AB56: BRAK | AC56: BRAK | AD56: BRAK | AE56: BRAK | AF56: BRAK | AG56: BRAK | AH56: BRAK | AI56: BRAK | AJ56: BRAK | AK56: BRAK | AL56: T1 | AM56: Rolnik
A57: Wiązka słomy | B57: Wiązka słomy | C57: ITEM_CAT_ACSR2 | D57: - | E57: AccessorySlot2 | F57: Accessory | G57: AdminAccessory | H57: acsr2 | I57: TRUE | J57: LINK | K57: ITAC_GS_ACSR2_02 | L57: STATIC_KOZA_KLOSO_01.3ds | M57: 0.05 | N57: FALSE | O57: BRAK | P57: BRAK | Q57: BRAK | R57: BRAK | S57: BRAK | T57: BRAK | U57: BRAK | V57: BRAK | W57: BRAK | X57: BRAK | Y57: BRAK | Z57: BRAK | AA57: BRAK | AB57: BRAK | AC57: BRAK | AD57: BRAK | AE57: BRAK | AF57: BRAK | AG57: BRAK | AH57: BRAK | AI57: BRAK | AJ57: BRAK | AK57: BRAK | AL57: T1 | AM57: Rolnik
A58: Paczka lnu | B58: Ususzone włókna lnu zapakowane w małe paczki | C58: ITEM_CAT_NONE | D58: - | E58: Materials | F58: Materials | G58: AdminMaterials | H58: materials | I58: TRUE | J58: KM_ITMI_PACKET_03 | K58: ITMI_GS_MAT_05 | L58: KM_ITMI_PACKET_03.3ds | M58: 1 | N58: FALSE | O58: BRAK | P58: BRAK | Q58: BRAK | R58: BRAK | S58: BRAK | T58: BRAK | U58: BRAK | V58: BRAK | W58: BRAK | X58: BRAK | Y58: BRAK | Z58: BRAK | AA58: BRAK | AB58: BRAK | AC58: BRAK | AD58: BRAK | AE58: BRAK | AF58: BRAK | AG58: BRAK | AH58: BRAK | AI58: BRAK | AJ58: BRAK | AK58: BRAK | AL58: T1 | AM58: Rolnik
A59: Lina | B59: Wysuszone włókna poddaje się procesowi zaplatania | C59: ITEM_CAT_NONE | D59: - | E59: Materials | F59: Materials | G59: AdminMaterials | H59: materials | I59: TRUE | J59: ITMI_NACPANY | K59: ITMI_GS_MAT_06 | L59: IT_SlaveRope.3ds | M59: 1 | N59: FALSE | O59: BRAK | P59: BRAK | Q59: BRAK | R59: BRAK | S59: BRAK | T59: BRAK | U59: BRAK | V59: BRAK | W59: BRAK | X59: BRAK | Y59: BRAK | Z59: BRAK | AA59: BRAK | AB59: BRAK | AC59: BRAK | AD59: BRAK | AE59: BRAK | AF59: BRAK | AG59: BRAK | AH59: BRAK | AI59: BRAK | AJ59: BRAK | AK59: BRAK | AL59: T1 | AM59: Rolnik
A60: Ziarno lnu | B60: Suchą rośline dalikatnie zmiel, a następnie odseperuj ziarenka | C60: ITEM_CAT_NONE | D60: - | E60: Common | F60: Common | G60: AdminCommon | H60: common | I60: TRUE | J60: itpl_SDRP_herb_50 | K60: ITMI_GS_COM_03 | L60: NASIONO30.3ds | M60: 0.05 | N60: FALSE | O60: BRAK | P60: BRAK | Q60: BRAK | R60: BRAK | S60: BRAK | T60: BRAK | U60: BRAK | V60: BRAK | W60: BRAK | X60: BRAK | Y60: BRAK | Z60: BRAK | AA60: BRAK | AB60: BRAK | AC60: BRAK | AD60: BRAK | AE60: BRAK | AF60: BRAK | AG60: BRAK | AH60: BRAK | AI60: BRAK | AJ60: BRAK | AK60: BRAK | AL60: T1 | AM60: Rolnik
A61: Pasza | B61: Pasza stanowi jedzenie dla zwierząt hodowlanych | C61: ITEM_CAT_NONE | D61: - | E61: Common | F61: Common | G61: AdminCommon | H61: common | I61: TRUE | J61: PASZA | K61: ITMI_GS_COM_04 | L61: PASZA.3ds | M61: 1 | N61: FALSE | O61: BRAK | P61: BRAK | Q61: BRAK | R61: BRAK | S61: BRAK | T61: BRAK | U61: BRAK | V61: BRAK | W61: BRAK | X61: BRAK | Y61: BRAK | Z61: BRAK | AA61: BRAK | AB61: BRAK | AC61: BRAK | AD61: BRAK | AE61: BRAK | AF61: BRAK | AG61: BRAK | AH61: BRAK | AI61: BRAK | AJ61: BRAK | AK61: BRAK | AL61: T1 | AM61: Rolnik
A62: Nasiono rzepy | B62: Suchą rośline dalikatnie zmiel, a następnie odseperuj ziarenka | C62: ITEM_CAT_NONE | D62: - | E62: Common | F62: Common | G62: AdminCommon | H62: common | I62: TRUE | J62: itpl_SDRP_herb_31 | K62: ITMI_GS_COM_05 | L62: NASIONO12.3ds | M62: 0.05 | N62: FALSE | O62: BRAK | P62: BRAK | Q62: BRAK | R62: BRAK | S62: BRAK | T62: BRAK | U62: BRAK | V62: BRAK | W62: BRAK | X62: BRAK | Y62: BRAK | Z62: BRAK | AA62: BRAK | AB62: BRAK | AC62: BRAK | AD62: BRAK | AE62: BRAK | AF62: BRAK | AG62: BRAK | AH62: BRAK | AI62: BRAK | AJ62: BRAK | AK62: BRAK | AL62: T0 | AM62: Rolnik
A63: Pestka dyni | B63: Suchą rośline dalikatnie zmiel, a następnie odseperuj ziarenka | C63: ITEM_CAT_NONE | D63: - | E63: Common | F63: Common | G63: AdminCommon | H63: common | I63: TRUE | J63: itpl_SDRP_herb_69 | K63: ITMI_GS_COM_06 | L63: NASIONO28.3ds | M63: 0.05 | N63: FALSE | O63: BRAK | P63: BRAK | Q63: BRAK | R63: BRAK | S63: BRAK | T63: BRAK | U63: BRAK | V63: BRAK | W63: BRAK | X63: BRAK | Y63: BRAK | Z63: BRAK | AA63: BRAK | AB63: BRAK | AC63: BRAK | AD63: BRAK | AE63: BRAK | AF63: BRAK | AG63: BRAK | AH63: BRAK | AI63: BRAK | AJ63: BRAK | AK63: BRAK | AL63: T2 | AM63: Rolnik
A64: Paczka wełny | B64: Wełna zapakowane w małe paczuszki | C64: ITEM_CAT_NONE | D64: - | E64: Materials | F64: Materials | G64: AdminMaterials | H64: materials | I64: TRUE | J64: KM_ITMI_PACKET_07 | K64: ITMI_GS_MAT_07 | L64: KM_ITMI_PACKET_07.3ds | M64: 1.5 | N64: FALSE | O64: BRAK | P64: BRAK | Q64: BRAK | R64: BRAK | S64: BRAK | T64: BRAK | U64: BRAK | V64: BRAK | W64: BRAK | X64: BRAK | Y64: BRAK | Z64: BRAK | AA64: BRAK | AB64: BRAK | AC64: BRAK | AD64: BRAK | AE64: BRAK | AF64: BRAK | AG64: BRAK | AH64: BRAK | AI64: BRAK | AJ64: BRAK | AK64: BRAK | AL64: T2 | AM64: Rolnik
A65: Nasiono kapusty | B65: Suchą rośline dalikatnie zmiel, a następnie odseperuj ziarenka | C65: ITEM_CAT_NONE | D65: - | E65: Common | F65: Common | G65: AdminCommon | H65: common | I65: TRUE | J65: itpl_SDRP_herb_21 | K65: ITMI_GS_COM_07 | L65: NASIONO2.3ds | M65: 0.05 | N65: FALSE | O65: BRAK | P65: BRAK | Q65: BRAK | R65: BRAK | S65: BRAK | T65: BRAK | U65: BRAK | V65: BRAK | W65: BRAK | X65: BRAK | Y65: BRAK | Z65: BRAK | AA65: BRAK | AB65: BRAK | AC65: BRAK | AD65: BRAK | AE65: BRAK | AF65: BRAK | AG65: BRAK | AH65: BRAK | AI65: BRAK | AJ65: BRAK | AK65: BRAK | AL65: T3 | AM65: Rolnik
A66: =HYPERLINK("https://imgur.com/fMgtFfX","Mączka kostna") -> Mączka kostna | B66: Przemielone kości idealnie nadające się do użyźnienia gleby | C66: ITEM_CAT_NONE | D66: - | E66: Common | F66: Common | G66: AdminCommon | H66: common | I66: TRUE | J66: ITCR_SDRP_INGR_21 | K66: ITMI_GS_COM_08 | L66: ItMi_Pocket.3ds | M66: 0.5 | N66: FALSE | O66: BRAK | P66: BRAK | Q66: BRAK | R66: BRAK | S66: BRAK | T66: BRAK | U66: BRAK | V66: BRAK | W66: BRAK | X66: BRAK | Y66: BRAK | Z66: BRAK | AA66: BRAK | AB66: BRAK | AC66: BRAK | AD66: BRAK | AE66: BRAK | AF66: BRAK | AG66: BRAK | AH66: BRAK | AI66: BRAK | AJ66: BRAK | AK66: BRAK | AL66: T1 | AM66: Rolnik
A67: Mąka | B67: Worek pełen białego proszku | C67: ITEM_CAT_NONE | D67: - | E67: Materials | F67: Materials | G67: AdminMaterials | H67: materials | I67: TRUE | J67: ITCR_SDRP_INGR_24 | K67: ITMI_GS_MAT_08 | L67: ItMi_Alchemy_Salt_01.3ds | M67: 0.5 | N67: FALSE | O67: BRAK | P67: BRAK | Q67: BRAK | R67: BRAK | S67: BRAK | T67: BRAK | U67: BRAK | V67: BRAK | W67: BRAK | X67: BRAK | Y67: BRAK | Z67: BRAK | AA67: BRAK | AB67: BRAK | AC67: BRAK | AD67: BRAK | AE67: BRAK | AF67: BRAK | AG67: BRAK | AH67: BRAK | AI67: BRAK | AJ67: BRAK | AK67: BRAK | AL67: T1 | AM67: Rolnik
A68: Jajko | B68: Idealne do jajecznicy | C68: ITEM_CAT_NONE | D68: - | E68: Materials | F68: Materials | G68: AdminMaterials | H68: materials | I68: TRUE | J68: ITCR_SDRP_DROP_10 | K68: ITMI_GS_MAT_09 | L68: TOD_HUEHNEREI01.3ds | M68: 0.1 | N68: FALSE | O68: 1 | P68: 1 | Q68: 0 | R68: 0 | S68: =O68*P68 -> 1 | T68: =O68*Q68 -> 0 | U68: =O68*R68 -> 0 | V68: BRAK | W68: BRAK | X68: BRAK | Y68: BRAK | Z68: BRAK | AA68: BRAK | AB68: BRAK | AC68: BRAK | AD68: BRAK | AE68: 21600 | AF68: BRAK | AG68: BRAK | AH68: BRAK | AI68: BRAK | AJ68: BRAK | AK68: BRAK | AL68: T1 | AM68: Rolnik
A69: Wełna | B69: Wełna zebrana z owcy | C69: ITEM_CAT_NONE | D69: - | E69: Materials | F69: Materials | G69: AdminMaterials | H69: materials | I69: TRUE | J69: ITFO_GS_Bawelna | K69: ITMI_GS_MAT_10 | L69: ITFO_GS_Bawelna.3ds | M69: 0.5 | N69: FALSE | O69: BRAK | P69: BRAK | Q69: BRAK | R69: BRAK | S69: BRAK | T69: BRAK | U69: BRAK | V69: BRAK | W69: BRAK | X69: BRAK | Y69: BRAK | Z69: BRAK | AA69: BRAK | AB69: BRAK | AC69: BRAK | AD69: BRAK | AE69: BRAK | AF69: BRAK | AG69: BRAK | AH69: BRAK | AI69: BRAK | AJ69: BRAK | AK69: BRAK | AL69: T2 | AM69: Rolnik
A70: Mleko | B70: Świeże, wiejskie mleko | C70: ITEM_CAT_FOOD | D70: ITEM_FLAG_DRINK | E70: Consumable | F70: Food | G70: AdminFood | H70: consumable | I70: TRUE | J70: ITFO_MILK | K70: ITFO_GS_51 | L70: ItFo_Milk.3ds | M70: 0.2 | N70: FALSE | O70: 1 | P70: 2 | Q70: 0 | R70: 0 | S70: =O70*P70 -> 2 | T70: =O70*Q70 -> 0 | U70: =O70*R70 -> 0 | V70: BRAK | W70: BRAK | X70: BRAK | Y70: BRAK | Z70: BRAK | AA70: BRAK | AB70: BRAK | AC70: BRAK | AD70: BRAK | AE70: 21600 | AF70: BRAK | AG70: BRAK | AH70: BRAK | AI70: BRAK | AJ70: BRAK | AK70: BRAK | AL70: T2 | AM70: Rolnik
A71: Ser | B71: Ma trójkątny kształt, zawiera dużą ilość dziur | C71: ITEM_CAT_FOOD | D71: - | E71: Consumable | F71: Food | G71: AdminFood | H71: consumable | I71: TRUE | J71: ITFO_CHEESE | K71: ITFO_GS_52 | L71: ItFo_Cheese.3ds | M71: 0.5 | N71: FALSE | O71: 2 | P71: 2 | Q71: 0 | R71: 0 | S71: =O71*P71 -> 4 | T71: =O71*Q71 -> 0 | U71: =O71*R71 -> 0 | V71: BRAK | W71: BRAK | X71: BRAK | Y71: BRAK | Z71: BRAK | AA71: BRAK | AB71: BRAK | AC71: BRAK | AD71: BRAK | AE71: 21600 | AF71: BRAK | AG71: BRAK | AH71: BRAK | AI71: BRAK | AJ71: BRAK | AK71: BRAK | AL71: T3 | AM71: Rolnik
A72: Duża bryła węgla | B72: Duża bryła węgla idelna do zmielenia na mniejsze części | C72: ITEM_CAT_NONE | D72: - | E72: Materials | F72: Materials | G72: AdminMaterials | H72: materials | I72: TRUE | J72: BIG_BRYLKA_WEGIEL | K72: ITMI_GS_MAT_11 | L72: BIG_BRYLKA_WEGIEL.3ds | M72: 1.5 | N72: FALSE | O72: BRAK | P72: BRAK | Q72: BRAK | R72: BRAK | S72: BRAK | T72: BRAK | U72: BRAK | V72: BRAK | W72: BRAK | X72: BRAK | Y72: BRAK | Z72: BRAK | AA72: BRAK | AB72: BRAK | AC72: BRAK | AD72: BRAK | AE72: BRAK | AF72: BRAK | AG72: BRAK | AH72: BRAK | AI72: BRAK | AJ72: BRAK | AK72: BRAK | AL72: BRAK | AM72: Górnik
A73: Duża bryła złota | B73: Duża bryła złota idelna do zmielenia na mniejsze części | C73: ITEM_CAT_NONE | D73: - | E73: Materials | F73: Materials | G73: AdminMaterials | H73: materials | I73: TRUE | J73: BIG_BRYLKA_ZLOTO | K73: ITMI_GS_MAT_12 | L73: BIG_BRYLKA_ZLOTO.3ds | M73: 1.5 | N73: FALSE | O73: BRAK | P73: BRAK | Q73: BRAK | R73: BRAK | S73: BRAK | T73: BRAK | U73: BRAK | V73: BRAK | W73: BRAK | X73: BRAK | Y73: BRAK | Z73: BRAK | AA73: BRAK | AB73: BRAK | AC73: BRAK | AD73: BRAK | AE73: BRAK | AF73: BRAK | AG73: BRAK | AH73: BRAK | AI73: BRAK | AJ73: BRAK | AK73: BRAK | AL73: BRAK | AM73: Górnik
A74: Duża bryła żelaza | B74: Duża bryła żelaza idelna do zmielenia na mniejsze części | C74: ITEM_CAT_NONE | D74: - | E74: Materials | F74: Materials | G74: AdminMaterials | H74: materials | I74: TRUE | J74: BIG_BRYLKA_ZELAZO | K74: ITMI_GS_MAT_13 | L74: BIG_BRYLKA_ZELAZO.3ds | M74: 1.5 | N74: FALSE | O74: BRAK | P74: BRAK | Q74: BRAK | R74: BRAK | S74: BRAK | T74: BRAK | U74: BRAK | V74: BRAK | W74: BRAK | X74: BRAK | Y74: BRAK | Z74: BRAK | AA74: BRAK | AB74: BRAK | AC74: BRAK | AD74: BRAK | AE74: BRAK | AF74: BRAK | AG74: BRAK | AH74: BRAK | AI74: BRAK | AJ74: BRAK | AK74: BRAK | AL74: BRAK | AM74: Górnik
A75: Bryłka węgla | B75: Węgiel w bryłkach. | C75: ITEM_CAT_NONE | D75: - | E75: Materials | F75: Materials | G75: AdminMaterials | H75: materials | I75: TRUE | J75: ITCR_SDRP_DROP_60 | K75: ITMI_GS_MAT_14 | L75: kohle_nugget.3ds | M75: 0.5 | N75: FALSE | O75: BRAK | P75: BRAK | Q75: BRAK | R75: BRAK | S75: BRAK | T75: BRAK | U75: BRAK | V75: BRAK | W75: BRAK | X75: BRAK | Y75: BRAK | Z75: BRAK | AA75: BRAK | AB75: BRAK | AC75: BRAK | AD75: BRAK | AE75: BRAK | AF75: BRAK | AG75: BRAK | AH75: BRAK | AI75: BRAK | AJ75: BRAK | AK75: BRAK | AL75: BRAK | AM75: Górnik
A76: Bryłka Kamienia | B76: Kamień w bryłkach. | C76: ITEM_CAT_NONE | D76: - | E76: Materials | F76: Materials | G76: AdminMaterials | H76: materials | I76: TRUE | J76: ITCR_SDRP_DROP_85 | K76: ITMI_GS_MAT_15 | L76: ITAT_STONEGOLEMHEART.3ds | M76: 0.5 | N76: FALSE | O76: BRAK | P76: BRAK | Q76: BRAK | R76: BRAK | S76: BRAK | T76: BRAK | U76: BRAK | V76: BRAK | W76: BRAK | X76: BRAK | Y76: BRAK | Z76: BRAK | AA76: BRAK | AB76: BRAK | AC76: BRAK | AD76: BRAK | AE76: BRAK | AF76: BRAK | AG76: BRAK | AH76: BRAK | AI76: BRAK | AJ76: BRAK | AK76: BRAK | AL76: BRAK | AM76: Górnik
A77: Bryłka soli | B77: Sól w bryłkach | C77: ITEM_CAT_NONE | D77: - | E77: Materials | F77: Materials | G77: AdminMaterials | H77: materials | I77: TRUE | J77: ITCR_SDRP_DROP_59 | K77: ITMI_GS_MAT_16 | L77: salz_nugget.3ds | M77: 0.5 | N77: FALSE | O77: BRAK | P77: BRAK | Q77: BRAK | R77: BRAK | S77: BRAK | T77: BRAK | U77: BRAK | V77: BRAK | W77: BRAK | X77: BRAK | Y77: BRAK | Z77: BRAK | AA77: BRAK | AB77: BRAK | AC77: BRAK | AD77: BRAK | AE77: BRAK | AF77: BRAK | AG77: BRAK | AH77: BRAK | AI77: BRAK | AJ77: BRAK | AK77: BRAK | AL77: BRAK | AM77: Górnik
A78: Kwarcyt | B78: Drobne ziarna piasku znajdują zastosowanie przy wytwarzania wyrobów w hucie. | C78: ITEM_CAT_NONE | D78: - | E78: Materials | F78: Materials | G78: AdminMaterials | H78: materials | I78: TRUE | J78: ItMi_Quartz | K78: ITMI_GS_MAT_17 | L78: ItMi_Quartz.3ds | M78: 0.5 | N78: FALSE | O78: BRAK | P78: BRAK | Q78: BRAK | R78: BRAK | S78: BRAK | T78: BRAK | U78: BRAK | V78: BRAK | W78: BRAK | X78: BRAK | Y78: BRAK | Z78: BRAK | AA78: BRAK | AB78: BRAK | AC78: BRAK | AD78: BRAK | AE78: BRAK | AF78: BRAK | AG78: BRAK | AH78: BRAK | AI78: BRAK | AJ78: BRAK | AK78: BRAK | AL78: BRAK | AM78: Górnik
A79: Samorodek złota | B79: Duża bryła złota. Można z niej wytworzyć wiele monet. | C79: ITEM_CAT_NONE | D79: - | E79: Materials | F79: Materials | G79: AdminMaterials | H79: materials | I79: TRUE | J79: ITMI_GOLDNUGGET_ADDON | K79: ITMI_GS_MAT_18 | L79: ItMi_GoldNugget_01.3ds | M79: 0.5 | N79: FALSE | O79: BRAK | P79: BRAK | Q79: BRAK | R79: BRAK | S79: BRAK | T79: BRAK | U79: BRAK | V79: BRAK | W79: BRAK | X79: BRAK | Y79: BRAK | Z79: BRAK | AA79: BRAK | AB79: BRAK | AC79: BRAK | AD79: BRAK | AE79: BRAK | AF79: BRAK | AG79: BRAK | AH79: BRAK | AI79: BRAK | AJ79: BRAK | AK79: BRAK | AL79: BRAK | AM79: Górnik
A80: Bryłka siarki | B80: Żółta bryłka, zapachem przypominająca odór zgniłych jaj. | C80: ITEM_CAT_NONE | D80: - | E80: Materials | F80: Materials | G80: AdminMaterials | H80: materials | I80: TRUE | J80: CRAFT_BRYLKA_SIARKI | K80: ITMI_GS_MAT_19 | L80: CRAFT_BRYLKA_SIARKI.3ds | M80: 0.5 | N80: FALSE | O80: BRAK | P80: BRAK | Q80: BRAK | R80: BRAK | S80: BRAK | T80: BRAK | U80: BRAK | V80: BRAK | W80: BRAK | X80: BRAK | Y80: BRAK | Z80: BRAK | AA80: BRAK | AB80: BRAK | AC80: BRAK | AD80: BRAK | AE80: BRAK | AF80: BRAK | AG80: BRAK | AH80: BRAK | AI80: BRAK | AJ80: BRAK | AK80: BRAK | AL80: BRAK | AM80: Górnik
A81: Bryłka żelaza | B81: Ruda żelaza w bryłkach. | C81: ITEM_CAT_NONE | D81: - | E81: Materials | F81: Materials | G81: AdminMaterials | H81: materials | I81: TRUE | J81: ITCR_SDRP_DROP_13 | K81: ITMI_GS_MAT_20 | L81: CRAFT_BRYLKA_ZELAZO.3ds | M81: 0.5 | N81: FALSE | O81: BRAK | P81: BRAK | Q81: BRAK | R81: BRAK | S81: BRAK | T81: BRAK | U81: BRAK | V81: BRAK | W81: BRAK | X81: BRAK | Y81: BRAK | Z81: BRAK | AA81: BRAK | AB81: BRAK | AC81: BRAK | AD81: BRAK | AE81: BRAK | AF81: BRAK | AG81: BRAK | AH81: BRAK | AI81: BRAK | AJ81: BRAK | AK81: BRAK | AL81: BRAK | AM81: Górnik
A82: Ametyst | B82: Składnik potrzebny do wykonania niektórych run i biżuterii | C82: ITEM_CAT_NONE | D82: - | E82: Materials | F82: Materials | G82: AdminMaterials | H82: materials | I82: TRUE | J82: AMETHYST_CRYSTAL | K82: ITMI_GS_MAT_21 | L82: AMETHYST_CRYSTAL.3ds | M82: 0.5 | N82: FALSE | O82: BRAK | P82: BRAK | Q82: BRAK | R82: BRAK | S82: BRAK | T82: BRAK | U82: BRAK | V82: BRAK | W82: BRAK | X82: BRAK | Y82: BRAK | Z82: BRAK | AA82: BRAK | AB82: BRAK | AC82: BRAK | AD82: BRAK | AE82: BRAK | AF82: BRAK | AG82: BRAK | AH82: BRAK | AI82: BRAK | AJ82: BRAK | AK82: BRAK | AL82: BRAK | AM82: Górnik
A83: Akwamaryn | B83: Składnik potrzebny do wykonania niektórych run i biżuterii | C83: ITEM_CAT_NONE | D83: - | E83: Materials | F83: Materials | G83: AdminMaterials | H83: materials | I83: TRUE | J83: AQUAMARIN_CRYSTAL | K83: ITMI_GS_MAT_22 | L83: AQUAMARIN_CRYSTAL.3ds | M83: 0.5 | N83: FALSE | O83: BRAK | P83: BRAK | Q83: BRAK | R83: BRAK | S83: BRAK | T83: BRAK | U83: BRAK | V83: BRAK | W83: BRAK | X83: BRAK | Y83: BRAK | Z83: BRAK | AA83: BRAK | AB83: BRAK | AC83: BRAK | AD83: BRAK | AE83: BRAK | AF83: BRAK | AG83: BRAK | AH83: BRAK | AI83: BRAK | AJ83: BRAK | AK83: BRAK | AL83: BRAK | AM83: Górnik
... A114: Deska z szlachetnego drewna | B114: Solidna deska | C114: ITEM_CAT_NONE | D114: - | E114: Materials | F114: Materials | G114: AdminMaterials | H114: materials | I114: TRUE | J114: deska3 | K114: ITMI_GS_MAT_50 | L114: deska3.3ds | M114: 1 | N114: FALSE | O114: BRAK | P114: BRAK | Q114: BRAK | R114: BRAK | S114: BRAK | T114: BRAK | U114: BRAK | V114: BRAK | W114: BRAK | X114: BRAK | Y114: BRAK | Z114: BRAK | AA114: BRAK | AB114: BRAK | AC114: BRAK | AD114: BRAK | AE114: BRAK | AF114: BRAK | AG114: BRAK | AH114: BRAK | AI114: BRAK | AJ114: BRAK | AK114: BRAK | AL114: BRAK | AM114: Drwal
A115: Chwast | B115: Gorzka roślina, wykorzystywana do tworzenia dań dla biedoty. | C115: ITEM_CAT_NONE | D115: - | E115: Materials | F115: Materials | G115: AdminMaterials | H115: materials | I115: TRUE | J115: ITPL_WEED | K115: ITMI_GS_MAT_51 | L115: ItPl_Weed.3ds | M115: 0.1 | N115: FALSE | O115: BRAK | P115: BRAK | Q115: BRAK | R115: BRAK | S115: BRAK | T115: BRAK | U115: BRAK | V115: BRAK | W115: BRAK | X115: BRAK | Y115: BRAK | Z115: BRAK | AA115: BRAK | AB115: BRAK | AC115: BRAK | AD115: BRAK | AE115: BRAK | AF115: BRAK | AG115: BRAK | AH115: BRAK | AI115: BRAK | AJ115: BRAK | AK115: BRAK | AL115: BRAK | AM115: Zbieracz | AN115: Rośliny
A116: Piekielnik | B116: Grzyb ma brunatny trzon, natomiast jego kapelusz jest barwy białej | C116: ITEM_CAT_NONE | D116: - | E116: Materials | F116: Materials | G116: AdminMaterials | H116: materials | I116: TRUE | J116: itpl_SDRP_herb_18 | K116: ITMI_GS_MAT_52 | L116: ItFo_Plants_mushroom_01.3ds | M116: 0.1 | N116: FALSE | O116: BRAK | P116: BRAK | Q116: BRAK | R116: BRAK | S116: BRAK | T116: BRAK | U116: BRAK | V116: BRAK | W116: BRAK | X116: BRAK | Y116: BRAK | Z116: BRAK | AA116: BRAK | AB116: BRAK | AC116: BRAK | AD116: BRAK | AE116: BRAK | AF116: BRAK | AG116: BRAK | AH116: BRAK | AI116: BRAK | AJ116: BRAK | AK116: BRAK | AL116: BRAK | AM116: Zbieracz | AN116: Rośliny
A117: Ciemny grzyb | B117: Mułowe grzyby są przepełnione magiczną energią. Za każdym razem, kiedy zjadasz taki grzyb, jej niewielka część odkłada się w twoim ciele | C117: ITEM_CAT_NONE | D117: - | E117: Materials | F117: Materials | G117: AdminMaterials | H117: materials | I117: TRUE | J117: ITPL_MUSHROOM_01 | K117: ITMI_GS_MAT_53 | L117: ItPl_Mushroom_01.3ds | M117: 0.1 | N117: FALSE | O117: BRAK | P117: BRAK | Q117: BRAK | R117: BRAK | S117: BRAK | T117: BRAK | U117: BRAK | V117: BRAK | W117: BRAK | X117: BRAK | Y117: BRAK | Z117: BRAK | AA117: BRAK | AB117: BRAK | AC117: BRAK | AD117: BRAK | AE117: BRAK | AF117: BRAK | AG117: BRAK | AH117: BRAK | AI117: BRAK | AJ117: BRAK | AK117: BRAK | AL117: BRAK | AM117: Zbieracz | AN117: Rośliny
A118: Bagienne ziele | B118: Po odpowiednim ususzeniu rośliny, może znaleźć swoje zastosowanie przy wypoczynku lub medytacji | C118: ITEM_CAT_NONE | D118: - | E118: Materials | F118: Materials | G118: AdminMaterials | H118: materials | I118: TRUE | J118: ITPL_WEED | K118: ITMI_GS_MAT_54 | L118: ItPl_Weed.3ds | M118: 0.1 | N118: FALSE | O118: BRAK | P118: BRAK | Q118: BRAK | R118: BRAK | S118: BRAK | T118: BRAK | U118: BRAK | V118: BRAK | W118: BRAK | X118: BRAK | Y118: BRAK | Z118: BRAK | AA118: BRAK | AB118: BRAK | AC118: BRAK | AD118: BRAK | AE118: BRAK | AF118: BRAK | AG118: BRAK | AH118: BRAK | AI118: BRAK | AJ118: BRAK | AK118: BRAK | AL118: BRAK | AM118: Zbieracz | AN118: Rośliny
A119: Rdest polny | B119: Rosną przeważnie w ciemnych, podmokłych i trudno dostępnych miejscach | C119: ITEM_CAT_NONE | D119: - | E119: Materials | F119: Materials | G119: AdminMaterials | H119: materials | I119: TRUE | J119: ITPL_TEMP_HERB | K119: ITMI_GS_MAT_55 | L119: ItPl_Temp_Herb.3ds | M119: 0.1 | N119: FALSE | O119: BRAK | P119: BRAK | Q119: BRAK | R119: BRAK | S119: BRAK | T119: BRAK | U119: BRAK | V119: BRAK | W119: BRAK | X119: BRAK | Y119: BRAK | Z119: BRAK | AA119: BRAK | AB119: BRAK | AC119: BRAK | AD119: BRAK | AE119: BRAK | AF119: BRAK | AG119: BRAK | AH119: BRAK | AI119: BRAK | AJ119: BRAK | AK119: BRAK | AL119: BRAK | AM119: Zbieracz | AN119: Rośliny
A120: Niebieski bez | B120: Ma zielone liście i niebieskie owoce | C120: ITEM_CAT_NONE | D120: - | E120: Materials | F120: Materials | G120: AdminMaterials | H120: materials | I120: TRUE | J120: ITPL_BLUEPLANT | K120: ITMI_GS_MAT_56 | L120: ItPl_Blueplant.3ds | M120: 0.1 | N120: FALSE | O120: BRAK | P120: BRAK | Q120: BRAK | R120: BRAK | S120: BRAK | T120: BRAK | U120: BRAK | V120: BRAK | W120: BRAK | X120: BRAK | Y120: BRAK | Z120: BRAK | AA120: BRAK | AB120: BRAK | AC120: BRAK | AD120: BRAK | AE120: BRAK | AF120: BRAK | AG120: BRAK | AH120: BRAK | AI120: BRAK | AJ120: BRAK | AK120: BRAK | AL120: BRAK | AM120: Zbieracz | AN120: Rośliny
A121: Roślina lecznicza | B121: Podstawowy skladnik potrzebny do warzenia podstawowych wywarów leczniczych | C121: ITEM_CAT_NONE | D121: - | E121: Materials | F121: Materials | G121: AdminMaterials | H121: materials | I121: TRUE | J121: itpl_SDRP_herb_09 | K121: ITMI_GS_MAT_57 | L121: ItFo_Plants_Herb_01.3ds | M121: 0.1 | N121: FALSE | O121: BRAK | P121: BRAK | Q121: BRAK | R121: BRAK | S121: BRAK | T121: BRAK | U121: BRAK | V121: BRAK | W121: BRAK | X121: BRAK | Y121: BRAK | Z121: BRAK | AA121: BRAK | AB121: BRAK | AC121: BRAK | AD121: BRAK | AE121: BRAK | AF121: BRAK | AG121: BRAK | AH121: BRAK | AI121: BRAK | AJ121: BRAK | AK121: BRAK | AL121: BRAK | AM121: Zbieracz | AN121: Rośliny
A122: Ognista pokrzywa | B122: Podstawowy skladnik potrzebny do warzenia podstawowych wywarów odnawiających mane | C122: ITEM_CAT_NONE | D122: - | E122: Materials | F122: Materials | G122: AdminMaterials | H122: materials | I122: TRUE | J122: ITPL_MANA_HERB_01 | K122: ITMI_GS_MAT_58 | L122: ItPl_Mana_Herb_01.3ds | M122: 0.1 | N122: FALSE | O122: BRAK | P122: BRAK | Q122: BRAK | R122: BRAK | S122: BRAK | T122: BRAK | U122: BRAK | V122: BRAK | W122: BRAK | X122: BRAK | Y122: BRAK | Z122: BRAK | AA122: BRAK | AB122: BRAK | AC122: BRAK | AD122: BRAK | AE122: BRAK | AF122: BRAK | AG122: BRAK | AH122: BRAK | AI122: BRAK | AJ122: BRAK | AK122: BRAK | AL122: BRAK | AM122: Zbieracz | AN122: Rośliny
A123: Ziele lecznicze | B123: Główny składnik ekstraktu leczniczego | C123: ITEM_CAT_NONE | D123: - | E123: Materials | F123: Materials | G123: AdminMaterials | H123: materials | I123: TRUE | J123: ITPL_HEALTH_HERB_02 | K123: ITMI_GS_MAT_59 | L123: ItPl_Health_Herb_02.3ds | M123: 0.1 | N123: FALSE | O123: BRAK | P123: BRAK | Q123: BRAK | R123: BRAK | S123: BRAK | T123: BRAK | U123: BRAK | V123: BRAK | W123: BRAK | X123: BRAK | Y123: BRAK | Z123: BRAK | AA123: BRAK | AB123: BRAK | AC123: BRAK | AD123: BRAK | AE123: BRAK | AF123: BRAK | AG123: BRAK | AH123: BRAK | AI123: BRAK | AJ123: BRAK | AK123: BRAK | AL123: BRAK | AM123: Zbieracz | AN123: Rośliny
A124: Ogniste ziele | B124: Główny składnik ekstraktu many | C124: ITEM_CAT_NONE | D124: - | E124: Materials | F124: Materials | G124: AdminMaterials | H124: materials | I124: TRUE | J124: ITPL_MANA_HERB_02 | K124: ITMI_GS_MAT_60 | L124: ItPl_Mana_Herb_02.3ds | M124: 0.1 | N124: FALSE | O124: BRAK | P124: BRAK | Q124: BRAK | R124: BRAK | S124: BRAK | T124: BRAK | U124: BRAK | V124: BRAK | W124: BRAK | X124: BRAK | Y124: BRAK | Z124: BRAK | AA124: BRAK | AB124: BRAK | AC124: BRAK | AD124: BRAK | AE124: BRAK | AF124: BRAK | AG124: BRAK | AH124: BRAK | AI124: BRAK | AJ124: BRAK | AK124: BRAK | AL124: BRAK | AM124: Zbieracz | AN124: Rośliny
A125: Zębate ziele | B125: Jest składnikiem alchemicznym służącym do wytworzenia mikstury szybkości | C125: ITEM_CAT_NONE | D125: - | E125: Materials | F125: Materials | G125: AdminMaterials | H125: materials | I125: TRUE | J125: ITPL_SPEED_HERB_01 | K125: ITMI_GS_MAT_61 | L125: ItPl_Speed_Herb_01.3ds | M125: 0.1 | N125: FALSE | O125: BRAK | P125: BRAK | Q125: BRAK | R125: BRAK | S125: BRAK | T125: BRAK | U125: BRAK | V125: BRAK | W125: BRAK | X125: BRAK | Y125: BRAK | Z125: BRAK | AA125: BRAK | AB125: BRAK | AC125: BRAK | AD125: BRAK | AE125: BRAK | AF125: BRAK | AG125: BRAK | AH125: BRAK | AI125: BRAK | AJ125: BRAK | AK125: BRAK | AL125: BRAK | AM125: Zbieracz | AN125: Rośliny
A126: Szczaw królewski | B126: Bardzo rzadka roślina poszukiwana przez wielu alchemików | C126: ITEM_CAT_NONE | D126: - | E126: Materials | F126: Materials | G126: AdminMaterials | H126: materials | I126: TRUE | J126: ITPL_PERM_HERB | K126: ITMI_GS_MAT_62 | L126: ItPl_Perm_Herb.3ds | M126: 0.1 | N126: FALSE | O126: BRAK | P126: BRAK | Q126: BRAK | R126: BRAK | S126: BRAK | T126: BRAK | U126: BRAK | V126: BRAK | W126: BRAK | X126: BRAK | Y126: BRAK | Z126: BRAK | AA126: BRAK | AB126: BRAK | AC126: BRAK | AD126: BRAK | AE126: BRAK | AF126: BRAK | AG126: BRAK | AH126: BRAK | AI126: BRAK | AJ126: BRAK | AK126: BRAK | AL126: BRAK | AM126: Zbieracz | AN126: Rośliny
... A128: Ognisty korzeń | B128: Roślina będąca składnikiem do najsilniejszych mikstur many | C128: ITEM_CAT_NONE | D128: - | E128: Materials | F128: Materials | G128: AdminMaterials | H128: materials | I128: TRUE | J128: ITPL_MANA_HERB_03 | K128: ITMI_GS_MAT_64 | L128: ItPl_Mana_Herb_03.3ds | M128: 0.1 | N128: FALSE | O128: BRAK | P128: BRAK | Q128: BRAK | R128: BRAK | S128: BRAK | T128: BRAK | U128: BRAK | V128: BRAK | W128: BRAK | X128: BRAK | Y128: BRAK | Z128: BRAK | AA128: BRAK | AB128: BRAK | AC128: BRAK | AD128: BRAK | AE128: BRAK | AF128: BRAK | AG128: BRAK | AH128: BRAK | AI128: BRAK | AJ128: BRAK | AK128: BRAK | AL128: BRAK | AM128: Zbieracz | AN128: Rośliny
A129: Polna jagoda | B129: Czerwone owoce rosnące na krzakach | C129: ITEM_CAT_FOOD | D129: - | E129: Consumable | F129: Food | G129: AdminFood | H129: consumable | I129: TRUE | J129: ITPL_FORESTBERRY | K129: ITFO_GS_53 | L129: ItPl_Forestberry.3ds | M129: 0.1 | N129: FALSE | O129: 1 | P129: 1 | Q129: 0 | R129: 0 | S129: =O129*P129 -> 1 | T129: =O129*Q129 -> 0 | U129: =O129*R129 -> 0 | V129: BRAK | W129: BRAK | X129: BRAK | Y129: BRAK | Z129: BRAK | AA129: BRAK | AB129: BRAK | AC129: BRAK | AD129: BRAK | AE129: BRAK | AF129: BRAK | AG129: BRAK | AH129: BRAK | AI129: BRAK | AJ129: BRAK | AK129: BRAK | AL129: T1 | AM129: Zbieracz | AN129: Rośliny
A130: Leśna jagoda | B130: Owoc spory jak palec trolla, wykorzystywana jako baza alkoholi | C130: ITEM_CAT_FOOD | D130: - | E130: Consumable | F130: Food | G130: AdminFood | H130: consumable | I130: TRUE | J130: ITPL_DEX_HERB_01 | K130: ITFO_GS_54 | L130: ItPl_Dex_Herb_01.3ds | M130: 0.1 | N130: FALSE | O130: 1 | P130: 2 | Q130: 0 | R130: 0 | S130: =O130*P130 -> 2 | T130: =O130*Q130 -> 0 | U130: =O130*R130 -> 0 | V130: BRAK | W130: BRAK | X130: BRAK | Y130: BRAK | Z130: BRAK | AA130: BRAK | AB130: BRAK | AC130: BRAK | AD130: BRAK | AE130: BRAK | AF130: BRAK | AG130: BRAK | AH130: BRAK | AI130: BRAK | AJ130: BRAK | AK130: BRAK | AL130: T2 | AM130: Zbieracz | AN130: Rośliny
A131: Jabłko | B131: Owoc o dużej liczbie zastosowań. Można robić z niego alkohole, ciasta jest również wykorzysytwany do tworzenia cukru. | C131: ITEM_CAT_FOOD | D131: - | E131: Consumable | F131: Food | G131: AdminFood | H131: consumable | I131: TRUE | J131: ITFO_APPLE | K131: ITFO_GS_55 | L131: ItFo_Apple.3ds | M131: 0.1 | N131: FALSE | O131: 1 | P131: 1 | Q131: 0 | R131: 0 | S131: =O131*P131 -> 1 | T131: =O131*Q131 -> 0 | U131: =O131*R131 -> 0 | V131: BRAK | W131: BRAK | X131: BRAK | Y131: BRAK | Z131: BRAK | AA131: BRAK | AB131: BRAK | AC131: BRAK | AD131: BRAK | AE131: BRAK | AF131: BRAK | AG131: BRAK | AH131: BRAK | AI131: BRAK | AJ131: BRAK | AK131: BRAK | AL131: T1 | AM131: Zbieracz | AN131: Dary lasu
A132: Kora drzewna | B132: Kora używana, do tworzenia papirusu, a także najeefektywniejszy element do tworzenie odwarów garbarskich. | C132: ITEM_CAT_NONE | D132: - | E132: Materials | F132: Materials | G132: AdminMaterials | H132: materials | I132: TRUE | J132: kora | K132: ITMI_GS_MAT_65 | L132: kora.3ds | M132: 0.2 | N132: FALSE | O132: BRAK | P132: BRAK | Q132: BRAK | R132: BRAK | S132: BRAK | T132: BRAK | U132: BRAK | V132: BRAK | W132: BRAK | X132: BRAK | Y132: BRAK | Z132: BRAK | AA132: BRAK | AB132: BRAK | AC132: BRAK | AD132: BRAK | AE132: BRAK | AF132: BRAK | AG132: BRAK | AH132: BRAK | AI132: BRAK | AJ132: BRAK | AK132: BRAK | AL132: T2 | AM132: Zbieracz | AN132: Dary lasu
A133: Pajęczyna | B133: Pajęczyna wytwarzana przez ogromne pająki. Cechuje je wyjątkowa trwałość | C133: ITEM_CAT_NONE | D133: - | E133: Materials | F133: Materials | G133: AdminMaterials | H133: materials | I133: TRUE | J133: ITCR_SDRP_DROP_86 | K133: ITMI_GS_MAT_66 | L133: HK_ITEM_PAJECZYNA.3ds | M133: 0.1 | N133: FALSE | O133: BRAK | P133: BRAK | Q133: BRAK | R133: BRAK | S133: BRAK | T133: BRAK | U133: BRAK | V133: BRAK | W133: BRAK | X133: BRAK | Y133: BRAK | Z133: BRAK | AA133: BRAK | AB133: BRAK | AC133: BRAK | AD133: BRAK | AE133: BRAK | AF133: BRAK | AG133: BRAK | AH133: BRAK | AI133: BRAK | AJ133: BRAK | AK133: BRAK | AL133: T1 | AM133: Zbieracz | AN133: Dary lasu
A134: Wosk pszczeli | B134: Wosk pszczeli służacy do impregnowania poszczególnych gatunków skór | C134: ITEM_CAT_NONE | D134: - | E134: Materials | F134: Materials | G134: AdminMaterials | H134: materials | I134: TRUE | J134: ITUS_SDRP_TOOL_34 | K134: ITMI_GS_MAT_67 | L134: ItMi_Bottle_Empty.3ds | M134: 0.2 | N134: FALSE | O134: BRAK | P134: BRAK | Q134: BRAK | R134: BRAK | S134: BRAK | T134: BRAK | U134: BRAK | V134: BRAK | W134: BRAK | X134: BRAK | Y134: BRAK | Z134: BRAK | AA134: BRAK | AB134: BRAK | AC134: BRAK | AD134: BRAK | AE134: BRAK | AF134: BRAK | AG134: BRAK | AH134: BRAK | AI134: BRAK | AJ134: BRAK | AK134: BRAK | AL134: T3 | AM134: Zbieracz | AN134: Dary lasu
A135: Miód | B135: Słodki przysmak niedźwiedzi, wykorzystywany do wykwintych dań, które mają wzbogacić jego smak, a także przedłużyć jego trwałość. | C135: ITEM_CAT_FOOD | D135: - | E135: Consumable | F135: Food | G135: AdminFood | H135: consumable | I135: TRUE | J135: ITFO_HONEY | K135: ITFO_GS_56 | L135: ItFo_Honey.3ds | M135: 0.2 | N135: FALSE | O135: 2 | P135: 2 | Q135: 1.5 | R135: 0 | S135: =O135*P135 -> 4 | T135: =O135*Q135 -> 3 | U135: =O135*R135 -> 0 | V135: BRAK | W135: BRAK | X135: BRAK | Y135: BRAK | Z135: BRAK | AA135: BRAK | AB135: BRAK | AC135: BRAK | AD135: BRAK | AE135: BRAK | AF135: BRAK | AG135: BRAK | AH135: BRAK | AI135: BRAK | AJ135: BRAK | AK135: BRAK | AL135: T3 | AM135: Zbieracz | AN135: Dary lasu
A136: Ryba | B136: Ryba gotowa do wypatroszenia, ponoć można ją upiec, przy grillu. | C136: ITEM_CAT_NONE | D136: - | E136: Materials | F136: Materials | G136: AdminMaterials | H136: materials | I136: TRUE | J136: ITFO_FISH | K136: ITMI_GS_MAT_68 | L136: ItFo_Fish.3ds | M136: 0.3 | N136: FALSE | O136: BRAK | P136: BRAK | Q136: BRAK | R136: BRAK | S136: BRAK | T136: BRAK | U136: BRAK | V136: BRAK | W136: BRAK | X136: BRAK | Y136: BRAK | Z136: BRAK | AA136: BRAK | AB136: BRAK | AC136: BRAK | AD136: BRAK | AE136: 21600 | AF136: BRAK | AG136: BRAK | AH136: BRAK | AI136: BRAK | AJ136: BRAK | AK136: BRAK | AL136: T0 | AM136: Zbieracz | AN136: Owoce morza
A137: Wypatroszona ryba | B137: Płat ryby gotowy do smażenia. | C137: ITEM_CAT_NONE | D137: - | E137: Materials | F137: Materials | G137: AdminMaterials | H137: materials | I137: TRUE | J137: itfo_SDRP_food_33 | K137: ITMI_GS_MAT_69 | L137: SDRP_FISH_04.3ds | M137: 0.4 | N137: FALSE | O137: BRAK | P137: BRAK | Q137: BRAK | R137: BRAK | S137: BRAK | T137: BRAK | U137: BRAK | V137: BRAK | W137: BRAK | X137: BRAK | Y137: BRAK | Z137: BRAK | AA137: BRAK | AB137: BRAK | AC137: BRAK | AD137: BRAK | AE137: 21600 | AF137: BRAK | AG137: BRAK | AH137: BRAK | AI137: BRAK | AJ137: BRAK | AK137: BRAK | AL137: T1 | AM137: Zbieracz | AN137: Owoce morza
A138: Perła | B138: Perła to klejnot morski i piękna ozdoba. Jest dość rzadka. | C138: ITEM_CAT_NONE | D138: - | E138: Materials | F138: Materials | G138: AdminMaterials | H138: materials | I138: TRUE | J138: ITMI_ADDON_WHITEPEARL | K138: ITMI_GS_MAT_70 | L138: ItMi_WhitePearl_01.3ds | M138: 0.1 | N138: FALSE | O138: BRAK | P138: BRAK | Q138: BRAK | R138: BRAK | S138: BRAK | T138: BRAK | U138: BRAK | V138: BRAK | W138: BRAK | X138: BRAK | Y138: BRAK | Z138: BRAK | AA138: BRAK | AB138: BRAK | AC138: BRAK | AD138: BRAK | AE138: BRAK | AF138: BRAK | AG138: BRAK | AH138: BRAK | AI138: BRAK | AJ138: BRAK | AK138: BRAK | AL138: T2 | AM138: Zbieracz | AN138: Owoce morza
A139: Ostryga | B139: Wyglądem przypomina owadzie mięso, ale jest bardziej odżywcza. | C139: ITEM_CAT_FOOD | D139: - | E139: Consumable | F139: Food | G139: AdminFood | H139: consumable | I139: TRUE | J139: ItFo_Addon_Shellflesh | K139: ITFO_GS_57 | L139: ItAt_Meatbugflesh.3ds | M139: 0.1 | N139: FALSE | O139: 1 | P139: 2 | Q139: 0 | R139: 0 | S139: =O139*P139 -> 2 | T139: =O139*Q139 -> 0 | U139: =O139*R139 -> 0 | V139: BRAK | W139: BRAK | X139: BRAK | Y139: BRAK | Z139: BRAK | AA139: BRAK | AB139: BRAK | AC139: BRAK | AD139: BRAK | AE139: BRAK | AF139: BRAK | AG139: BRAK | AH139: BRAK | AI139: BRAK | AJ139: BRAK | AK139: BRAK | AL139: T2 | AM139: Zbieracz | AN139: Owoce morza
A140: Czarna perła | B140: Niezwykle rzadka odmiana perły. Dla kolekcjonerów stanowi nielada gratkę. | C140: ITEM_CAT_NONE | D140: - | E140: Materials | F140: Materials | G140: AdminMaterials | H140: materials | I140: TRUE | J140: ItMi_DarkPearl | K140: ITMI_GS_MAT_71 | L140: ItMi_DarkPearl.3ds | M140: 0.1 | N140: FALSE | O140: BRAK | P140: BRAK | Q140: BRAK | R140: BRAK | S140: BRAK | T140: BRAK | U140: BRAK | V140: BRAK | W140: BRAK | X140: BRAK | Y140: BRAK | Z140: BRAK | AA140: BRAK | AB140: BRAK | AC140: BRAK | AD140: BRAK | AE140: BRAK | AF140: BRAK | AG140: BRAK | AH140: BRAK | AI140: BRAK | AJ140: BRAK | AK140: BRAK | AL140: T3 | AM140: Zbieracz | AN140: Owoce morza
A141: Spirytus | B141: Baza mikstur i alkoholi | C141: ITEM_CAT_FOOD | D141: ITEM_FLAG_DRINK | E141: Consumable | F141: Food | G141: AdminFood | H141: consumable | I141: TRUE | J141: ITFO_SDRP_ALH_01 | K141: ITFO_GS_58 | L141: ITFO_ALCH_NEW.3ds | M141: 0.2 | N141: FALSE | O141: 2 | P141: 0 | Q141: -2.5 | R141: 0 | S141: =O141*P141 -> 0 | T141: =O141*Q141 -> -5 | U141: =O141*R141 -> 0 | V141: BRAK | W141: BRAK | X141: BRAK | Y141: BRAK | Z141: BRAK | AA141: BRAK | AB141: BRAK | AC141: BRAK | AD141: BRAK | AE141: 32400 | AF141: BRAK | AG141: BRAK | AH141: BRAK | AI141: BRAK | AJ141: BRAK | AK141: BRAK | AL141: T0 | AM141: Alchemik | AN141: Alkohole
A142: Pieprz | B142: Drobna przyprawa, która daje wielki smak! | C142: ITEM_CAT_NONE | D142: - | E142: Materials | F142: Materials | G142: AdminMaterials | H142: materials | I142: TRUE | J142: ITFO_ADDON_PFEFFER_01 | K142: ITMI_GS_MAT_72 | L142: ItMi_Pocket.3ds | M142: 0.2 | N142: FALSE | O142: BRAK | P142: BRAK | Q142: BRAK | R142: BRAK | S142: BRAK | T142: BRAK | U142: BRAK | V142: BRAK | W142: BRAK | X142: BRAK | Y142: BRAK | Z142: BRAK | AA142: BRAK | AB142: BRAK | AC142: BRAK | AD142: BRAK | AE142: BRAK | AF142: BRAK | AG142: BRAK | AH142: BRAK | AI142: BRAK | AJ142: BRAK | AK142: BRAK | AL142: T0 | AM142: Alchemik | AN142: Alkohole
A143: Cukier | B143: Słodycze bez tego by wiele straciły. | C143: ITEM_CAT_NONE | D143: - | E143: Materials | F143: Materials | G143: AdminMaterials | H143: materials | I143: TRUE | J143: ITCR_SDRP_INGR_24 | K143: ITMI_GS_MAT_73 | L143: ItMi_Alchemy_Salt_01.3ds | M143: 0.2 | N143: FALSE | O143: BRAK | P143: BRAK | Q143: BRAK | R143: BRAK | S143: BRAK | T143: BRAK | U143: BRAK | V143: BRAK | W143: BRAK | X143: BRAK | Y143: BRAK | Z143: BRAK | AA143: BRAK | AB143: BRAK | AC143: BRAK | AD143: BRAK | AE143: BRAK | AF143: BRAK | AG143: BRAK | AH143: BRAK | AI143: BRAK | AJ143: BRAK | AK143: BRAK | AL143: T0 | AM143: Alchemik | AN143: Alkohole
A144: Drożdze | B144: Mieszanka wody z mąką. | C144: ITEM_CAT_NONE | D144: - | E144: Materials | F144: Materials | G144: AdminMaterials | H144: materials | I144: TRUE | J144: ITCR_SDRP_DROP_75 | K144: ITMI_GS_MAT_74 | L144: ItMi_Alchemy_Moleratlubric_01.3ds | M144: 0.2 | N144: FALSE | O144: BRAK | P144: BRAK | Q144: BRAK | R144: BRAK | S144: BRAK | T144: BRAK | U144: BRAK | V144: BRAK | W144: BRAK | X144: BRAK | Y144: BRAK | Z144: BRAK | AA144: BRAK | AB144: BRAK | AC144: BRAK | AD144: BRAK | AE144: BRAK | AF144: BRAK | AG144: BRAK | AH144: BRAK | AI144: BRAK | AJ144: BRAK | AK144: BRAK | AL144: T1 | AM144: Alchemik | AN144: Alkohole
A145: Piwo portowe | B145: Prawdziwy napój portowca. | C145: ITEM_CAT_FOOD | D145: ITEM_FLAG_DRINK | E145: Consumable | F145: Food | G145: AdminFood | H145: consumable | I145: TRUE | J145: ITFO_SDRP_KM_57 | K145: ITFO_GS_59 | L145: ItFo_Lakomy_Beer_01.3ds | M145: 0.2 | N145: FALSE | O145: 1 | P145: 5 | Q145: 1 | R145: 0 | S145: =O145*P145 -> 5 | T145: =O145*Q145 -> 1 | U145: =O145*R145 -> 0 | V145: BRAK | W145: BRAK | X145: BRAK | Y145: BRAK | Z145: BRAK | AA145: BRAK | AB145: BRAK | AC145: BRAK | AD145: BRAK | AE145: 32400 | AF145: BRAK | AG145: BRAK | AH145: BRAK | AI145: BRAK | AJ145: BRAK | AK145: BRAK | AL145: T1 | AM145: Alchemik | AN145: Alkohole
A146: Jabol | B146: Przysmak okolicznych wsi. | C146: ITEM_CAT_FOOD | D146: ITEM_FLAG_DRINK | E146: Consumable | F146: Food | G146: AdminFood | H146: consumable | I146: TRUE | J146: ITFO_SDRP_ALH_03 | K146: ITFO_GS_60 | L146: APFELSAFT.3ds | M146: 0.2 | N146: FALSE | O146: 3 | P146: 4 | Q146: 1 | R146: 0 | S146: =O146*P146 -> 12 | T146: =O146*Q146 -> 3 | U146: =O146*R146 -> 0 | V146: BRAK | W146: BRAK | X146: BRAK | Y146: BRAK | Z146: BRAK | AA146: BRAK | AB146: BRAK | AC146: BRAK | AD146: BRAK | AE146: 32400 | AF146: BRAK | AG146: BRAK | AH146: BRAK | AI146: BRAK | AJ146: BRAK | AK146: BRAK | AL146: T1 | AM146: Alchemik | AN146: Alkohole
A147: Nalewka Jagodowa | B147: Słodki alkohol o rubinowej barwie. | C147: ITEM_CAT_FOOD | D147: ITEM_FLAG_DRINK | E147: Consumable | F147: Food | G147: AdminFood | H147: consumable | I147: TRUE | J147: ITFO_SDRP_ALH_06 | K147: ITFO_GS_61 | L147: BEERENLIKOER.3ds | M147: 0.2 | N147: FALSE | O147: 3 | P147: 6 | Q147: 1 | R147: 0 | S147: =O147*P147 -> 18 | T147: =O147*Q147 -> 3 | U147: =O147*R147 -> 0 | V147: BRAK | W147: BRAK | X147: BRAK | Y147: BRAK | Z147: BRAK | AA147: BRAK | AB147: BRAK | AC147: BRAK | AD147: BRAK | AE147: 32400 | AF147: BRAK | AG147: BRAK | AH147: BRAK | AI147: BRAK | AJ147: BRAK | AK147: BRAK | AL147: T2 | AM147: Alchemik | AN147: Alkohole
A148: Piwo pszeniczne | B148: Podawane w każdej myrtańskiej karczmie. | C148: ITEM_CAT_FOOD | D148: ITEM_FLAG_DRINK | E148: Consumable | F148: Food | G148: AdminFood | H148: consumable | I148: TRUE | J148: ITFO_SDRP_KM_14 | K148: ITFO_GS_62 | L148: KM_vob_darkbeer.3ds | M148: 0.2 | N148: FALSE | O148: 2 | P148: 5 | Q148: 1 | R148: 0 | S148: =O148*P148 -> 10 | T148: =O148*Q148 -> 2 | U148: =O148*R148 -> 0 | V148: BRAK | W148: BRAK | X148: BRAK | Y148: BRAK | Z148: BRAK | AA148: BRAK | AB148: BRAK | AC148: BRAK | AD148: BRAK | AE148: 32400 | AF148: BRAK | AG148: BRAK | AH148: BRAK | AI148: BRAK | AJ148: BRAK | AK148: BRAK | AL148: T2 | AM148: Alchemik | AN148: Alkohole
A149: Wino | B149: Z delikatnym smakiem, stworzone z myślą o wysublinowanym smaku | C149: ITEM_CAT_FOOD | D149: ITEM_FLAG_DRINK | E149: Consumable | F149: Food | G149: AdminFood | H149: consumable | I149: TRUE | J149: ITFO_WINE | K149: ITFO_GS_63 | L149: ItFo_Wine.3ds | M149: 0.2 | N149: FALSE | O149: 4 | P149: 4 | Q149: 1 | R149: 0 | S149: =O149*P149 -> 16 | T149: =O149*Q149 -> 4 | U149: =O149*R149 -> 0 | V149: BRAK | W149: BRAK | X149: BRAK | Y149: BRAK | Z149: BRAK | AA149: BRAK | AB149: BRAK | AC149: BRAK | AD149: BRAK | AE149: 32400 | AF149: BRAK | AG149: BRAK | AH149: BRAK | AI149: BRAK | AJ149: BRAK | AK149: BRAK | AL149: T2 | AM149: Alchemik | AN149: Alkohole
A150: Wóda Ziołowa | B150: Alkohol powstały wyłącznie z fermentacji ziół. | C150: ITEM_CAT_FOOD | D150: ITEM_FLAG_DRINK | E150: Consumable | F150: Food | G150: AdminFood | H150: consumable | I150: TRUE | J150: ITFO_SDRP_KM_59 | K150: ITFO_GS_64 | L150: KM_new_bottle_02.3ds | M150: 0.2 | N150: FALSE | O150: 2 | P150: 12.5 | Q150: 2.5 | R150: 0 | S150: =O150*P150 -> 25 | T150: =O150*Q150 -> 5 | U150: =O150*R150 -> 0 | V150: BRAK | W150: BRAK | X150: BRAK | Y150: BRAK | Z150: BRAK | AA150: BRAK | AB150: BRAK | AC150: BRAK | AD150: BRAK | AE150: 32400 | AF150: BRAK | AG150: BRAK | AH150: BRAK | AI150: BRAK | AJ150: BRAK | AK150: BRAK | AL150: T3 | AM150: Alchemik | AN150: Alkohole
A151: Piwo Miodowe | B151: Specjalne piwo z dodatkiem miodu. | C151: ITEM_CAT_FOOD | D151: ITEM_FLAG_DRINK | E151: Consumable | F151: Food | G151: AdminFood | H151: consumable | I151: TRUE | J151: ITFO_SDRP_KM_08 | K151: ITFO_GS_65 | L151: KM_new_bottle_09.3ds | M151: 0.2 | N151: FALSE | O151: 2 | P151: 10 | Q151: 1 | R151: 0 | S151: =O151*P151 -> 20 | T151: =O151*Q151 -> 2 | U151: =O151*R151 -> 0 | V151: BRAK | W151: BRAK | X151: BRAK | Y151: BRAK | Z151: BRAK | AA151: BRAK | AB151: BRAK | AC151: BRAK | AD151: BRAK | AE151: 32400 | AF151: BRAK | AG151: BRAK | AH151: BRAK | AI151: BRAK | AJ151: BRAK | AK151: BRAK | AL151: T3 | AM151: Alchemik | AN151: Alkohole
A152: Gin | B152: Bardzo popularny alkohol na kontynencie. | C152: ITEM_CAT_FOOD | D152: ITEM_FLAG_DRINK | E152: Consumable | F152: Food | G152: AdminFood | H152: consumable | I152: TRUE | J152: ITFO_SDRP_ALH_13 | K152: ITFO_GS_66 | L152: TRAUBENSAFT.3ds | M152: 0.2 | N152: FALSE | O152: 5 | P152: 7 | Q152: 1 | R152: 0 | S152: =O152*P152 -> 35 | T152: =O152*Q152 -> 5 | U152: =O152*R152 -> 0 | V152: BRAK | W152: BRAK | X152: BRAK | Y152: BRAK | Z152: BRAK | AA152: BRAK | AB152: BRAK | AC152: BRAK | AD152: BRAK | AE152: 32400 | AF152: BRAK | AG152: BRAK | AH152: BRAK | AI152: BRAK | AJ152: BRAK | AK152: BRAK | AL152: T4 | AM152: Alchemik | AN152: Alkohole
A153: Rum | B153: Mocny i słodki napój alkoholowy | C153: ITEM_CAT_FOOD | D153: ITEM_FLAG_DRINK | E153: Consumable | F153: Food | G153: AdminFood | H153: consumable | I153: TRUE | J153: ITFO_ADDON_RUM | K153: ITFO_GS_67 | L153: ItMi_Rum_02.3ds | M153: 0.2 | N153: FALSE | O153: 2 | P153: 12.5 | Q153: 3 | R153: 0 | S153: =O153*P153 -> 25 | T153: =O153*Q153 -> 6 | U153: =O153*R153 -> 0 | V153: BRAK | W153: BRAK | X153: BRAK | Y153: BRAK | Z153: BRAK | AA153: BRAK | AB153: BRAK | AC153: BRAK | AD153: BRAK | AE153: 32400 | AF153: BRAK | AG153: BRAK | AH153: BRAK | AI153: BRAK | AJ153: BRAK | AK153: BRAK | AL153: T4 | AM153: Alchemik | AN153: Alkohole
A154: Szybki Śledź | B154: Niebezpieczny i tajemniczy zabójca, który działa szybko i bezlitośnie. | C154: ITEM_CAT_FOOD | D154: ITEM_FLAG_DRINK | E154: Consumable | F154: Food | G154: AdminFood | H154: consumable | I154: TRUE | J154: ITFO_ADDON_SCHNELLERHERING | K154: ITFO_GS_68 | L154: ItMi_Rum_01.3ds | M154: 0.2 | N154: FALSE | O154: 4 | P154: 10 | Q154: 3 | R154: 2.5 | S154: =O154*P154 -> 40 | T154: =O154*Q154 -> 12 | U154: =O154*R154 -> 10 | V154: BRAK | W154: BRAK | X154: BRAK | Y154: BRAK | Z154: BRAK | AA154: BRAK | AB154: BRAK | AC154: BRAK | AD154: BRAK | AE154: 32400 | AF154: BRAK | AG154: BRAK | AH154: BRAK | AI154: BRAK | AJ154: BRAK | AK154: BRAK | AL154: T5 | AM154: Alchemik | AN154: Alkohole
A155: Młot Lou | B155: Potężna trunek, która może zmiażdżyć wszystko na swojej drodze | C155: ITEM_CAT_FOOD | D155: ITEM_FLAG_DRINK | E155: Consumable | F155: Food | G155: AdminFood | H155: consumable | I155: TRUE | J155: ITFO_ADDON_SCHNELLERHERING | K155: ITFO_GS_69 | L155: ItMi_Rum_01.3ds | M155: 0.2 | N155: FALSE | O155: 2 | P155: 20 | Q155: 6 | R155: 5 | S155: =O155*P155 -> 40 | T155: =O155*Q155 -> 12 | U155: =O155*R155 -> 10 | V155: BRAK | W155: BRAK | X155: BRAK | Y155: BRAK | Z155: BRAK | AA155: BRAK | AB155: BRAK | AC155: BRAK | AD155: BRAK | AE155: 32400 | AF155: BRAK | AG155: BRAK | AH155: BRAK | AI155: BRAK | AJ155: BRAK | AK155: BRAK | AL155: T5 | AM155: Alchemik | AN155: Alkohole
A156: Skręt z bagiennego ziela | B156: Palenie łodyg bagiennego ziela to najbardziej popularna forma zażywania narkotyku. Ze względu na ich właściwości halucynogenne i relaksujące są one zakazane. | C156: ITEM_CAT_POTION | D156: ? | E156: Consumable | F156: Food | G156: AdminFood | H156: consumable | I156: TRUE | J156: ITMI_JOINT | K156: ITPO_GS_01 | L156: ItMi_Joint_US.3ds | M156: 0.05 | N156: FALSE | O156: 1 | P156: 0 | Q156: 0 | R156: 15 | S156: =O156*P156 -> 0 | T156: =O156*Q156 -> 0 | U156: =O156*R156 -> 15 | V156: BRAK | W156: BRAK | X156: BRAK | Y156: BRAK | Z156: BRAK | AA156: BRAK | AB156: BRAK | AC156: BRAK | AD156: BRAK | AE156: BRAK | AF156: BRAK | AG156: BRAK | AH156: BRAK | AI156: BRAK | AJ156: BRAK | AK156: BRAK | AL156: T1 | AM156: Alchemik | AN156: Alchemia
A157: Skręt zza uchem | B157: Skręt zza uchem | C157: ITEM_CAT_ACSR1 | D157: - | E157: AccessorySlot1 | F157: Accessory | G157: AdminAccessory | H157: acsr1 | I157: FALSE | J157: ITUS_SDRP_ACS_17 | K157: ITAC_GS_ACSR1_01 | L157: STATIC_joint_zauchem.3ds | M157: 0.05 | N157: FALSE | O157: BRAK | P157: BRAK | Q157: BRAK | R157: BRAK | S157: BRAK | T157: BRAK | U157: BRAK | V157: BRAK | W157: BRAK | X157: BRAK | Y157: BRAK | Z157: BRAK | AA157: BRAK | AB157: BRAK | AC157: BRAK | AD157: BRAK | AE157: BRAK | AF157: BRAK | AG157: BRAK | AH157: BRAK | AI157: BRAK | AJ157: BRAK | AK157: BRAK | AL157: T1 | AM157: Alchemik | AN157: Alchemia
...

Sheet All instancje z modelami saga 3
A1: Instancja | B1: Model (visual) | C1: Visual Change | D1: Nazwa (name)
A2: itam_addon_franco | B2: ItAm_Hp_01.3ds
A3: itam_addon_health | B3: ItAm_Hp_01.3ds
A4: itri_addon_health_01 | B4: ItRi_Prot_Total_01.3ds
A5: itri_addon_health_02 | B5: ItRi_Prot_Total_01.3ds
A6: itam_addon_mana | B6: ItAm_Hp_01.3ds
A7: itri_addon_mana_01 | B7: ItRi_Prot_Total_01.3ds
A8: itri_addon_mana_02 | B8: ItRi_Prot_Total_01.3ds
A9: itam_addon_str | B9: ItAm_Hp_01.3ds
A10: itri_addon_str_01 | B10: ItRi_Prot_Total_02.3ds
A11: itri_addon_str_02 | B11: ItRi_Prot_Total_02.3ds
A12: itar_pir_l_addon | B12: ItAr_PIR_L_ADDON.3ds | C12: Armor_Pir_L_Addon.ASC | D12: Piratenkleidung
A13: itar_pir_m_addon | B13: ItAr_PIR_M_ADDON.3ds | C13: Armor_PIR_M_ADDON.asc | D13: Piratenrüstung
A14: itar_pir_h_addon | B14: ItAr_PIR_H_ADDON.3ds | C14: Armor_PIR_H_ADDON.asc | D14: Kapitäns Kleidung
A15: itar_thorus_addon | B15: ItAr_Thorus_ADDON.3ds | C15: Armor_Thorus_ADDON.asc | D15: Schwere Gardistenrüstung
A16: itar_raven_addon | B16: ItAr_Raven_ADDON.3ds | C16: Armor_Raven_ADDON.asc | D16: Ravens Rüstung
A17: itar_orebaron_addon | B17: ItAr_CHAOS_ADDON.3ds | C17: Armor_CHAOS_ADDON.asc | D17: Erzbaronrüstung
A18: itar_ranger_addon | B18: ItAr_Ranger_ADDON.3ds | C18: Armor_Ranger_ADDON.asc | D18: Rüstung des 'Rings des Wassers'
A19: itar_fake_ranger | B19: ItAr_Ranger_ADDON.3ds | C19: Armor_Ranger_ADDON.asc | D19: zerissene Rüstung
A20: itar_kdw_l_addon | B20: ItAr_KDW_L_ADDON.3ds | C20: Armor_KDW_L_ADDON.asc | D20: Leichte KDW
A21: itar_bloodwyn_addon | B21: ItAr_Bloodwyn_ADDON.3ds | C21: Armor_Bloodwyn_ADDON.asc | D21: Bloodwyn Rüstung
A22: itar_mayazombie_addon | B22: ItAr_Raven_ADDON.3ds | C22: Armor_MayaZombie_Addon.asc | D22: alte Rüstung
A23: itar_firearmor_addon | B23: ItAr_Xardas.3ds | C23: Armor_Xardas.asc | D23: Magische Rüstung
A24: itbe_addon_leather_01 | B24: ItMI_Belt_06.3ds
A25: itbe_addon_sld_01 | B25: ItMi_Belt_05.3ds
A26: itbe_addon_nov_01 | B26: ItMi_Belt_02.3ds
A27: itbe_addon_mil_01 | B27: ItMi_Belt_03.3ds
A28: itbe_addon_kdf_01 | B28: ItMi_Belt_02.3ds
A29: itbe_addon_mc | B29: ItMi_Belt_08.3ds
A30: itbe_addon_str_5 | B30: ItMi_Belt_08.3ds
A31: itbe_addon_str_10 | B31: ItMi_Belt_05.3ds
A32: itbe_addon_dex_5 | B32: ItMi_Belt_08.3ds
A33: itbe_addon_dex_10 | B33: ItMi_Belt_05.3ds
A34: itbe_addon_prot_edge | B34: ItMi_Belt_02.3ds
A35: itbe_addon_prot_point | B35: ItMi_Belt_02.3ds
... A39: itbe_addon_prot_total | B39: ItMi_Belt_02.3ds
A40: itfo_addon_shellflesh | B40: ItAt_Meatbugflesh.3DS | D40: Muschelfleisch
A41: itfo_addon_rum | B41: ItMi_Rum_02.3ds | D41: Rum
A42: itfo_addon_grog | B42: ItMi_Rum_02.3ds | D42: Grog
A43: itfo_addon_loushammer | B43: ItMi_Rum_01.3ds | D43: Lou's Hammer
A44: itfo_addon_schlafhammer | B44: ItMi_Rum_01.3ds | D44: Doppelter Hammer
A45: itfo_addon_schnellerhering | B45: ItMi_Rum_01.3ds | D45: Schneller Hering
A46: itfo_addon_pfeffer_01 | B46: ItMi_Pocket.3ds | D46: Pfefferbeutel
A47: itfo_addon_firestew | B47: ItFo_Stew.3ds | D47: Feuergeschnetzeltes
A48: itfo_addon_meatsoup | B48: ItFo_FishSoup.3ds | D48: Fleischsuppe
A49: itke_portaltempelwalkthrough_addon | B49: ItKe_Key_01.3ds | D49: Rostiger Schlüssel
A50: itke_greg_addon_mis | B50: ItKe_Key_01.3ds
A51: itke_addon_tavern_01 | B51: ItKe_Key_02.3ds
A52: itke_addon_esteban_01 | B52: ItKe_Key_02.3ds
A53: itke_orlan_teleportstation | B53: ItKe_Key_02.3ds
A54: itke_canyonlibrary_hierarchy_books_addon | B54: ItKe_Key_01.3ds
A55: itke_addon_buddler_01 | B55: ItKe_Key_02.3ds
A56: itke_addon_skinner | B56: ItKe_Key_02.3ds
A57: itke_addon_thorus | B57: ItKe_Key_02.3ds
A58: itmi_goldnugget_addon | B58: ItMi_GoldNugget_01.3ds | D58: Goldbrocken
A59: itmi_addon_whitepearl | B59: ItMi_WhitePearl_01.3ds | D59: Perle
A60: itmi_addon_joint_01 | B60: ItMi_Joint_US.3ds | D60: Grüner Novize
A61: itmi_baltrampaket | B61: ItMi_Packet.3ds | D61: Baltram's Lieferung
A62: itmi_packet_baltram4skip_addon | B62: ItMi_Packet.3ds | D62: Paket für Skip
A63: itmi_bromorsgeld_addon | B63: ItMi_GoldChalice.3DS | D63: Bromors Goldene Schale
A64: itse_addon_cavalornsbeutel | B64: ItMi_Pocket.3ds | D64: Cavalorns Lederbeutel
A65: itmi_skull | B65: DT_SKELETON_V01_HEAD.3ds | D65: Schädel
A66: itmi_iecello | B66: Itmi_IE_Cello.3ds | D66: Cello
A67: itmi_iecellobow | B67: Itmi_IE_CelloBow.3ds | D67: CelloBow
A68: itmi_iedrum | B68: Itmi_IE_Drum.3ds | D68: Drum
A69: itmi_iedrumscheit | B69: Itmi_IE_Drumscheit.3ds | D69: Drumscheit
... A80: itpo_mana_addon_04 | B80: ItPo_Mana_03.3ds | D80: POTIONFAST
A81: itru_thunderstorm | B81: ItRu_Water05.3DS
A82: itru_whirlwind | B82: ItRu_Water02.3DS
A83: itru_geyser | B83: ItRu_Water01.3DS
A84: itru_waterfist | B84: ItRu_Water03.3DS
A85: itru_icelance | B85: ItRu_Water04.3DS
A86: itru_beliarsrage | B86: ItRu_Beliar04.3DS
A87: itru_suckenergy | B87: ItRu_Beliar01.3DS
A88: itru_greententacle | B88: ItRu_Beliar03.3DS
A89: itru_swarm | B89: ItRu_Beliar02.3DS
A90: itru_skull | B90: ItRu_Beliar05.3DS
A91: itru_summonzombie | B91: ItRu_Beliar07.3DS
A92: itru_summonguardian | B92: ItRu_Beliar06.3DS
... A97: itsc_whirlwind | B97: ItSc_Water02.3DS
A98: itmi_addon_shell_01 | B98: ItMi_Shell_01.3ds | D98: Klappmuschel
A99: itmi_addon_shell_02 | B99: ItMi_Shell_02.3ds | D99: Hornmuschel
A100: itwr_strstoneplate1_addon | B100: ItMi_StonePlate_PowerUp_01.3DS
A101: itwr_strstoneplate2_addon | B101: ItMi_StonePlate_PowerUp_01.3DS
A102: itwr_strstoneplate3_addon | B102: ItMi_StonePlate_PowerUp_01.3DS
A103: itwr_dexstoneplate1_addon | B103: ItMi_StonePlate_PowerUp_02.3DS
A104: itwr_dexstoneplate2_addon | B104: ItMi_StonePlate_PowerUp_02.3DS
A105: itwr_dexstoneplate3_addon | B105: ItMi_StonePlate_PowerUp_02.3DS
A106: itwr_hitpointstoneplate1_addon | B106: ItMi_StonePlate_PowerUp_03.3DS
A107: itwr_hitpointstoneplate2_addon | B107: ItMi_StonePlate_PowerUp_03.3DS
A108: itwr_hitpointstoneplate3_addon | B108: ItMi_StonePlate_PowerUp_03.3DS
A109: itwr_manastoneplate1_addon | B109: ItMi_StonePlate_PowerUp_03.3DS
A110: itwr_manastoneplate2_addon | B110: ItMi_StonePlate_PowerUp_03.3DS
A111: itwr_manastoneplate3_addon | B111: ItMi_StonePlate_PowerUp_03.3DS
... A123: itwr_crsbowstoneplate3_addon | B123: ItMi_StonePlate_PowerUp_04.3DS
A124: itmw_addon_knife01 | B124: ItMw_012_1h_Knife_02.3DS | D124: Wolfsmesser
A125: itmw_addon_stab01 | B125: ItMW_MageStaff_Good_2H_01.3DS | D125: Magierstab
A126: itmw_addon_stab02 | B126: ItMW_MageStaff_Good_2H_02.3DS | D126: Zauberstab
A127: itmw_addon_stab03 | B127: ItMW_MageStaff_Blades_2H_01.3DS | D127: Wasserstab
A128: itmw_addon_stab04 | B128: ItMW_MageStaff_Good_2H_02.3DS | D128: Ulthar's Stab
...

Sheet Lista mebli
A1: Nazwa | B1: Tier | C1: Opis | D1: Instancja | E1: Instancja [Saga3] | F1: Składnik 1 | H1: Składnik 2 | J1: Składnik 3 | L1: Składnik 4 | N1: Składnik 5 | P1: Składnik 6 | R1: Składnik 7 | T1: Składnik 8 | V1: Składnik 9 | X1: Składnik 10 | Z1: Składnik 11 | AB1: Składnik 12 | AD1: Waga | AE1: VobType | AF1: category | AG1: Do mieszkania? | AH1: Dla graczy | AI1: Cena
F3: Nazwa | G3: Ilość | H3: Nazwa | I3: Ilość | J3: Nazwa | K3: Ilość | L3: Nazwa | M3: Ilość | N3: Nazwa | O3: Ilość | P3: Nazwa | Q3: Ilość | R3: Nazwa | S3: Ilość | T3: Nazwa | U3: Ilość | V3: Nazwa | W3: Ilość | X3: Nazwa | Y3: Ilość | Z3: Nazwa | AA3: Ilość | AB3: Nazwa | AC3: Ilość
A4: Drewniana skrzynia | B4: 1 | C4: Drewniana skrzynia. | D4: CHESTSMALL_OCCHESTSMALLLOCKED.ASC | E4: CHESTSMALL_OCCHESTSMALLLOCKED.ASC | F4: Deska z miękiego drewna | G4: 13 | H4: Gwoździe | I4: 1 | J4: Smoła | K4: 1 | L4: Żelazne elementy | M4: 1 | N4: - | P4: - | R4: - | T4: - | V4: - | X4: - | Z4: - | AB4: - | AD4: 20 | AE4: MobInter | AF4: chest | AG4: TRUE | AH4: TRUE | AI4: =IFERROR(VLOOKUP(F4,Cennik!$A$4:$B892, 2, FALSE()) * G4 + VLOOKUP(H4,Cennik!$A$4:$B892, 2, FALSE()) * I4 + VLOOKUP(J4,Cennik!$A$4:$B892, 2, FALSE()) * K4 + VLOOKUP(L4,Cennik!$A$4:$B892, 2, FALSE()) * M4 + VLOOKUP(N4,Cennik!$A$4:$B892, 2, FALSE()) * O4 + VLOOKUP(P4,Cennik!$A$4:$B892, 2, FALSE()) * Q4 + VLOOKUP(R4,Cennik!$A$4:$B892, 2, FALSE()) * S4 + VLOOKUP(T4,Cennik!$A$4:$B892, 2, FALSE()) * U4 + VLOOKUP(V4,Cennik!$A$4:$B892, 2, FALSE()) * W4 + VLOOKUP(X4,Cennik!$A$4:$B892, 2, FALSE()) * Y4 + VLOOKUP(Z4,Cennik!$A$4:$B892, 2, FALSE()) * AA4 + VLOOKUP(AB4,Cennik!$A$4:$B892, 2, FALSE() * AC4),"Brak wartości") -> Brak wartości
A5: Mała prowizoryczna skrzynia | B5: 1 | C5: Mala prowizoryczna skrzynia | D5: CHESTSMALL_OCCRATESMALLLOCKED.ASC | E5: CHESTSMALL_OCCRATESMALLLOCKED.ASC | F5: Deska z miękiego drewna | G5: 10 | H5: Smoła | I5: 1 | J5: Gwoździe | K5: 2 | L5: Żelazne elementy | M5: 1 | N5: - | P5: - | R5: - | T5: - | V5: - | X5: - | Z5: - | AB5: - | AD5: 10 | AE5: MobInter | AF5: chest | AG5: TRUE | AH5: TRUE | AI5: =IFERROR(VLOOKUP(F5,Cennik!$A$4:$B892, 2, FALSE()) * G5 + VLOOKUP(H5,Cennik!$A$4:$B892, 2, FALSE()) * I5 + VLOOKUP(J5,Cennik!$A$4:$B892, 2, FALSE()) * K5 + VLOOKUP(L5,Cennik!$A$4:$B892, 2, FALSE()) * M5 + VLOOKUP(N5,Cennik!$A$4:$B892, 2, FALSE()) * O5 + VLOOKUP(P5,Cennik!$A$4:$B892, 2, FALSE()) * Q5 + VLOOKUP(R5,Cennik!$A$4:$B892, 2, FALSE()) * S5 + VLOOKUP(T5,Cennik!$A$4:$B892, 2, FALSE()) * U5 + VLOOKUP(V5,Cennik!$A$4:$B892, 2, FALSE()) * W5 + VLOOKUP(X5,Cennik!$A$4:$B892, 2, FALSE()) * Y5 + VLOOKUP(Z5,Cennik!$A$4:$B892, 2, FALSE()) * AA5 + VLOOKUP(AB5,Cennik!$A$4:$B892, 2, FALSE() * AC5),"Brak wartości") -> Brak wartości
A6: Duża prowizoryczna skrzynia | B6: 1 | C6: Duża prowizoryczna skrzynia | D6: CHESTBIG_OCCRATELARGELOCKED.ASC | E6: CHESTBIG_OCCRATELARGELOCKED.ASC | F6: Deska z miękiego drewna | G6: 20 | H6: Smoła | I6: 1 | J6: Gwoździe | K6: 2 | L6: Żelazne elementy | M6: 1 | N6: - | P6: - | R6: - | T6: - | V6: - | X6: - | Z6: - | AB6: - | AD6: 30 | AE6: MobInter | AF6: chest | AG6: TRUE | AH6: TRUE | AI6: =IFERROR(VLOOKUP(F6,Cennik!$A$4:$B892, 2, FALSE()) * G6 + VLOOKUP(H6,Cennik!$A$4:$B892, 2, FALSE()) * I6 + VLOOKUP(J6,Cennik!$A$4:$B892, 2, FALSE()) * K6 + VLOOKUP(L6,Cennik!$A$4:$B892, 2, FALSE()) * M6 + VLOOKUP(N6,Cennik!$A$4:$B892, 2, FALSE()) * O6 + VLOOKUP(P6,Cennik!$A$4:$B892, 2, FALSE()) * Q6 + VLOOKUP(R6,Cennik!$A$4:$B892, 2, FALSE()) * S6 + VLOOKUP(T6,Cennik!$A$4:$B892, 2, FALSE()) * U6 + VLOOKUP(V6,Cennik!$A$4:$B892, 2, FALSE()) * W6 + VLOOKUP(X6,Cennik!$A$4:$B892, 2, FALSE()) * Y6 + VLOOKUP(Z6,Cennik!$A$4:$B892, 2, FALSE()) * AA6 + VLOOKUP(AB6,Cennik!$A$4:$B892, 2, FALSE() * AC6),"Brak wartości") -> Brak wartości
A7: Beczka | B7: 1 | C7: Nie dajmy się zwieść wyglądowi, beczka może mieć w sobie więcej, niż się spodziewamy. | D7: KM_VOB_BARRELTABLE_02.3DS | E7: KM_VOB_BARRELTABLE_02.3DS | F7: Deska z miękiego drewna | G7: 10 | H7: Gwoździe | I7: 2 | J7: Żelazny pręt | K7: 1 | L7: Smoła | M7: 1 | N7: - | P7: - | R7: - | T7: - | V7: - | X7: - | Z7: - | AB7: - | AD7: 15 | AE7: MobInter | AF7: chest | AG7: TRUE | AH7: TRUE | AI7: =IFERROR(VLOOKUP(F7,Cennik!$A$4:$B892, 2, FALSE()) * G7 + VLOOKUP(H7,Cennik!$A$4:$B892, 2, FALSE()) * I7 + VLOOKUP(J7,Cennik!$A$4:$B892, 2, FALSE()) * K7 + VLOOKUP(L7,Cennik!$A$4:$B892, 2, FALSE()) * M7 + VLOOKUP(N7,Cennik!$A$4:$B892, 2, FALSE()) * O7 + VLOOKUP(P7,Cennik!$A$4:$B892, 2, FALSE()) * Q7 + VLOOKUP(R7,Cennik!$A$4:$B892, 2, FALSE()) * S7 + VLOOKUP(T7,Cennik!$A$4:$B892, 2, FALSE()) * U7 + VLOOKUP(V7,Cennik!$A$4:$B892, 2, FALSE()) * W7 + VLOOKUP(X7,Cennik!$A$4:$B892, 2, FALSE()) * Y7 + VLOOKUP(Z7,Cennik!$A$4:$B892, 2, FALSE()) * AA7 + VLOOKUP(AB7,Cennik!$A$4:$B892, 2, FALSE() * AC7),"Brak wartości") -> Brak wartości
A8: Skrzynia na drewno | B8: 1 | C8: Skrzynia na drewno | D8: OC_FIREWOOD_V2.ASC | E8: OC_FIREWOOD_V2.3ds | F8: Deska z miękiego drewna | G8: 5 | H8: Smoła | I8: 1 | J8: - | L8: - | N8: - | P8: - | R8: - | T8: - | V8: - | X8: - | Z8: - | AB8: - | AD8: 10 | AE8: MobInter | AF8: chest | AG8: TRUE | AH8: TRUE | AI8: =IFERROR(VLOOKUP(F8,Cennik!$A$4:$B892, 2, FALSE()) * G8 + VLOOKUP(H8,Cennik!$A$4:$B892, 2, FALSE()) * I8 + VLOOKUP(J8,Cennik!$A$4:$B892, 2, FALSE()) * K8 + VLOOKUP(L8,Cennik!$A$4:$B892, 2, FALSE()) * M8 + VLOOKUP(N8,Cennik!$A$4:$B892, 2, FALSE()) * O8 + VLOOKUP(P8,Cennik!$A$4:$B892, 2, FALSE()) * Q8 + VLOOKUP(R8,Cennik!$A$4:$B892, 2, FALSE()) * S8 + VLOOKUP(T8,Cennik!$A$4:$B892, 2, FALSE()) * U8 + VLOOKUP(V8,Cennik!$A$4:$B892, 2, FALSE()) * W8 + VLOOKUP(X8,Cennik!$A$4:$B892, 2, FALSE()) * Y8 + VLOOKUP(Z8,Cennik!$A$4:$B892, 2, FALSE()) * AA8 + VLOOKUP(AB8,Cennik!$A$4:$B892, 2, FALSE() * AC8),"Brak wartości") -> Brak wartości
A9: Biedna skrzynia | B9: 2 | C9: Niby biedna a jednak lepsza niż prowizoryczne. | D9: CHESTSMALL_NW_POOR_LOCKED.ASC | E9: CHESTSMALL_NW_POOR_LOCKED.ASC | F9: Twarde drewno | G9: 1 | H9: Deska z twardego drewna | I9: 4 | J9: Gwoździe | K9: 2 | L9: Smoła | M9: 1 | N9: Sztaba żelaza | O9: 1 | P9: Żelazne elementy | Q9: 1 | R9: - | T9: - | V9: - | X9: - | Z9: - | AB9: - | AD9: 25 | AE9: MobInter | AF9: chest | AG9: TRUE | AH9: TRUE | AI9: =IFERROR(VLOOKUP(F9,Cennik!$A$4:$B892, 2, FALSE()) * G9 + VLOOKUP(H9,Cennik!$A$4:$B892, 2, FALSE()) * I9 + VLOOKUP(J9,Cennik!$A$4:$B892, 2, FALSE()) * K9 + VLOOKUP(L9,Cennik!$A$4:$B892, 2, FALSE()) * M9 + VLOOKUP(N9,Cennik!$A$4:$B892, 2, FALSE()) * O9 + VLOOKUP(P9,Cennik!$A$4:$B892, 2, FALSE()) * Q9 + VLOOKUP(R9,Cennik!$A$4:$B892, 2, FALSE()) * S9 + VLOOKUP(T9,Cennik!$A$4:$B892, 2, FALSE()) * U9 + VLOOKUP(V9,Cennik!$A$4:$B892, 2, FALSE()) * W9 + VLOOKUP(X9,Cennik!$A$4:$B892, 2, FALSE()) * Y9 + VLOOKUP(Z9,Cennik!$A$4:$B892, 2, FALSE()) * AA9 + VLOOKUP(AB9,Cennik!$A$4:$B892, 2, FALSE() * AC9),"Brak wartości") -> Brak wartości
A10: Duży drewniany kufer | B10: 2 | C10: Skrzynia będzie posiadała liczne okucia z pretów oraz blach. | D10: CHESTBIG_OCCHESTMEDIUMLOCKED.ASC | E10: CHESTBIG_OCCHESTMEDIUMLOCKED.ASC | F10: Twarde drewno | G10: 2 | H10: Deska z twardego drewna | I10: 6 | J10: Gwoździe | K10: 3 | L10: Smoła | M10: 2 | N10: Sztaba żelaza | O10: 2 | P10: Żelazne elementy | Q10: 1 | R10: - | T10: - | V10: - | X10: - | Z10: - | AB10: - | AD10: 40 | AE10: MobInter | AF10: chest | AG10: TRUE | AH10: TRUE | AI10: =IFERROR(VLOOKUP(F10,Cennik!$A$4:$B892, 2, FALSE()) * G10 + VLOOKUP(H10,Cennik!$A$4:$B892, 2, FALSE()) * I10 + VLOOKUP(J10,Cennik!$A$4:$B892, 2, FALSE()) * K10 + VLOOKUP(L10,Cennik!$A$4:$B892, 2, FALSE()) * M10 + VLOOKUP(N10,Cennik!$A$4:$B892, 2, FALSE()) * O10 + VLOOKUP(P10,Cennik!$A$4:$B892, 2, FALSE()) * Q10 + VLOOKUP(R10,Cennik!$A$4:$B892, 2, FALSE()) * S10 + VLOOKUP(T10,Cennik!$A$4:$B892, 2, FALSE()) * U10 + VLOOKUP(V10,Cennik!$A$4:$B892, 2, FALSE()) * W10 + VLOOKUP(X10,Cennik!$A$4:$B892, 2, FALSE()) * Y10 + VLOOKUP(Z10,Cennik!$A$4:$B892, 2, FALSE()) * AA10 + VLOOKUP(AB10,Cennik!$A$4:$B892, 2, FALSE() * AC10),"Brak wartości") -> Brak wartości
A11: Mała wzmacniana skrzynia | B11: 3 | C11: Skrzynia będzie posiadała liczne okucia z pretów oraz blach. | D11: CHESTSMALL_NW_NORMAL_LOCKED.ASC | E11: CHESTBIG_NW_NORMAL_LOCKED.mds | F11: Szlachetne drewno | G11: 2 | H11: Deska z miękiego drewna | I11: 8 | J11: Deska z szlachetnego drewna | K11: 4 | L11: Gwoździe | M11: 3 | N11: Smoła | O11: 2 | P11: Sztabka stali | Q11: 1 | R11: Żelazne elementy | S11: 2 | T11: - | V11: - | X11: - | Z11: - | AB11: - | AD11: 35 | AE11: MobInter | AF11: chest | AG11: TRUE | AH11: TRUE | AI11: =IFERROR(VLOOKUP(F11,Cennik!$A$4:$B892, 2, FALSE()) * G11 + VLOOKUP(H11,Cennik!$A$4:$B892, 2, FALSE()) * I11 + VLOOKUP(J11,Cennik!$A$4:$B892, 2, FALSE()) * K11 + VLOOKUP(L11,Cennik!$A$4:$B892, 2, FALSE()) * M11 + VLOOKUP(N11,Cennik!$A$4:$B892, 2, FALSE()) * O11 + VLOOKUP(P11,Cennik!$A$4:$B892, 2, FALSE()) * Q11 + VLOOKUP(R11,Cennik!$A$4:$B892, 2, FALSE()) * S11 + VLOOKUP(T11,Cennik!$A$4:$B892, 2, FALSE()) * U11 + VLOOKUP(V11,Cennik!$A$4:$B892, 2, FALSE()) * W11 + VLOOKUP(X11,Cennik!$A$4:$B892, 2, FALSE()) * Y11 + VLOOKUP(Z11,Cennik!$A$4:$B892, 2, FALSE()) * AA11 + VLOOKUP(AB11,Cennik!$A$4:$B892, 2, FALSE() * AC11),"Brak wartości") -> Brak wartości
A12: Duża wzmacniana skrzynia | B12: 3 | C12: Skrzynia będzie posiadała jeszcze więcej okuć niż wersja mniejsza. | D12: CHESTBIG_NW_NORMAL_LOCKED.ASC | E12: CHESTBIG_NW_NORMAL_LOCKED.ASC | F12: Szlachetne drewno | G12: 4 | H12: Deska z miękiego drewna | I12: 12 | J12: Deska z szlachetnego drewna | K12: 6 | L12: Gwoździe | M12: 4 | N12: Smoła | O12: 2 | P12: Sztabka stali | Q12: 1 | R12: Żelazne elementy | S12: 2 | T12: - | V12: - | X12: - | Z12: - | AB12: - | AD12: 50 | AE12: MobInter | AF12: chest | AG12: TRUE | AH12: TRUE | AI12: =IFERROR(VLOOKUP(F12,Cennik!$A$4:$B892, 2, FALSE()) * G12 + VLOOKUP(H12,Cennik!$A$4:$B892, 2, FALSE()) * I12 + VLOOKUP(J12,Cennik!$A$4:$B892, 2, FALSE()) * K12 + VLOOKUP(L12,Cennik!$A$4:$B892, 2, FALSE()) * M12 + VLOOKUP(N12,Cennik!$A$4:$B892, 2, FALSE()) * O12 + VLOOKUP(P12,Cennik!$A$4:$B892, 2, FALSE()) * Q12 + VLOOKUP(R12,Cennik!$A$4:$B892, 2, FALSE()) * S12 + VLOOKUP(T12,Cennik!$A$4:$B892, 2, FALSE()) * U12 + VLOOKUP(V12,Cennik!$A$4:$B892, 2, FALSE()) * W12 + VLOOKUP(X12,Cennik!$A$4:$B892, 2, FALSE()) * Y12 + VLOOKUP(Z12,Cennik!$A$4:$B892, 2, FALSE()) * AA12 + VLOOKUP(AB12,Cennik!$A$4:$B892, 2, FALSE() * AC12),"Brak wartości") -> Brak wartości
A13: Solidna skrzynia | B13: 4 | C13: Solidna skrzynia | D13: CHESTBIG_NW_RICH_LOCKED.ASC | E13: CHESTBIG_NW_RICH_LOCKED.ASC | F13: Szlachetne drewno | G13: 5 | H13: Deska z szlachetnego drewna | I13: 8 | J13: Gwoździe | K13: 8 | L13: Smoła | M13: 3 | N13: Sztabka stali | O13: 1 | P13: Żelazny pręt | Q13: 5 | R13: Żelazne elementy | S13: 3 | T13: - | V13: - | X13: - | Z13: - | AB13: - | AD13: 60 | AE13: MobInter | AF13: chest | AG13: TRUE | AH13: TRUE | AI13: =IFERROR(VLOOKUP(F13,Cennik!$A$4:$B892, 2, FALSE()) * G13 + VLOOKUP(H13,Cennik!$A$4:$B892, 2, FALSE()) * I13 + VLOOKUP(J13,Cennik!$A$4:$B892, 2, FALSE()) * K13 + VLOOKUP(L13,Cennik!$A$4:$B892, 2, FALSE()) * M13 + VLOOKUP(N13,Cennik!$A$4:$B892, 2, FALSE()) * O13 + VLOOKUP(P13,Cennik!$A$4:$B892, 2, FALSE()) * Q13 + VLOOKUP(R13,Cennik!$A$4:$B892, 2, FALSE()) * S13 + VLOOKUP(T13,Cennik!$A$4:$B892, 2, FALSE()) * U13 + VLOOKUP(V13,Cennik!$A$4:$B892, 2, FALSE()) * W13 + VLOOKUP(X13,Cennik!$A$4:$B892, 2, FALSE()) * Y13 + VLOOKUP(Z13,Cennik!$A$4:$B892, 2, FALSE()) * AA13 + VLOOKUP(AB13,Cennik!$A$4:$B892, 2, FALSE() * AC13),"Brak wartości") -> Brak wartości
A14: Stalowy kufer | B14: 4 | C14: Solidna skrzynia | D14: ItHc_Chest_Silver.3DS | E14: CHESTBIG_SILVEROPEN_LOCKED.MDS | F14: Szlachetne drewno | G14: 6 | H14: Deska z szlachetnego drewna | I14: 12 | J14: Gwoździe | K14: 8 | L14: Smoła | M14: 4 | N14: Sztabka stali | O14: 1 | P14: Żelazna blacha | Q14: 10 | R14: Żelazny pręt | S14: 5 | T14: Żelazne elementy | U14: 3 | V14: - | X14: - | Z14: - | AB14: - | AD14: 60 | AE14: MobInter | AF14: chest | AG14: TRUE | AH14: TRUE | AI14: =IFERROR(VLOOKUP(F14,Cennik!$A$4:$B892, 2, FALSE()) * G14 + VLOOKUP(H14,Cennik!$A$4:$B892, 2, FALSE()) * I14 + VLOOKUP(J14,Cennik!$A$4:$B892, 2, FALSE()) * K14 + VLOOKUP(L14,Cennik!$A$4:$B892, 2, FALSE()) * M14 + VLOOKUP(N14,Cennik!$A$4:$B892, 2, FALSE()) * O14 + VLOOKUP(P14,Cennik!$A$4:$B892, 2, FALSE()) * Q14 + VLOOKUP(R14,Cennik!$A$4:$B892, 2, FALSE()) * S14 + VLOOKUP(T14,Cennik!$A$4:$B892, 2, FALSE()) * U14 + VLOOKUP(V14,Cennik!$A$4:$B892, 2, FALSE()) * W14 + VLOOKUP(X14,Cennik!$A$4:$B892, 2, FALSE()) * Y14 + VLOOKUP(Z14,Cennik!$A$4:$B892, 2, FALSE()) * AA14 + VLOOKUP(AB14,Cennik!$A$4:$B892, 2, FALSE() * AC14),"Brak wartości") -> Brak wartości
A15: Varancki skarbiec | B15: 5 | C15: Majestatyczny kufer zdobiony misternymi drzeworytami i ornamentami, który przechowuje skarby godne samego króla Rhobara. | D15: KM_VOB_GOLD_HEAP_01.ASC | E15: KM_VOB_GOLD_HEAP_01.3ds | F15: - | H15: - | J15: - | L15: - | N15: - | P15: - | R15: - | T15: - | V15: - | X15: - | Z15: - | AB15: - | AD15: 80 | AE15: MobInter | AF15: chest | AG15: FALSE | AH15: FALSE | AI15: 2000
A16: Królewska skrzynia | B16: 5 | C16: Majestatyczny kufer zdobiony misternymi drzeworytami i ornamentami, który przechowuje skarby godne samego króla Rhobara. | D16: ItHc_Chest_Gold.3DS | E16: CHESTBIG_GOLDOPEN_LOCKED.MDS | F16: Szlachetne drewno | G16: 8 | H16: Gwoździe | I16: 5 | J16: Smoła | K16: 5 | L16: Stalowy pręt | M16: 4 | N16: Moneta | O16: 1000 | P16: Żelazne elementy | Q16: 4 | R16: - | T16: - | V16: - | X16: - | Z16: - | AB16: - | AD16: 80 | AE16: MobInter | AF16: chest | AG16: TRUE | AH16: TRUE | AI16: =IFERROR(VLOOKUP(F16,Cennik!$A$4:$B892, 2, FALSE()) * G16 + VLOOKUP(H16,Cennik!$A$4:$B892, 2, FALSE()) * I16 + VLOOKUP(J16,Cennik!$A$4:$B892, 2, FALSE()) * K16 + VLOOKUP(L16,Cennik!$A$4:$B892, 2, FALSE()) * M16 + VLOOKUP(N16,Cennik!$A$4:$B892, 2, FALSE()) * O16 + VLOOKUP(P16,Cennik!$A$4:$B892, 2, FALSE()) * Q16 + VLOOKUP(R16,Cennik!$A$4:$B892, 2, FALSE()) * S16 + VLOOKUP(T16,Cennik!$A$4:$B892, 2, FALSE()) * U16 + VLOOKUP(V16,Cennik!$A$4:$B892, 2, FALSE()) * W16 + VLOOKUP(X16,Cennik!$A$4:$B892, 2, FALSE()) * Y16 + VLOOKUP(Z16,Cennik!$A$4:$B892, 2, FALSE()) * AA16 + VLOOKUP(AB16,Cennik!$A$4:$B892, 2, FALSE() * AC16),"Brak wartości") -> Brak wartości
F17: - | H17: - | J17: - | L17: - | N17: - | P17: - | R17: - | T17: - | V17: - | X17: - | Z17: - | AB17: -
F18: - | H18: - | J18: - | L18: - | N18: - | P18: - | R18: - | T18: - | V18: - | X18: - | Z18: - | AB18: -
F19: - | H19: - | J19: - | L19: - | N19: - | P19: - | R19: - | T19: - | V19: - | X19: - | Z19: - | AB19: -
A20: Zbity drewniany stolik | B20: 1 | C20: Stół zrobiony z resztek, ale i tak wydaje się dość solidny. Może służyć do różnych celów. | D20: PC_LOB_TABLE2.3ds | E20: PC_LOB_TABLE2.3ds | F20: Deska z miękiego drewna | G20: 5 | H20: Gwoździe | I20: 1 | J20: Smoła | K20: 1 | L20: - | N20: - | P20: - | R20: - | T20: - | V20: - | X20: - | Z20: - | AB20: - | AD20: 5 | AE20: Vob | AF20: table | AG20: TRUE | AH20: TRUE | AI20: =IFERROR(VLOOKUP(F20,Cennik!$A$4:$B892, 2, FALSE()) * G20 + VLOOKUP(H20,Cennik!$A$4:$B892, 2, FALSE()) * I20 + VLOOKUP(J20,Cennik!$A$4:$B892, 2, FALSE()) * K20 + VLOOKUP(L20,Cennik!$A$4:$B892, 2, FALSE()) * M20 + VLOOKUP(N20,Cennik!$A$4:$B892, 2, FALSE()) * O20 + VLOOKUP(P20,Cennik!$A$4:$B892, 2, FALSE()) * Q20 + VLOOKUP(R20,Cennik!$A$4:$B892, 2, FALSE()) * S20 + VLOOKUP(T20,Cennik!$A$4:$B892, 2, FALSE()) * U20 + VLOOKUP(V20,Cennik!$A$4:$B892, 2, FALSE()) * W20 + VLOOKUP(X20,Cennik!$A$4:$B892, 2, FALSE()) * Y20 + VLOOKUP(Z20,Cennik!$A$4:$B892, 2, FALSE()) * AA20 + VLOOKUP(AB20,Cennik!$A$4:$B892, 2, FALSE() * AC20),"Brak wartości") -> Brak wartości
A21: Stół z pniaka | B21: 1 | C21: Stół zrobiony z resztek, ale i tak wydaje się dość solidny. Może służyć do różnych celów. | D21: NC_LOB_TABLE2.3ds | E21: NC_LOB_TABLE2.3ds | F21: Deska z miękiego drewna | G21: 5 | H21: Gwoździe | I21: 1 | J21: Smoła | K21: 1 | L21: - | N21: - | P21: - | R21: - | T21: - | V21: - | X21: - | Z21: - | AB21: - | AD21: 5 | AE21: Vob | AF21: table | AG21: TRUE | AH21: TRUE | AI21: =IFERROR(VLOOKUP(F21,Cennik!$A$4:$B892, 2, FALSE()) * G21 + VLOOKUP(H21,Cennik!$A$4:$B892, 2, FALSE()) * I21 + VLOOKUP(J21,Cennik!$A$4:$B892, 2, FALSE()) * K21 + VLOOKUP(L21,Cennik!$A$4:$B892, 2, FALSE()) * M21 + VLOOKUP(N21,Cennik!$A$4:$B892, 2, FALSE()) * O21 + VLOOKUP(P21,Cennik!$A$4:$B892, 2, FALSE()) * Q21 + VLOOKUP(R21,Cennik!$A$4:$B892, 2, FALSE()) * S21 + VLOOKUP(T21,Cennik!$A$4:$B892, 2, FALSE()) * U21 + VLOOKUP(V21,Cennik!$A$4:$B892, 2, FALSE()) * W21 + VLOOKUP(X21,Cennik!$A$4:$B892, 2, FALSE()) * Y21 + VLOOKUP(Z21,Cennik!$A$4:$B892, 2, FALSE()) * AA21 + VLOOKUP(AB21,Cennik!$A$4:$B892, 2, FALSE() * AC21),"Brak wartości") -> Brak wartości
A22: Prowizoryczny stół | B22: 1 | C22: Stół zrobiony z resztek, ale i tak wydaje się dość solidny. Może służyć do różnych celów. | D22: OC_TABLE_V3.3ds | E22: OC_TABLE_V3.3ds | F22: Deska z miękiego drewna | G22: 10 | H22: Gwoździe | I22: 1 | J22: Smoła | K22: 1 | L22: - | N22: - | P22: - | R22: - | T22: - | V22: - | X22: - | Z22: - | AB22: - | AD22: 5 | AE22: Vob | AF22: table | AG22: TRUE | AH22: TRUE | AI22: =IFERROR(VLOOKUP(F22,Cennik!$A$4:$B892, 2, FALSE()) * G22 + VLOOKUP(H22,Cennik!$A$4:$B892, 2, FALSE()) * I22 + VLOOKUP(J22,Cennik!$A$4:$B892, 2, FALSE()) * K22 + VLOOKUP(L22,Cennik!$A$4:$B892, 2, FALSE()) * M22 + VLOOKUP(N22,Cennik!$A$4:$B892, 2, FALSE()) * O22 + VLOOKUP(P22,Cennik!$A$4:$B892, 2, FALSE()) * Q22 + VLOOKUP(R22,Cennik!$A$4:$B892, 2, FALSE()) * S22 + VLOOKUP(T22,Cennik!$A$4:$B892, 2, FALSE()) * U22 + VLOOKUP(V22,Cennik!$A$4:$B892, 2, FALSE()) * W22 + VLOOKUP(X22,Cennik!$A$4:$B892, 2, FALSE()) * Y22 + VLOOKUP(Z22,Cennik!$A$4:$B892, 2, FALSE()) * AA22 + VLOOKUP(AB22,Cennik!$A$4:$B892, 2, FALSE() * AC22),"Brak wartości") -> Brak wartości
A23: Okrągły prowizoryczny stół | B23: 1 | C23: Stół zrobiony z resztek, ale i tak wydaje się dość solidny. Może służyć do różnych celów. | D23: KM_LAKOMY_TABLE_CIRCULAR_PEASANT_01.3ds | E23: KM_LAKOMY_TABLE_CIRCULAR_PEASANT_01.3ds | F23: Deska z miękiego drewna | G23: 10 | H23: Gwoździe | I23: 1 | J23: Smoła | K23: 1 | L23: - | N23: - | P23: - | R23: - | T23: - | V23: - | X23: - | Z23: - | AB23: - | AD23: 5 | AE23: Vob | AF23: table | AG23: TRUE | AH23: TRUE | AI23: =IFERROR(VLOOKUP(F23,Cennik!$A$4:$B892, 2, FALSE()) * G23 + VLOOKUP(H23,Cennik!$A$4:$B892, 2, FALSE()) * I23 + VLOOKUP(J23,Cennik!$A$4:$B892, 2, FALSE()) * K23 + VLOOKUP(L23,Cennik!$A$4:$B892, 2, FALSE()) * M23 + VLOOKUP(N23,Cennik!$A$4:$B892, 2, FALSE()) * O23 + VLOOKUP(P23,Cennik!$A$4:$B892, 2, FALSE()) * Q23 + VLOOKUP(R23,Cennik!$A$4:$B892, 2, FALSE()) * S23 + VLOOKUP(T23,Cennik!$A$4:$B892, 2, FALSE()) * U23 + VLOOKUP(V23,Cennik!$A$4:$B892, 2, FALSE()) * W23 + VLOOKUP(X23,Cennik!$A$4:$B892, 2, FALSE()) * Y23 + VLOOKUP(Z23,Cennik!$A$4:$B892, 2, FALSE()) * AA23 + VLOOKUP(AB23,Cennik!$A$4:$B892, 2, FALSE() * AC23),"Brak wartości") -> Brak wartości
A24: Karczmienna ława | B24: 1 | C24: Ława zwykle stawiana w karczmach lub innych budach. | D24: KM_VOB_TAVERN_TABLE_01.3ds | E24: KM_VOB_TAVERN_TABLE_01.3ds | F24: Deska z miękiego drewna | G24: 10 | H24: Gwoździe | I24: 1 | J24: Smoła | K24: 1 | L24: - | N24: - | P24: - | R24: - | T24: - | V24: - | X24: - | Z24: - | AB24: - | AD24: 5 | AE24: Vob | AF24: table | AG24: TRUE | AH24: TRUE | AI24: =IFERROR(VLOOKUP(F24,Cennik!$A$4:$B892, 2, FALSE()) * G24 + VLOOKUP(H24,Cennik!$A$4:$B892, 2, FALSE()) * I24 + VLOOKUP(J24,Cennik!$A$4:$B892, 2, FALSE()) * K24 + VLOOKUP(L24,Cennik!$A$4:$B892, 2, FALSE()) * M24 + VLOOKUP(N24,Cennik!$A$4:$B892, 2, FALSE()) * O24 + VLOOKUP(P24,Cennik!$A$4:$B892, 2, FALSE()) * Q24 + VLOOKUP(R24,Cennik!$A$4:$B892, 2, FALSE()) * S24 + VLOOKUP(T24,Cennik!$A$4:$B892, 2, FALSE()) * U24 + VLOOKUP(V24,Cennik!$A$4:$B892, 2, FALSE()) * W24 + VLOOKUP(X24,Cennik!$A$4:$B892, 2, FALSE()) * Y24 + VLOOKUP(Z24,Cennik!$A$4:$B892, 2, FALSE()) * AA24 + VLOOKUP(AB24,Cennik!$A$4:$B892, 2, FALSE() * AC24),"Brak wartości") -> Brak wartości
A25: Bukowy stół | B25: 2 | C25: Ten mebel bukowy to najlepszy wybór dla każdego, kto ceni sobie solidność i prostotę. | D25: GS_CITY_TABLE_NORMAL_BLACK_01_KOZA.3ds | E25: GS_CITY_TABLE_NORMAL_BLACK_01_KOZA.3ds | F25: Deska z twardego drewna | G25: 10 | H25: Deska z miękiego drewna | I25: 6 | J25: Gwoździe | K25: 2 | L25: Smoła | M25: 1 | N25: - | P25: - | R25: - | T25: - | V25: - | X25: - | Z25: - | AB25: - | AD25: 15 | AE25: Vob | AF25: table | AG25: TRUE | AH25: TRUE | AI25: =IFERROR(VLOOKUP(F25,Cennik!$A$4:$B892, 2, FALSE()) * G25 + VLOOKUP(H25,Cennik!$A$4:$B892, 2, FALSE()) * I25 + VLOOKUP(J25,Cennik!$A$4:$B892, 2, FALSE()) * K25 + VLOOKUP(L25,Cennik!$A$4:$B892, 2, FALSE()) * M25 + VLOOKUP(N25,Cennik!$A$4:$B892, 2, FALSE()) * O25 + VLOOKUP(P25,Cennik!$A$4:$B892, 2, FALSE()) * Q25 + VLOOKUP(R25,Cennik!$A$4:$B892, 2, FALSE()) * S25 + VLOOKUP(T25,Cennik!$A$4:$B892, 2, FALSE()) * U25 + VLOOKUP(V25,Cennik!$A$4:$B892, 2, FALSE()) * W25 + VLOOKUP(X25,Cennik!$A$4:$B892, 2, FALSE()) * Y25 + VLOOKUP(Z25,Cennik!$A$4:$B892, 2, FALSE()) * AA25 + VLOOKUP(AB25,Cennik!$A$4:$B892, 2, FALSE() * AC25),"Brak wartości") -> Brak wartości
A26: Bukowy stół 2 | B26: 2 | C26: Ten mebel bukowy to najlepszy wybór dla każdego, kto ceni sobie solidność i prostotę. | D26: GS_LOB_TABLE_HEAVY_BLACK_01_KOZA.3ds | E26: GS_LOB_TABLE_HEAVY_BLACK_01_KOZA.3ds | F26: Deska z twardego drewna | G26: 10 | H26: Deska z miękiego drewna | I26: 6 | J26: Gwoździe | K26: 2 | L26: Smoła | M26: 1 | N26: - | P26: - | R26: - | T26: - | V26: - | X26: - | Z26: - | AB26: - | AD26: 15 | AE26: Vob | AF26: table | AG26: TRUE | AH26: TRUE | AI26: =IFERROR(VLOOKUP(F26,Cennik!$A$4:$B892, 2, FALSE()) * G26 + VLOOKUP(H26,Cennik!$A$4:$B892, 2, FALSE()) * I26 + VLOOKUP(J26,Cennik!$A$4:$B892, 2, FALSE()) * K26 + VLOOKUP(L26,Cennik!$A$4:$B892, 2, FALSE()) * M26 + VLOOKUP(N26,Cennik!$A$4:$B892, 2, FALSE()) * O26 + VLOOKUP(P26,Cennik!$A$4:$B892, 2, FALSE()) * Q26 + VLOOKUP(R26,Cennik!$A$4:$B892, 2, FALSE()) * S26 + VLOOKUP(T26,Cennik!$A$4:$B892, 2, FALSE()) * U26 + VLOOKUP(V26,Cennik!$A$4:$B892, 2, FALSE()) * W26 + VLOOKUP(X26,Cennik!$A$4:$B892, 2, FALSE()) * Y26 + VLOOKUP(Z26,Cennik!$A$4:$B892, 2, FALSE()) * AA26 + VLOOKUP(AB26,Cennik!$A$4:$B892, 2, FALSE() * AC26),"Brak wartości") -> Brak wartości
A27: Bukowy okrągły stół | B27: 2 | C27: Ten mebel bukowy to najlepszy wybór dla każdego, kto ceni sobie solidność i prostotę. | D27: GS_TABLE_CIRCULAR_BLACK_01_KOZA.3ds | E27: GS_TABLE_CIRCULAR_BLACK_01_KOZA.3ds | F27: Deska z twardego drewna | G27: 10 | H27: Deska z miękiego drewna | I27: 6 | J27: Gwoździe | K27: 2 | L27: Smoła | M27: 1 | N27: - | P27: - | R27: - | T27: - | V27: - | X27: - | Z27: - | AB27: - | AD27: 15 | AE27: Vob | AF27: table | AG27: TRUE | AH27: TRUE | AI27: =IFERROR(VLOOKUP(F27,Cennik!$A$4:$B892, 2, FALSE()) * G27 + VLOOKUP(H27,Cennik!$A$4:$B892, 2, FALSE()) * I27 + VLOOKUP(J27,Cennik!$A$4:$B892, 2, FALSE()) * K27 + VLOOKUP(L27,Cennik!$A$4:$B892, 2, FALSE()) * M27 + VLOOKUP(N27,Cennik!$A$4:$B892, 2, FALSE()) * O27 + VLOOKUP(P27,Cennik!$A$4:$B892, 2, FALSE()) * Q27 + VLOOKUP(R27,Cennik!$A$4:$B892, 2, FALSE()) * S27 + VLOOKUP(T27,Cennik!$A$4:$B892, 2, FALSE()) * U27 + VLOOKUP(V27,Cennik!$A$4:$B892, 2, FALSE()) * W27 + VLOOKUP(X27,Cennik!$A$4:$B892, 2, FALSE()) * Y27 + VLOOKUP(Z27,Cennik!$A$4:$B892, 2, FALSE()) * AA27 + VLOOKUP(AB27,Cennik!$A$4:$B892, 2, FALSE() * AC27),"Brak wartości") -> Brak wartości
A28: Długi bukowy stół | B28: 2 | C28: Ten mebel bukowy to najlepszy wybór dla każdego, kto ceni sobie solidność i prostotę. | D28: GS_LOB_TABLE_HEAVY_LONG_BLACK_01_KOZA.3ds | E28: GS_LOB_TABLE_HEAVY_LONG_BLACK_01_KOZA.3ds | F28: Deska z twardego drewna | G28: 10 | H28: Deska z miękiego drewna | I28: 6 | J28: Gwoździe | K28: 2 | L28: Smoła | M28: 1 | N28: - | P28: - | R28: - | T28: - | V28: - | X28: - | Z28: - | AB28: - | AD28: 15 | AE28: Vob | AF28: table | AG28: TRUE | AH28: TRUE | AI28: =IFERROR(VLOOKUP(F28,Cennik!$A$4:$B892, 2, FALSE()) * G28 + VLOOKUP(H28,Cennik!$A$4:$B892, 2, FALSE()) * I28 + VLOOKUP(J28,Cennik!$A$4:$B892, 2, FALSE()) * K28 + VLOOKUP(L28,Cennik!$A$4:$B892, 2, FALSE()) * M28 + VLOOKUP(N28,Cennik!$A$4:$B892, 2, FALSE()) * O28 + VLOOKUP(P28,Cennik!$A$4:$B892, 2, FALSE()) * Q28 + VLOOKUP(R28,Cennik!$A$4:$B892, 2, FALSE()) * S28 + VLOOKUP(T28,Cennik!$A$4:$B892, 2, FALSE()) * U28 + VLOOKUP(V28,Cennik!$A$4:$B892, 2, FALSE()) * W28 + VLOOKUP(X28,Cennik!$A$4:$B892, 2, FALSE()) * Y28 + VLOOKUP(Z28,Cennik!$A$4:$B892, 2, FALSE()) * AA28 + VLOOKUP(AB28,Cennik!$A$4:$B892, 2, FALSE() * AC28),"Brak wartości") -> Brak wartości
A29: Bukowy stolik z półkami | B29: 2 | C29: Ten mebel bukowy to najlepszy wybór dla każdego, kto ceni sobie solidność i prostotę. | D29: GS_VOB_TABLESHELVES_BLACK_01_KOZA.3ds | E29: GS_VOB_TABLESHELVES_BLACK_01_KOZA.3ds | F29: Deska z twardego drewna | G29: 10 | H29: Deska z miękiego drewna | I29: 6 | J29: Gwoździe | K29: 2 | L29: Smoła | M29: 1 | N29: - | P29: - | R29: - | T29: - | V29: - | X29: - | Z29: - | AB29: - | AD29: 15 | AE29: Vob | AF29: table | AG29: TRUE | AH29: TRUE | AI29: =IFERROR(VLOOKUP(F29,Cennik!$A$4:$B892, 2, FALSE()) * G29 + VLOOKUP(H29,Cennik!$A$4:$B892, 2, FALSE()) * I29 + VLOOKUP(J29,Cennik!$A$4:$B892, 2, FALSE()) * K29 + VLOOKUP(L29,Cennik!$A$4:$B892, 2, FALSE()) * M29 + VLOOKUP(N29,Cennik!$A$4:$B892, 2, FALSE()) * O29 + VLOOKUP(P29,Cennik!$A$4:$B892, 2, FALSE()) * Q29 + VLOOKUP(R29,Cennik!$A$4:$B892, 2, FALSE()) * S29 + VLOOKUP(T29,Cennik!$A$4:$B892, 2, FALSE()) * U29 + VLOOKUP(V29,Cennik!$A$4:$B892, 2, FALSE()) * W29 + VLOOKUP(X29,Cennik!$A$4:$B892, 2, FALSE()) * Y29 + VLOOKUP(Z29,Cennik!$A$4:$B892, 2, FALSE()) * AA29 + VLOOKUP(AB29,Cennik!$A$4:$B892, 2, FALSE() * AC29),"Brak wartości") -> Brak wartości
A30: Okrągły stolik | B30: 2 | C30: Stolik zwykle stawiany w karczmach lub innych budach. | D30: DT_TABLE_01.3ds | E30: DT_TABLE_01.3ds | F30: Deska z twardego drewna | G30: 10 | H30: Deska z miękiego drewna | I30: 6 | J30: Gwoździe | K30: 2 | L30: Smoła | M30: 1 | N30: - | P30: - | R30: - | T30: - | V30: - | X30: - | Z30: - | AB30: - | AD30: 15 | AE30: Vob | AF30: table | AG30: TRUE | AH30: TRUE | AI30: =IFERROR(VLOOKUP(F30,Cennik!$A$4:$B892, 2, FALSE()) * G30 + VLOOKUP(H30,Cennik!$A$4:$B892, 2, FALSE()) * I30 + VLOOKUP(J30,Cennik!$A$4:$B892, 2, FALSE()) * K30 + VLOOKUP(L30,Cennik!$A$4:$B892, 2, FALSE()) * M30 + VLOOKUP(N30,Cennik!$A$4:$B892, 2, FALSE()) * O30 + VLOOKUP(P30,Cennik!$A$4:$B892, 2, FALSE()) * Q30 + VLOOKUP(R30,Cennik!$A$4:$B892, 2, FALSE()) * S30 + VLOOKUP(T30,Cennik!$A$4:$B892, 2, FALSE()) * U30 + VLOOKUP(V30,Cennik!$A$4:$B892, 2, FALSE()) * W30 + VLOOKUP(X30,Cennik!$A$4:$B892, 2, FALSE()) * Y30 + VLOOKUP(Z30,Cennik!$A$4:$B892, 2, FALSE()) * AA30 + VLOOKUP(AB30,Cennik!$A$4:$B892, 2, FALSE() * AC30),"Brak wartości") -> Brak wartości
A31: Prosty stół | B31: 2 | C31: Nieoceniony w swojej prostocie, służy nie tylko do spożywania posiłków, ale również jako miejsce pracy czy zabawy. | D31: OC_TABLE_V1.3ds | E31: OC_TABLE_V1.3ds | F31: Deska z twardego drewna | G31: 10 | H31: Deska z miękiego drewna | I31: 6 | J31: Gwoździe | K31: 2 | L31: Smoła | M31: 1 | N31: - | P31: - | R31: - | T31: - | V31: - | X31: - | Z31: - | AB31: - | AD31: 15 | AE31: Vob | AF31: table | AG31: TRUE | AH31: TRUE | AI31: =IFERROR(VLOOKUP(F31,Cennik!$A$4:$B892, 2, FALSE()) * G31 + VLOOKUP(H31,Cennik!$A$4:$B892, 2, FALSE()) * I31 + VLOOKUP(J31,Cennik!$A$4:$B892, 2, FALSE()) * K31 + VLOOKUP(L31,Cennik!$A$4:$B892, 2, FALSE()) * M31 + VLOOKUP(N31,Cennik!$A$4:$B892, 2, FALSE()) * O31 + VLOOKUP(P31,Cennik!$A$4:$B892, 2, FALSE()) * Q31 + VLOOKUP(R31,Cennik!$A$4:$B892, 2, FALSE()) * S31 + VLOOKUP(T31,Cennik!$A$4:$B892, 2, FALSE()) * U31 + VLOOKUP(V31,Cennik!$A$4:$B892, 2, FALSE()) * W31 + VLOOKUP(X31,Cennik!$A$4:$B892, 2, FALSE()) * Y31 + VLOOKUP(Z31,Cennik!$A$4:$B892, 2, FALSE()) * AA31 + VLOOKUP(AB31,Cennik!$A$4:$B892, 2, FALSE() * AC31),"Brak wartości") -> Brak wartości
A32: Długa ława | B32: 2 | C32: Nieoceniony w swojej prostocie, służy nie tylko do spożywania posiłków, ale również jako miejsce pracy czy zabawy. | D32: KM_VOB_MERCHANT_LONGTABLE.3ds | E32: KM_VOB_MERCHANT_LONGTABLE.3ds | F32: Deska z twardego drewna | G32: 10 | H32: Deska z miękiego drewna | I32: 6 | J32: Gwoździe | K32: 2 | L32: Smoła | M32: 1 | N32: - | P32: - | R32: - | T32: - | V32: - | X32: - | Z32: - | AB32: - | AD32: 15 | AE32: Vob | AF32: table | AG32: TRUE | AH32: TRUE | AI32: =IFERROR(VLOOKUP(F32,Cennik!$A$4:$B892, 2, FALSE()) * G32 + VLOOKUP(H32,Cennik!$A$4:$B892, 2, FALSE()) * I32 + VLOOKUP(J32,Cennik!$A$4:$B892, 2, FALSE()) * K32 + VLOOKUP(L32,Cennik!$A$4:$B892, 2, FALSE()) * M32 + VLOOKUP(N32,Cennik!$A$4:$B892, 2, FALSE()) * O32 + VLOOKUP(P32,Cennik!$A$4:$B892, 2, FALSE()) * Q32 + VLOOKUP(R32,Cennik!$A$4:$B892, 2, FALSE()) * S32 + VLOOKUP(T32,Cennik!$A$4:$B892, 2, FALSE()) * U32 + VLOOKUP(V32,Cennik!$A$4:$B892, 2, FALSE()) * W32 + VLOOKUP(X32,Cennik!$A$4:$B892, 2, FALSE()) * Y32 + VLOOKUP(Z32,Cennik!$A$4:$B892, 2, FALSE()) * AA32 + VLOOKUP(AB32,Cennik!$A$4:$B892, 2, FALSE() * AC32),"Brak wartości") -> Brak wartości
A33: Dębowy stół | B33: 3 | C33: Ten stół dębowy to najlepszy wybór dla każdego, kto ceni sobie solidność i prostotę. | D33: GS_CITY_TABLE_NORMAL_BROWN_01_KOZA.3ds | E33: GS_CITY_TABLE_NORMAL_BROWN_01_KOZA.3ds | F33: Deska z szlachetnego drewna | G33: 10 | H33: Twarde drewno | I33: 2 | J33: Gwoździe | K33: 3 | L33: Smoła | M33: 1 | N33: - | P33: - | R33: - | T33: - | V33: - | X33: - | Z33: - | AB33: - | AD33: 25 | AE33: Vob | AF33: table | AG33: TRUE | AH33: TRUE | AI33: =IFERROR(VLOOKUP(F33,Cennik!$A$4:$B892, 2, FALSE()) * G33 + VLOOKUP(H33,Cennik!$A$4:$B892, 2, FALSE()) * I33 + VLOOKUP(J33,Cennik!$A$4:$B892, 2, FALSE()) * K33 + VLOOKUP(L33,Cennik!$A$4:$B892, 2, FALSE()) * M33 + VLOOKUP(N33,Cennik!$A$4:$B892, 2, FALSE()) * O33 + VLOOKUP(P33,Cennik!$A$4:$B892, 2, FALSE()) * Q33 + VLOOKUP(R33,Cennik!$A$4:$B892, 2, FALSE()) * S33 + VLOOKUP(T33,Cennik!$A$4:$B892, 2, FALSE()) * U33 + VLOOKUP(V33,Cennik!$A$4:$B892, 2, FALSE()) * W33 + VLOOKUP(X33,Cennik!$A$4:$B892, 2, FALSE()) * Y33 + VLOOKUP(Z33,Cennik!$A$4:$B892, 2, FALSE()) * AA33 + VLOOKUP(AB33,Cennik!$A$4:$B892, 2, FALSE() * AC33),"Brak wartości") -> Brak wartości
A34: Dębowy stół 2 | B34: 3 | C34: Ten stół dębowy to najlepszy wybór dla każdego, kto ceni sobie solidność i prostotę. | D34: GS_LOB_TABLE_HEAVY_BROWN_01_KOZA.3ds | E34: GS_LOB_TABLE_HEAVY_BROWN_01_KOZA.3ds | F34: Deska z szlachetnego drewna | G34: 10 | H34: Twarde drewno | I34: 2 | J34: Gwoździe | K34: 3 | L34: Smoła | M34: 1 | N34: - | P34: - | R34: - | T34: - | V34: - | X34: - | Z34: - | AB34: - | AD34: 25 | AE34: Vob | AF34: table | AG34: TRUE | AH34: TRUE | AI34: =IFERROR(VLOOKUP(F34,Cennik!$A$4:$B892, 2, FALSE()) * G34 + VLOOKUP(H34,Cennik!$A$4:$B892, 2, FALSE()) * I34 + VLOOKUP(J34,Cennik!$A$4:$B892, 2, FALSE()) * K34 + VLOOKUP(L34,Cennik!$A$4:$B892, 2, FALSE()) * M34 + VLOOKUP(N34,Cennik!$A$4:$B892, 2, FALSE()) * O34 + VLOOKUP(P34,Cennik!$A$4:$B892, 2, FALSE()) * Q34 + VLOOKUP(R34,Cennik!$A$4:$B892, 2, FALSE()) * S34 + VLOOKUP(T34,Cennik!$A$4:$B892, 2, FALSE()) * U34 + VLOOKUP(V34,Cennik!$A$4:$B892, 2, FALSE()) * W34 + VLOOKUP(X34,Cennik!$A$4:$B892, 2, FALSE()) * Y34 + VLOOKUP(Z34,Cennik!$A$4:$B892, 2, FALSE()) * AA34 + VLOOKUP(AB34,Cennik!$A$4:$B892, 2, FALSE() * AC34),"Brak wartości") -> Brak wartości
A35: Dębowy okrągły stół | B35: 3 | C35: Ten stół dębowy to najlepszy wybór dla każdego, kto ceni sobie solidność i prostotę. | D35: GS_TABLE_CIRCULAR_BROWN_01_KOZA.3ds | E35: GS_TABLE_CIRCULAR_BROWN_01_KOZA.3ds | F35: Deska z szlachetnego drewna | G35: 10 | H35: Twarde drewno | I35: 2 | J35: Gwoździe | K35: 3 | L35: Smoła | M35: 1 | N35: - | P35: - | R35: - | T35: - | V35: - | X35: - | Z35: - | AB35: - | AD35: 25 | AE35: Vob | AF35: table | AG35: TRUE | AH35: TRUE | AI35: =IFERROR(VLOOKUP(F35,Cennik!$A$4:$B892, 2, FALSE()) * G35 + VLOOKUP(H35,Cennik!$A$4:$B892, 2, FALSE()) * I35 + VLOOKUP(J35,Cennik!$A$4:$B892, 2, FALSE()) * K35 + VLOOKUP(L35,Cennik!$A$4:$B892, 2, FALSE()) * M35 + VLOOKUP(N35,Cennik!$A$4:$B892, 2, FALSE()) * O35 + VLOOKUP(P35,Cennik!$A$4:$B892, 2, FALSE()) * Q35 + VLOOKUP(R35,Cennik!$A$4:$B892, 2, FALSE()) * S35 + VLOOKUP(T35,Cennik!$A$4:$B892, 2, FALSE()) * U35 + VLOOKUP(V35,Cennik!$A$4:$B892, 2, FALSE()) * W35 + VLOOKUP(X35,Cennik!$A$4:$B892, 2, FALSE()) * Y35 + VLOOKUP(Z35,Cennik!$A$4:$B892, 2, FALSE()) * AA35 + VLOOKUP(AB35,Cennik!$A$4:$B892, 2, FALSE() * AC35),"Brak wartości") -> Brak wartości
A36: Długi dębowy stół | B36: 3 | C36: Ten stół dębowy to najlepszy wybór dla każdego, kto ceni sobie solidność i prostotę. | D36: GS_LOB_TABLE_HEAVY_LONG_BROWN_01_KOZA.3ds | E36: GS_LOB_TABLE_HEAVY_LONG_BROWN_01_KOZA.3ds | F36: Deska z szlachetnego drewna | G36: 10 | H36: Twarde drewno | I36: 2 | J36: Gwoździe | K36: 3 | L36: Smoła | M36: 1 | N36: - | P36: - | R36: - | T36: - | V36: - | X36: - | Z36: - | AB36: - | AD36: 25 | AE36: Vob | AF36: table | AG36: TRUE | AH36: TRUE | AI36: =IFERROR(VLOOKUP(F36,Cennik!$A$4:$B892, 2, FALSE()) * G36 + VLOOKUP(H36,Cennik!$A$4:$B892, 2, FALSE()) * I36 + VLOOKUP(J36,Cennik!$A$4:$B892, 2, FALSE()) * K36 + VLOOKUP(L36,Cennik!$A$4:$B892, 2, FALSE()) * M36 + VLOOKUP(N36,Cennik!$A$4:$B892, 2, FALSE()) * O36 + VLOOKUP(P36,Cennik!$A$4:$B892, 2, FALSE()) * Q36 + VLOOKUP(R36,Cennik!$A$4:$B892, 2, FALSE()) * S36 + VLOOKUP(T36,Cennik!$A$4:$B892, 2, FALSE()) * U36 + VLOOKUP(V36,Cennik!$A$4:$B892, 2, FALSE()) * W36 + VLOOKUP(X36,Cennik!$A$4:$B892, 2, FALSE()) * Y36 + VLOOKUP(Z36,Cennik!$A$4:$B892, 2, FALSE()) * AA36 + VLOOKUP(AB36,Cennik!$A$4:$B892, 2, FALSE() * AC36),"Brak wartości") -> Brak wartości
A37: Dębowy stolik z półkami | B37: 3 | C37: Ten stół dębowy to najlepszy wybór dla każdego, kto ceni sobie solidność i prostotę. | D37: GS_VOB_TABLESHELVES_BROWN_01_KOZA.3ds | E37: GS_VOB_TABLESHELVES_BROWN_01_KOZA.3ds | F37: Deska z szlachetnego drewna | G37: 10 | H37: Twarde drewno | I37: 2 | J37: Gwoździe | K37: 3 | L37: Smoła | M37: 1 | N37: - | P37: - | R37: - | T37: - | V37: - | X37: - | Z37: - | AB37: - | AD37: 25 | AE37: Vob | AF37: table | AG37: TRUE | AH37: TRUE | AI37: =IFERROR(VLOOKUP(F37,Cennik!$A$4:$B892, 2, FALSE()) * G37 + VLOOKUP(H37,Cennik!$A$4:$B892, 2, FALSE()) * I37 + VLOOKUP(J37,Cennik!$A$4:$B892, 2, FALSE()) * K37 + VLOOKUP(L37,Cennik!$A$4:$B892, 2, FALSE()) * M37 + VLOOKUP(N37,Cennik!$A$4:$B892, 2, FALSE()) * O37 + VLOOKUP(P37,Cennik!$A$4:$B892, 2, FALSE()) * Q37 + VLOOKUP(R37,Cennik!$A$4:$B892, 2, FALSE()) * S37 + VLOOKUP(T37,Cennik!$A$4:$B892, 2, FALSE()) * U37 + VLOOKUP(V37,Cennik!$A$4:$B892, 2, FALSE()) * W37 + VLOOKUP(X37,Cennik!$A$4:$B892, 2, FALSE()) * Y37 + VLOOKUP(Z37,Cennik!$A$4:$B892, 2, FALSE()) * AA37 + VLOOKUP(AB37,Cennik!$A$4:$B892, 2, FALSE() * AC37),"Brak wartości") -> Brak wartości
A38: Stół świerkowy | B38: 3 | C38: Ten stół świerkowy to najlepszy wybór dla każdego, kto ceni sobie solidność i prostotę. | D38: OC_LOB_TABLE_HEAVY.3ds | E38: OC_LOB_TABLE_HEAVY.3ds | F38: Deska z szlachetnego drewna | G38: 10 | H38: Twarde drewno | I38: 2 | J38: Gwoździe | K38: 3 | L38: Smoła | M38: 1 | N38: - | P38: - | R38: - | T38: - | V38: - | X38: - | Z38: - | AB38: - | AD38: 25 | AE38: Vob | AF38: table | AG38: TRUE | AH38: TRUE | AI38: =IFERROR(VLOOKUP(F38,Cennik!$A$4:$B892, 2, FALSE()) * G38 + VLOOKUP(H38,Cennik!$A$4:$B892, 2, FALSE()) * I38 + VLOOKUP(J38,Cennik!$A$4:$B892, 2, FALSE()) * K38 + VLOOKUP(L38,Cennik!$A$4:$B892, 2, FALSE()) * M38 + VLOOKUP(N38,Cennik!$A$4:$B892, 2, FALSE()) * O38 + VLOOKUP(P38,Cennik!$A$4:$B892, 2, FALSE()) * Q38 + VLOOKUP(R38,Cennik!$A$4:$B892, 2, FALSE()) * S38 + VLOOKUP(T38,Cennik!$A$4:$B892, 2, FALSE()) * U38 + VLOOKUP(V38,Cennik!$A$4:$B892, 2, FALSE()) * W38 + VLOOKUP(X38,Cennik!$A$4:$B892, 2, FALSE()) * Y38 + VLOOKUP(Z38,Cennik!$A$4:$B892, 2, FALSE()) * AA38 + VLOOKUP(AB38,Cennik!$A$4:$B892, 2, FALSE() * AC38),"Brak wartości") -> Brak wartości
A39: Stół z półkami | B39: 3 | C39: Ten stół idealnie współgra z poukładaną małą biblioteczką. | D39: KM_VOB_TABLESHELVES.3ds | E39: KM_VOB_TABLESHELVES.3ds | F39: Deska z szlachetnego drewna | G39: 10 | H39: Twarde drewno | I39: 2 | J39: Gwoździe | K39: 3 | L39: Smoła | M39: 1 | N39: - | P39: - | R39: - | T39: - | V39: - | X39: - | Z39: - | AB39: - | AD39: 25 | AE39: Vob | AF39: table | AG39: TRUE | AH39: TRUE | AI39: =IFERROR(VLOOKUP(F39,Cennik!$A$4:$B892, 2, FALSE()) * G39 + VLOOKUP(H39,Cennik!$A$4:$B892, 2, FALSE()) * I39 + VLOOKUP(J39,Cennik!$A$4:$B892, 2, FALSE()) * K39 + VLOOKUP(L39,Cennik!$A$4:$B892, 2, FALSE()) * M39 + VLOOKUP(N39,Cennik!$A$4:$B892, 2, FALSE()) * O39 + VLOOKUP(P39,Cennik!$A$4:$B892, 2, FALSE()) * Q39 + VLOOKUP(R39,Cennik!$A$4:$B892, 2, FALSE()) * S39 + VLOOKUP(T39,Cennik!$A$4:$B892, 2, FALSE()) * U39 + VLOOKUP(V39,Cennik!$A$4:$B892, 2, FALSE()) * W39 + VLOOKUP(X39,Cennik!$A$4:$B892, 2, FALSE()) * Y39 + VLOOKUP(Z39,Cennik!$A$4:$B892, 2, FALSE()) * AA39 + VLOOKUP(AB39,Cennik!$A$4:$B892, 2, FALSE() * AC39),"Brak wartości") -> Brak wartości
A40: Hebanowy stół | B40: 4 | C40: Ten stół jest wykonany z najlepszego dębu, jakiego kiedykolwiek widziałem. Mocny, wytrzymały i piękny - taki mebel to prawdziwe dzieło sztuki. | D40: GS_CITY_TABLE_NORMAL_ORANGE_01_KOZA.3ds | E40: GS_CITY_TABLE_NORMAL_ORANGE_01_KOZA.3ds | F40: Deska z szlachetnego drewna | G40: 15 | H40: Twarde drewno | I40: 3 | J40: Gwoździe | K40: 3 | L40: Smoła | M40: 1 | N40: Żelazna blacha | O40: 3 | P40: - | R40: - | T40: - | V40: - | X40: - | Z40: - | AB40: - | AD40: 50 | AE40: Vob | AF40: table | AG40: TRUE | AH40: TRUE | AI40: =IFERROR(VLOOKUP(F40,Cennik!$A$4:$B892, 2, FALSE()) * G40 + VLOOKUP(H40,Cennik!$A$4:$B892, 2, FALSE()) * I40 + VLOOKUP(J40,Cennik!$A$4:$B892, 2, FALSE()) * K40 + VLOOKUP(L40,Cennik!$A$4:$B892, 2, FALSE()) * M40 + VLOOKUP(N40,Cennik!$A$4:$B892, 2, FALSE()) * O40 + VLOOKUP(P40,Cennik!$A$4:$B892, 2, FALSE()) * Q40 + VLOOKUP(R40,Cennik!$A$4:$B892, 2, FALSE()) * S40 + VLOOKUP(T40,Cennik!$A$4:$B892, 2, FALSE()) * U40 + VLOOKUP(V40,Cennik!$A$4:$B892, 2, FALSE()) * W40 + VLOOKUP(X40,Cennik!$A$4:$B892, 2, FALSE()) * Y40 + VLOOKUP(Z40,Cennik!$A$4:$B892, 2, FALSE()) * AA40 + VLOOKUP(AB40,Cennik!$A$4:$B892, 2, FALSE() * AC40),"Brak wartości") -> Brak wartości
A41: Hebanowy stół 2 | B41: 4 | C41: Ten stół jest wykonany z najlepszego dębu, jakiego kiedykolwiek widziałem. Mocny, wytrzymały i piękny - taki mebel to prawdziwe dzieło sztuki. | D41: GS_LOB_TABLE_HEAVY_ORANGE_01_KOZA.3ds | E41: GS_LOB_TABLE_HEAVY_ORANGE_01_KOZA.3ds | F41: Deska z szlachetnego drewna | G41: 15 | H41: Twarde drewno | I41: 3 | J41: Gwoździe | K41: 3 | L41: Smoła | M41: 1 | N41: Żelazna blacha | O41: 3 | P41: - | R41: - | T41: - | V41: - | X41: - | Z41: - | AB41: - | AD41: 50 | AE41: Vob | AF41: table | AG41: TRUE | AH41: TRUE | AI41: =IFERROR(VLOOKUP(F41,Cennik!$A$4:$B892, 2, FALSE()) * G41 + VLOOKUP(H41,Cennik!$A$4:$B892, 2, FALSE()) * I41 + VLOOKUP(J41,Cennik!$A$4:$B892, 2, FALSE()) * K41 + VLOOKUP(L41,Cennik!$A$4:$B892, 2, FALSE()) * M41 + VLOOKUP(N41,Cennik!$A$4:$B892, 2, FALSE()) * O41 + VLOOKUP(P41,Cennik!$A$4:$B892, 2, FALSE()) * Q41 + VLOOKUP(R41,Cennik!$A$4:$B892, 2, FALSE()) * S41 + VLOOKUP(T41,Cennik!$A$4:$B892, 2, FALSE()) * U41 + VLOOKUP(V41,Cennik!$A$4:$B892, 2, FALSE()) * W41 + VLOOKUP(X41,Cennik!$A$4:$B892, 2, FALSE()) * Y41 + VLOOKUP(Z41,Cennik!$A$4:$B892, 2, FALSE()) * AA41 + VLOOKUP(AB41,Cennik!$A$4:$B892, 2, FALSE() * AC41),"Brak wartości") -> Brak wartości
A42: Hebanowy okrągły stół | B42: 4 | C42: Ten stół jest wykonany z najlepszego dębu, jakiego kiedykolwiek widziałem. Mocny, wytrzymały i piękny - taki mebel to prawdziwe dzieło sztuki. | D42: GS_TABLE_CIRCULAR_ORANGE_01_KOZA.3ds | E42: GS_TABLE_CIRCULAR_ORANGE_01_KOZA.3ds | F42: Deska z szlachetnego drewna | G42: 15 | H42: Twarde drewno | I42: 3 | J42: Gwoździe | K42: 3 | L42: Smoła | M42: 1 | N42: Żelazna blacha | O42: 3 | P42: - | R42: - | T42: - | V42: - | X42: - | Z42: - | AB42: - | AD42: 50 | AE42: Vob | AF42: table | AG42: TRUE | AH42: TRUE | AI42: =IFERROR(VLOOKUP(F42,Cennik!$A$4:$B892, 2, FALSE()) * G42 + VLOOKUP(H42,Cennik!$A$4:$B892, 2, FALSE()) * I42 + VLOOKUP(J42,Cennik!$A$4:$B892, 2, FALSE()) * K42 + VLOOKUP(L42,Cennik!$A$4:$B892, 2, FALSE()) * M42 + VLOOKUP(N42,Cennik!$A$4:$B892, 2, FALSE()) * O42 + VLOOKUP(P42,Cennik!$A$4:$B892, 2, FALSE()) * Q42 + VLOOKUP(R42,Cennik!$A$4:$B892, 2, FALSE()) * S42 + VLOOKUP(T42,Cennik!$A$4:$B892, 2, FALSE()) * U42 + VLOOKUP(V42,Cennik!$A$4:$B892, 2, FALSE()) * W42 + VLOOKUP(X42,Cennik!$A$4:$B892, 2, FALSE()) * Y42 + VLOOKUP(Z42,Cennik!$A$4:$B892, 2, FALSE()) * AA42 + VLOOKUP(AB42,Cennik!$A$4:$B892, 2, FALSE() * AC42),"Brak wartości") -> Brak wartości
A43: Długi hebanowy stół | B43: 4 | C43: Ten stół jest wykonany z najlepszego dębu, jakiego kiedykolwiek widziałem. Mocny, wytrzymały i piękny - taki mebel to prawdziwe dzieło sztuki. | D43: GS_LOB_TABLE_HEAVY_LONG_ORANGE_01_KOZA.3ds | E43: GS_LOB_TABLE_HEAVY_LONG_ORANGE_01_KOZA.3ds | F43: Deska z szlachetnego drewna | G43: 15 | H43: Twarde drewno | I43: 3 | J43: Gwoździe | K43: 3 | L43: Smoła | M43: 1 | N43: Żelazna blacha | O43: 3 | P43: - | R43: - | T43: - | V43: - | X43: - | Z43: - | AB43: - | AD43: 50 | AE43: Vob | AF43: table | AG43: TRUE | AH43: TRUE | AI43: =IFERROR(VLOOKUP(F43,Cennik!$A$4:$B892, 2, FALSE()) * G43 + VLOOKUP(H43,Cennik!$A$4:$B892, 2, FALSE()) * I43 + VLOOKUP(J43,Cennik!$A$4:$B892, 2, FALSE()) * K43 + VLOOKUP(L43,Cennik!$A$4:$B892, 2, FALSE()) * M43 + VLOOKUP(N43,Cennik!$A$4:$B892, 2, FALSE()) * O43 + VLOOKUP(P43,Cennik!$A$4:$B892, 2, FALSE()) * Q43 + VLOOKUP(R43,Cennik!$A$4:$B892, 2, FALSE()) * S43 + VLOOKUP(T43,Cennik!$A$4:$B892, 2, FALSE()) * U43 + VLOOKUP(V43,Cennik!$A$4:$B892, 2, FALSE()) * W43 + VLOOKUP(X43,Cennik!$A$4:$B892, 2, FALSE()) * Y43 + VLOOKUP(Z43,Cennik!$A$4:$B892, 2, FALSE()) * AA43 + VLOOKUP(AB43,Cennik!$A$4:$B892, 2, FALSE() * AC43),"Brak wartości") -> Brak wartości
A44: Hebanowy stolik z półkami | B44: 4 | C44: Ten stół jest wykonany z najlepszego dębu, jakiego kiedykolwiek widziałem. Mocny, wytrzymały i piękny - taki mebel to prawdziwe dzieło sztuki. | D44: GS_VOB_TABLESHELVES_ORANGE_01_KOZA.3ds | E44: GS_VOB_TABLESHELVES_ORANGE_01_KOZA.3ds | F44: Deska z szlachetnego drewna | G44: 15 | H44: Twarde drewno | I44: 3 | J44: Gwoździe | K44: 3 | L44: Smoła | M44: 1 | N44: Żelazna blacha | O44: 3 | P44: - | R44: - | T44: - | V44: - | X44: - | Z44: - | AB44: - | AD44: 50 | AE44: Vob | AF44: table | AG44: TRUE | AH44: TRUE | AI44: =IFERROR(VLOOKUP(F44,Cennik!$A$4:$B892, 2, FALSE()) * G44 + VLOOKUP(H44,Cennik!$A$4:$B892, 2, FALSE()) * I44 + VLOOKUP(J44,Cennik!$A$4:$B892, 2, FALSE()) * K44 + VLOOKUP(L44,Cennik!$A$4:$B892, 2, FALSE()) * M44 + VLOOKUP(N44,Cennik!$A$4:$B892, 2, FALSE()) * O44 + VLOOKUP(P44,Cennik!$A$4:$B892, 2, FALSE()) * Q44 + VLOOKUP(R44,Cennik!$A$4:$B892, 2, FALSE()) * S44 + VLOOKUP(T44,Cennik!$A$4:$B892, 2, FALSE()) * U44 + VLOOKUP(V44,Cennik!$A$4:$B892, 2, FALSE()) * W44 + VLOOKUP(X44,Cennik!$A$4:$B892, 2, FALSE()) * Y44 + VLOOKUP(Z44,Cennik!$A$4:$B892, 2, FALSE()) * AA44 + VLOOKUP(AB44,Cennik!$A$4:$B892, 2, FALSE() * AC44),"Brak wartości") -> Brak wartości
A45: Stół dębowy | B45: 4 | C45: Ten stół jest wykonany z najlepszego dębu, jakiego kiedykolwiek widziałem. Mocny, wytrzymały i piękny - taki mebel to prawdziwe dzieło sztuki. | D45: NW_CITY_TABLE_NORMAL_01.3ds | E45: NW_CITY_TABLE_NORMAL_01.3ds | F45: Deska z szlachetnego drewna | G45: 15 | H45: Twarde drewno | I45: 3 | J45: Gwoździe | K45: 3 | L45: Smoła | M45: 1 | N45: Żelazna blacha | O45: 3 | P45: - | R45: - | T45: - | V45: - | X45: - | Z45: - | AB45: - | AD45: 50 | AE45: Vob | AF45: table | AG45: TRUE | AH45: TRUE | AI45: =IFERROR(VLOOKUP(F45,Cennik!$A$4:$B892, 2, FALSE()) * G45 + VLOOKUP(H45,Cennik!$A$4:$B892, 2, FALSE()) * I45 + VLOOKUP(J45,Cennik!$A$4:$B892, 2, FALSE()) * K45 + VLOOKUP(L45,Cennik!$A$4:$B892, 2, FALSE()) * M45 + VLOOKUP(N45,Cennik!$A$4:$B892, 2, FALSE()) * O45 + VLOOKUP(P45,Cennik!$A$4:$B892, 2, FALSE()) * Q45 + VLOOKUP(R45,Cennik!$A$4:$B892, 2, FALSE()) * S45 + VLOOKUP(T45,Cennik!$A$4:$B892, 2, FALSE()) * U45 + VLOOKUP(V45,Cennik!$A$4:$B892, 2, FALSE()) * W45 + VLOOKUP(X45,Cennik!$A$4:$B892, 2, FALSE()) * Y45 + VLOOKUP(Z45,Cennik!$A$4:$B892, 2, FALSE()) * AA45 + VLOOKUP(AB45,Cennik!$A$4:$B892, 2, FALSE() * AC45),"Brak wartości") -> Brak wartości
A46: Długi rzeźbiony stół | B46: 5 | C46: Ten stół z pewnością przyciągnie wzrok. Rzeźby na nogach zrobią wrażenie, a drewno będzie wyglądać bardzo solidnie. | D46: NW_CITY_TABLE_WAR_01.3ds | E46: NW_CITY_TABLE_WAR_01.3ds | F46: Deska z szlachetnego drewna | G46: 25 | H46: Szlachetne drewno | I46: 3 | J46: Gwoździe | K46: 8 | L46: Smoła | M46: 2 | N46: - | P46: - | R46: - | T46: - | V46: - | X46: - | Z46: - | AB46: - | AD46: 50 | AE46: Vob | AF46: table | AG46: TRUE | AH46: TRUE | AI46: =IFERROR(VLOOKUP(F46,Cennik!$A$4:$B892, 2, FALSE()) * G46 + VLOOKUP(H46,Cennik!$A$4:$B892, 2, FALSE()) * I46 + VLOOKUP(J46,Cennik!$A$4:$B892, 2, FALSE()) * K46 + VLOOKUP(L46,Cennik!$A$4:$B892, 2, FALSE()) * M46 + VLOOKUP(N46,Cennik!$A$4:$B892, 2, FALSE()) * O46 + VLOOKUP(P46,Cennik!$A$4:$B892, 2, FALSE()) * Q46 + VLOOKUP(R46,Cennik!$A$4:$B892, 2, FALSE()) * S46 + VLOOKUP(T46,Cennik!$A$4:$B892, 2, FALSE()) * U46 + VLOOKUP(V46,Cennik!$A$4:$B892, 2, FALSE()) * W46 + VLOOKUP(X46,Cennik!$A$4:$B892, 2, FALSE()) * Y46 + VLOOKUP(Z46,Cennik!$A$4:$B892, 2, FALSE()) * AA46 + VLOOKUP(AB46,Cennik!$A$4:$B892, 2, FALSE() * AC46),"Brak wartości") -> Brak wartości
A47: Brzozowy stół | B47: 5 | C47: Ten stół z pewnością przyciągnie wzrok. Rzeźby na nogach zrobią wrażenie, a drewno będzie wyglądać bardzo solidnie. | D47: GS_CITY_TABLE_NORMAL_YELLOW_01_KOZA.3ds | E47: GS_CITY_TABLE_NORMAL_YELLOW_01_KOZA.3ds | F47: Deska z szlachetnego drewna | G47: 25 | H47: Szlachetne drewno | I47: 3 | J47: Gwoździe | K47: 8 | L47: Smoła | M47: 2 | N47: - | P47: - | R47: - | T47: - | V47: - | X47: - | Z47: - | AB47: - | AD47: 50 | AE47: Vob | AF47: table | AG47: TRUE | AH47: TRUE | AI47: =IFERROR(VLOOKUP(F47,Cennik!$A$4:$B892, 2, FALSE()) * G47 + VLOOKUP(H47,Cennik!$A$4:$B892, 2, FALSE()) * I47 + VLOOKUP(J47,Cennik!$A$4:$B892, 2, FALSE()) * K47 + VLOOKUP(L47,Cennik!$A$4:$B892, 2, FALSE()) * M47 + VLOOKUP(N47,Cennik!$A$4:$B892, 2, FALSE()) * O47 + VLOOKUP(P47,Cennik!$A$4:$B892, 2, FALSE()) * Q47 + VLOOKUP(R47,Cennik!$A$4:$B892, 2, FALSE()) * S47 + VLOOKUP(T47,Cennik!$A$4:$B892, 2, FALSE()) * U47 + VLOOKUP(V47,Cennik!$A$4:$B892, 2, FALSE()) * W47 + VLOOKUP(X47,Cennik!$A$4:$B892, 2, FALSE()) * Y47 + VLOOKUP(Z47,Cennik!$A$4:$B892, 2, FALSE()) * AA47 + VLOOKUP(AB47,Cennik!$A$4:$B892, 2, FALSE() * AC47),"Brak wartości") -> Brak wartości
A48: Brzozowy stół 2 | B48: 5 | C48: Ten stół z pewnością przyciągnie wzrok. Rzeźby na nogach zrobią wrażenie, a drewno będzie wyglądać bardzo solidnie. | D48: GS_LOB_TABLE_HEAVY_YELLOW_01_KOZA.3ds | E48: GS_LOB_TABLE_HEAVY_YELLOW_01_KOZA.3ds | F48: Deska z szlachetnego drewna | G48: 25 | H48: Szlachetne drewno | I48: 3 | J48: Gwoździe | K48: 8 | L48: Smoła | M48: 2 | N48: - | P48: - | R48: - | T48: - | V48: - | X48: - | Z48: - | AB48: - | AD48: 50 | AE48: Vob | AF48: table | AG48: TRUE | AH48: TRUE | AI48: =IFERROR(VLOOKUP(F48,Cennik!$A$4:$B892, 2, FALSE()) * G48 + VLOOKUP(H48,Cennik!$A$4:$B892, 2, FALSE()) * I48 + VLOOKUP(J48,Cennik!$A$4:$B892, 2, FALSE()) * K48 + VLOOKUP(L48,Cennik!$A$4:$B892, 2, FALSE()) * M48 + VLOOKUP(N48,Cennik!$A$4:$B892, 2, FALSE()) * O48 + VLOOKUP(P48,Cennik!$A$4:$B892, 2, FALSE()) * Q48 + VLOOKUP(R48,Cennik!$A$4:$B892, 2, FALSE()) * S48 + VLOOKUP(T48,Cennik!$A$4:$B892, 2, FALSE()) * U48 + VLOOKUP(V48,Cennik!$A$4:$B892, 2, FALSE()) * W48 + VLOOKUP(X48,Cennik!$A$4:$B892, 2, FALSE()) * Y48 + VLOOKUP(Z48,Cennik!$A$4:$B892, 2, FALSE()) * AA48 + VLOOKUP(AB48,Cennik!$A$4:$B892, 2, FALSE() * AC48),"Brak wartości") -> Brak wartości
A49: Brzozowy okrągły stół | B49: 5 | C49: Ten stół z pewnością przyciągnie wzrok. Rzeźby na nogach zrobią wrażenie, a drewno będzie wyglądać bardzo solidnie. | D49: GS_TABLE_CIRCULAR_YELLOW_01_KOZA.3ds | E49: GS_TABLE_CIRCULAR_YELLOW_01_KOZA.3ds | F49: Deska z szlachetnego drewna | G49: 25 | H49: Szlachetne drewno | I49: 3 | J49: Gwoździe | K49: 8 | L49: Smoła | M49: 2 | N49: - | P49: - | R49: - | T49: - | V49: - | X49: - | Z49: - | AB49: - | AD49: 50 | AE49: Vob | AF49: table | AG49: TRUE | AH49: TRUE | AI49: =IFERROR(VLOOKUP(F49,Cennik!$A$4:$B892, 2, FALSE()) * G49 + VLOOKUP(H49,Cennik!$A$4:$B892, 2, FALSE()) * I49 + VLOOKUP(J49,Cennik!$A$4:$B892, 2, FALSE()) * K49 + VLOOKUP(L49,Cennik!$A$4:$B892, 2, FALSE()) * M49 + VLOOKUP(N49,Cennik!$A$4:$B892, 2, FALSE()) * O49 + VLOOKUP(P49,Cennik!$A$4:$B892, 2, FALSE()) * Q49 + VLOOKUP(R49,Cennik!$A$4:$B892, 2, FALSE()) * S49 + VLOOKUP(T49,Cennik!$A$4:$B892, 2, FALSE()) * U49 + VLOOKUP(V49,Cennik!$A$4:$B892, 2, FALSE()) * W49 + VLOOKUP(X49,Cennik!$A$4:$B892, 2, FALSE()) * Y49 + VLOOKUP(Z49,Cennik!$A$4:$B892, 2, FALSE()) * AA49 + VLOOKUP(AB49,Cennik!$A$4:$B892, 2, FALSE() * AC49),"Brak wartości") -> Brak wartości
A50: Długi brzozowy stół | B50: 5 | C50: Ten stół z pewnością przyciągnie wzrok. Rzeźby na nogach zrobią wrażenie, a drewno będzie wyglądać bardzo solidnie. | D50: GS_LOB_TABLE_HEAVY_LONG_YELLOW_01_KOZA.3ds | E50: GS_LOB_TABLE_HEAVY_LONG_YELLOW_01_KOZA.3ds | F50: Deska z szlachetnego drewna | G50: 25 | H50: Szlachetne drewno | I50: 3 | J50: Gwoździe | K50: 8 | L50: Smoła | M50: 2 | N50: - | P50: - | R50: - | T50: - | V50: - | X50: - | Z50: - | AB50: - | AD50: 50 | AE50: Vob | AF50: table | AG50: TRUE | AH50: TRUE | AI50: =IFERROR(VLOOKUP(F50,Cennik!$A$4:$B892, 2, FALSE()) * G50 + VLOOKUP(H50,Cennik!$A$4:$B892, 2, FALSE()) * I50 + VLOOKUP(J50,Cennik!$A$4:$B892, 2, FALSE()) * K50 + VLOOKUP(L50,Cennik!$A$4:$B892, 2, FALSE()) * M50 + VLOOKUP(N50,Cennik!$A$4:$B892, 2, FALSE()) * O50 + VLOOKUP(P50,Cennik!$A$4:$B892, 2, FALSE()) * Q50 + VLOOKUP(R50,Cennik!$A$4:$B892, 2, FALSE()) * S50 + VLOOKUP(T50,Cennik!$A$4:$B892, 2, FALSE()) * U50 + VLOOKUP(V50,Cennik!$A$4:$B892, 2, FALSE()) * W50 + VLOOKUP(X50,Cennik!$A$4:$B892, 2, FALSE()) * Y50 + VLOOKUP(Z50,Cennik!$A$4:$B892, 2, FALSE()) * AA50 + VLOOKUP(AB50,Cennik!$A$4:$B892, 2, FALSE() * AC50),"Brak wartości") -> Brak wartości
A51: Brzozowy stolik z półkami | B51: 5 | C51: Ten stół z pewnością przyciągnie wzrok. Rzeźby na nogach zrobią wrażenie, a drewno będzie wyglądać bardzo solidnie. | D51: GS_VOB_TABLESHELVES_YELLOW_01_KOZA.3ds | E51: GS_VOB_TABLESHELVES_YELLOW_01_KOZA.3ds | F51: Deska z szlachetnego drewna | G51: 25 | H51: Szlachetne drewno | I51: 3 | J51: Gwoździe | K51: 8 | L51: Smoła | M51: 2 | N51: - | P51: - | R51: - | T51: - | V51: - | X51: - | Z51: - | AB51: - | AD51: 50 | AE51: Vob | AF51: table | AG51: TRUE | AH51: TRUE | AI51: =IFERROR(VLOOKUP(F51,Cennik!$A$4:$B892, 2, FALSE()) * G51 + VLOOKUP(H51,Cennik!$A$4:$B892, 2, FALSE()) * I51 + VLOOKUP(J51,Cennik!$A$4:$B892, 2, FALSE()) * K51 + VLOOKUP(L51,Cennik!$A$4:$B892, 2, FALSE()) * M51 + VLOOKUP(N51,Cennik!$A$4:$B892, 2, FALSE()) * O51 + VLOOKUP(P51,Cennik!$A$4:$B892, 2, FALSE()) * Q51 + VLOOKUP(R51,Cennik!$A$4:$B892, 2, FALSE()) * S51 + VLOOKUP(T51,Cennik!$A$4:$B892, 2, FALSE()) * U51 + VLOOKUP(V51,Cennik!$A$4:$B892, 2, FALSE()) * W51 + VLOOKUP(X51,Cennik!$A$4:$B892, 2, FALSE()) * Y51 + VLOOKUP(Z51,Cennik!$A$4:$B892, 2, FALSE()) * AA51 + VLOOKUP(AB51,Cennik!$A$4:$B892, 2, FALSE() * AC51),"Brak wartości") -> Brak wartości
A52: Okrągły rzeźbiony stolik | B52: 5 | C52: Ten stół z pewnością przyciągnie wzrok. Rzeźby na nogach zrobią wrażenie, a drewno będzie wyglądać bardzo solidnie. | D52: KM_LAKOMY_TABLE_CIRCULAR_RICH_01.3ds | E52: KM_LAKOMY_TABLE_CIRCULAR_RICH_01.3ds | F52: Deska z szlachetnego drewna | G52: 25 | H52: Szlachetne drewno | I52: 3 | J52: Gwoździe | K52: 8 | L52: Smoła | M52: 2 | N52: - | P52: - | R52: - | T52: - | V52: - | X52: - | Z52: - | AB52: - | AD52: 50 | AE52: Vob | AF52: table | AG52: TRUE | AH52: TRUE | AI52: =IFERROR(VLOOKUP(F52,Cennik!$A$4:$B892, 2, FALSE()) * G52 + VLOOKUP(H52,Cennik!$A$4:$B892, 2, FALSE()) * I52 + VLOOKUP(J52,Cennik!$A$4:$B892, 2, FALSE()) * K52 + VLOOKUP(L52,Cennik!$A$4:$B892, 2, FALSE()) * M52 + VLOOKUP(N52,Cennik!$A$4:$B892, 2, FALSE()) * O52 + VLOOKUP(P52,Cennik!$A$4:$B892, 2, FALSE()) * Q52 + VLOOKUP(R52,Cennik!$A$4:$B892, 2, FALSE()) * S52 + VLOOKUP(T52,Cennik!$A$4:$B892, 2, FALSE()) * U52 + VLOOKUP(V52,Cennik!$A$4:$B892, 2, FALSE()) * W52 + VLOOKUP(X52,Cennik!$A$4:$B892, 2, FALSE()) * Y52 + VLOOKUP(Z52,Cennik!$A$4:$B892, 2, FALSE()) * AA52 + VLOOKUP(AB52,Cennik!$A$4:$B892, 2, FALSE() * AC52),"Brak wartości") -> Brak wartości
A53: Rzeźbiony stół | B53: 5 | C53: Ten stół z pewnością przyciągnie wzrok. Rzeźby na nogach zrobią wrażenie, a drewno będzie wyglądać bardzo solidnie. | D53: NW_CITY_TABLE_RICH_02.3ds | E53: NW_CITY_TABLE_RICH_02.3ds | F53: Deska z szlachetnego drewna | G53: 25 | H53: Szlachetne drewno | I53: 3 | J53: Gwoździe | K53: 8 | L53: Smoła | M53: 2 | N53: - | P53: - | R53: - | T53: - | V53: - | X53: - | Z53: - | AB53: - | AD53: 50 | AE53: Vob | AF53: table | AG53: TRUE | AH53: TRUE | AI53: =IFERROR(VLOOKUP(F53,Cennik!$A$4:$B892, 2, FALSE()) * G53 + VLOOKUP(H53,Cennik!$A$4:$B892, 2, FALSE()) * I53 + VLOOKUP(J53,Cennik!$A$4:$B892, 2, FALSE()) * K53 + VLOOKUP(L53,Cennik!$A$4:$B892, 2, FALSE()) * M53 + VLOOKUP(N53,Cennik!$A$4:$B892, 2, FALSE()) * O53 + VLOOKUP(P53,Cennik!$A$4:$B892, 2, FALSE()) * Q53 + VLOOKUP(R53,Cennik!$A$4:$B892, 2, FALSE()) * S53 + VLOOKUP(T53,Cennik!$A$4:$B892, 2, FALSE()) * U53 + VLOOKUP(V53,Cennik!$A$4:$B892, 2, FALSE()) * W53 + VLOOKUP(X53,Cennik!$A$4:$B892, 2, FALSE()) * Y53 + VLOOKUP(Z53,Cennik!$A$4:$B892, 2, FALSE()) * AA53 + VLOOKUP(AB53,Cennik!$A$4:$B892, 2, FALSE() * AC53),"Brak wartości") -> Brak wartości
A54: Rzeźbiony stół 2 | B54: 5 | C54: Ten stół z pewnością przyciągnie wzrok. Rzeźby na nogach zrobią wrażenie, a drewno będzie wyglądać bardzo solidnie. | D54: TABLEBOOK_WITHOUTBOOK_RICH_01.3ds | E54: TABLEBOOK_WITHOUTBOOK_RICH_01.ASC | F54: Deska z szlachetnego drewna | G54: 25 | H54: Szlachetne drewno | I54: 3 | J54: Gwoździe | K54: 8 | L54: Smoła | M54: 2 | N54: - | P54: - | R54: - | T54: - | V54: - | X54: - | Z54: - | AB54: - | AD54: 50 | AE54: Vob | AF54: table | AG54: TRUE | AH54: TRUE | AI54: =IFERROR(VLOOKUP(F54,Cennik!$A$4:$B892, 2, FALSE()) * G54 + VLOOKUP(H54,Cennik!$A$4:$B892, 2, FALSE()) * I54 + VLOOKUP(J54,Cennik!$A$4:$B892, 2, FALSE()) * K54 + VLOOKUP(L54,Cennik!$A$4:$B892, 2, FALSE()) * M54 + VLOOKUP(N54,Cennik!$A$4:$B892, 2, FALSE()) * O54 + VLOOKUP(P54,Cennik!$A$4:$B892, 2, FALSE()) * Q54 + VLOOKUP(R54,Cennik!$A$4:$B892, 2, FALSE()) * S54 + VLOOKUP(T54,Cennik!$A$4:$B892, 2, FALSE()) * U54 + VLOOKUP(V54,Cennik!$A$4:$B892, 2, FALSE()) * W54 + VLOOKUP(X54,Cennik!$A$4:$B892, 2, FALSE()) * Y54 + VLOOKUP(Z54,Cennik!$A$4:$B892, 2, FALSE()) * AA54 + VLOOKUP(AB54,Cennik!$A$4:$B892, 2, FALSE() * AC54),"Brak wartości") -> Brak wartości
F55: - | H55: - | J55: - | L55: - | N55: - | P55: - | R55: - | T55: - | V55: - | X55: - | Z55: - | AB55: -
F56: - | H56: - | J56: - | L56: - | N56: - | P56: - | R56: - | T56: - | V56: - | X56: - | Z56: - | AB56: -
F57: - | H57: - | J57: - | L57: - | N57: - | P57: - | R57: - | T57: - | V57: - | X57: - | Z57: - | AB57: -
A58: Siedzisko z kamienia | B58: 0 | C58: Może i twarde, ale będzie chociaż gdzie usiąść. | D58: CHAIR_2_NC.ASC | E58: CHAIR_2_NC.ASC | F58: Bryłka Kamienia | G58: 5 | H58: - | J58: - | L58: - | N58: - | P58: - | R58: - | T58: - | V58: - | X58: - | Z58: - | AB58: - | AD58: 15 | AE58: MobInter | AF58: chair | AG58: TRUE | AH58: TRUE | AI58: =IFERROR(VLOOKUP(F58,Cennik!$A$4:$B892, 2, FALSE()) * G58 + VLOOKUP(H58,Cennik!$A$4:$B892, 2, FALSE()) * I58 + VLOOKUP(J58,Cennik!$A$4:$B892, 2, FALSE()) * K58 + VLOOKUP(L58,Cennik!$A$4:$B892, 2, FALSE()) * M58 + VLOOKUP(N58,Cennik!$A$4:$B892, 2, FALSE()) * O58 + VLOOKUP(P58,Cennik!$A$4:$B892, 2, FALSE()) * Q58 + VLOOKUP(R58,Cennik!$A$4:$B892, 2, FALSE()) * S58 + VLOOKUP(T58,Cennik!$A$4:$B892, 2, FALSE()) * U58 + VLOOKUP(V58,Cennik!$A$4:$B892, 2, FALSE()) * W58 + VLOOKUP(X58,Cennik!$A$4:$B892, 2, FALSE()) * Y58 + VLOOKUP(Z58,Cennik!$A$4:$B892, 2, FALSE()) * AA58 + VLOOKUP(AB58,Cennik!$A$4:$B892, 2, FALSE() * AC58),"Brak wartości") -> 2.5
A59: Siedzisko z pniaka | B59: 0 | C59: Siedzisko z pniaka to unikatowe rozwiązanie dla osób, które cenią sobie naturalność i oryginalność w swoim otoczeniu. | D59: CHAIR_1_PC.ASC | E59: CHAIR_1_PC.ASC | F59: Pocięte miękkie drewno | G59: 5 | H59: - | J59: - | L59: - | N59: - | P59: - | R59: - | T59: - | V59: - | X59: - | Z59: - | AB59: - | AD59: 10 | AE59: MobInter | AF59: chair | AG59: TRUE | AH59: TRUE | AI59: =IFERROR(VLOOKUP(F59,Cennik!$A$4:$B892, 2, FALSE()) * G59 + VLOOKUP(H59,Cennik!$A$4:$B892, 2, FALSE()) * I59 + VLOOKUP(J59,Cennik!$A$4:$B892, 2, FALSE()) * K59 + VLOOKUP(L59,Cennik!$A$4:$B892, 2, FALSE()) * M59 + VLOOKUP(N59,Cennik!$A$4:$B892, 2, FALSE()) * O59 + VLOOKUP(P59,Cennik!$A$4:$B892, 2, FALSE()) * Q59 + VLOOKUP(R59,Cennik!$A$4:$B892, 2, FALSE()) * S59 + VLOOKUP(T59,Cennik!$A$4:$B892, 2, FALSE()) * U59 + VLOOKUP(V59,Cennik!$A$4:$B892, 2, FALSE()) * W59 + VLOOKUP(X59,Cennik!$A$4:$B892, 2, FALSE()) * Y59 + VLOOKUP(Z59,Cennik!$A$4:$B892, 2, FALSE()) * AA59 + VLOOKUP(AB59,Cennik!$A$4:$B892, 2, FALSE() * AC59),"Brak wartości") -> 11.5
A60: Ławka z kłody | B60: 0 | C60: Taka ławka to dowód na to, że z prostych przedmiotów można stworzyć coś użytecznego i estetycznego. | D60: BENCH_1_OC.ASC | E60: BENCH_1_OC.ASC | F60: Pocięte miękkie drewno | G60: 5 | H60: - | J60: - | L60: - | N60: - | P60: - | R60: - | T60: - | V60: - | X60: - | Z60: - | AB60: - | AD60: 20 | AE60: MobInter | AF60: chair | AG60: TRUE | AH60: TRUE | AI60: =IFERROR(VLOOKUP(F60,Cennik!$A$4:$B892, 2, FALSE()) * G60 + VLOOKUP(H60,Cennik!$A$4:$B892, 2, FALSE()) * I60 + VLOOKUP(J60,Cennik!$A$4:$B892, 2, FALSE()) * K60 + VLOOKUP(L60,Cennik!$A$4:$B892, 2, FALSE()) * M60 + VLOOKUP(N60,Cennik!$A$4:$B892, 2, FALSE()) * O60 + VLOOKUP(P60,Cennik!$A$4:$B892, 2, FALSE()) * Q60 + VLOOKUP(R60,Cennik!$A$4:$B892, 2, FALSE()) * S60 + VLOOKUP(T60,Cennik!$A$4:$B892, 2, FALSE()) * U60 + VLOOKUP(V60,Cennik!$A$4:$B892, 2, FALSE()) * W60 + VLOOKUP(X60,Cennik!$A$4:$B892, 2, FALSE()) * Y60 + VLOOKUP(Z60,Cennik!$A$4:$B892, 2, FALSE()) * AA60 + VLOOKUP(AB60,Cennik!$A$4:$B892, 2, FALSE() * AC60),"Brak wartości") -> 11.5
A61: Krzesło 1 | B61: 1 | C61: Wybierając krzesło, należy zwrócić uwagę na jego kształt i rozmiar, aby zapewnić optymalne warunki do siedzenia i uniknąć bólu pleców czy karku. | D61: CHAIR_1_OC.ASC | E61: CHAIR_1_OC.ASC | F61: Deska z miękiego drewna | G61: 5 | H61: Gwoździe | I61: 2 | J61: Smoła | K61: 1 | L61: - | N61: - | P61: - | R61: - | T61: - | V61: - | X61: - | Z61: - | AB61: - | AD61: 10 | AE61: MobInter | AF61: chair | AG61: TRUE | AH61: TRUE | AI61: =IFERROR(VLOOKUP(F61,Cennik!$A$4:$B892, 2, FALSE()) * G61 + VLOOKUP(H61,Cennik!$A$4:$B892, 2, FALSE()) * I61 + VLOOKUP(J61,Cennik!$A$4:$B892, 2, FALSE()) * K61 + VLOOKUP(L61,Cennik!$A$4:$B892, 2, FALSE()) * M61 + VLOOKUP(N61,Cennik!$A$4:$B892, 2, FALSE()) * O61 + VLOOKUP(P61,Cennik!$A$4:$B892, 2, FALSE()) * Q61 + VLOOKUP(R61,Cennik!$A$4:$B892, 2, FALSE()) * S61 + VLOOKUP(T61,Cennik!$A$4:$B892, 2, FALSE()) * U61 + VLOOKUP(V61,Cennik!$A$4:$B892, 2, FALSE()) * W61 + VLOOKUP(X61,Cennik!$A$4:$B892, 2, FALSE()) * Y61 + VLOOKUP(Z61,Cennik!$A$4:$B892, 2, FALSE()) * AA61 + VLOOKUP(AB61,Cennik!$A$4:$B892, 2, FALSE() * AC61),"Brak wartości") -> Brak wartości
A62: Krzesło 2 | B62: 1 | C62: Wybierając krzesło, należy zwrócić uwagę na jego kształt i rozmiar, aby zapewnić optymalne warunki do siedzenia i uniknąć bólu pleców czy karku. | D62: CHAIR_2_OC.ASC | E62: CHAIR_2_OC.ASC | F62: Deska z miękiego drewna | G62: 5 | H62: Gwoździe | I62: 2 | J62: Smoła | K62: 1 | L62: - | N62: - | P62: - | R62: - | T62: - | V62: - | X62: - | Z62: - | AB62: - | AD62: 10 | AE62: MobInter | AF62: chair | AG62: TRUE | AH62: TRUE | AI62: =IFERROR(VLOOKUP(F62,Cennik!$A$4:$B892, 2, FALSE()) * G62 + VLOOKUP(H62,Cennik!$A$4:$B892, 2, FALSE()) * I62 + VLOOKUP(J62,Cennik!$A$4:$B892, 2, FALSE()) * K62 + VLOOKUP(L62,Cennik!$A$4:$B892, 2, FALSE()) * M62 + VLOOKUP(N62,Cennik!$A$4:$B892, 2, FALSE()) * O62 + VLOOKUP(P62,Cennik!$A$4:$B892, 2, FALSE()) * Q62 + VLOOKUP(R62,Cennik!$A$4:$B892, 2, FALSE()) * S62 + VLOOKUP(T62,Cennik!$A$4:$B892, 2, FALSE()) * U62 + VLOOKUP(V62,Cennik!$A$4:$B892, 2, FALSE()) * W62 + VLOOKUP(X62,Cennik!$A$4:$B892, 2, FALSE()) * Y62 + VLOOKUP(Z62,Cennik!$A$4:$B892, 2, FALSE()) * AA62 + VLOOKUP(AB62,Cennik!$A$4:$B892, 2, FALSE() * AC62),"Brak wartości") -> Brak wartości
A63: Krzesło 3 | B63: 1 | C63: Wybierając krzesło, należy zwrócić uwagę na jego kształt i rozmiar, aby zapewnić optymalne warunki do siedzenia i uniknąć bólu pleców czy karku. | D63: CHAIR_3_OC.ASC | E63: CHAIR_3_OC.ASC | F63: Deska z miękiego drewna | G63: 5 | H63: Gwoździe | I63: 2 | J63: Smoła | K63: 1 | L63: - | N63: - | P63: - | R63: - | T63: - | V63: - | X63: - | Z63: - | AB63: - | AD63: 10 | AE63: MobInter | AF63: chair | AG63: TRUE | AH63: TRUE | AI63: =IFERROR(VLOOKUP(F63,Cennik!$A$4:$B892, 2, FALSE()) * G63 + VLOOKUP(H63,Cennik!$A$4:$B892, 2, FALSE()) * I63 + VLOOKUP(J63,Cennik!$A$4:$B892, 2, FALSE()) * K63 + VLOOKUP(L63,Cennik!$A$4:$B892, 2, FALSE()) * M63 + VLOOKUP(N63,Cennik!$A$4:$B892, 2, FALSE()) * O63 + VLOOKUP(P63,Cennik!$A$4:$B892, 2, FALSE()) * Q63 + VLOOKUP(R63,Cennik!$A$4:$B892, 2, FALSE()) * S63 + VLOOKUP(T63,Cennik!$A$4:$B892, 2, FALSE()) * U63 + VLOOKUP(V63,Cennik!$A$4:$B892, 2, FALSE()) * W63 + VLOOKUP(X63,Cennik!$A$4:$B892, 2, FALSE()) * Y63 + VLOOKUP(Z63,Cennik!$A$4:$B892, 2, FALSE()) * AA63 + VLOOKUP(AB63,Cennik!$A$4:$B892, 2, FALSE() * AC63),"Brak wartości") -> Brak wartości
A64: Krzesło 4 | B64: 1 | C64: Wybierając krzesło, należy zwrócić uwagę na jego kształt i rozmiar, aby zapewnić optymalne warunki do siedzenia i uniknąć bólu pleców czy karku. | D64: CHAIR_3_PC.ASC | E64: CHAIR_3_PC.ASC | F64: Deska z miękiego drewna | G64: 5 | H64: Gwoździe | I64: 2 | J64: Smoła | K64: 1 | L64: - | N64: - | P64: - | R64: - | T64: - | V64: - | X64: - | Z64: - | AB64: - | AD64: 10 | AE64: MobInter | AF64: chair | AG64: TRUE | AH64: TRUE | AI64: =IFERROR(VLOOKUP(F64,Cennik!$A$4:$B892, 2, FALSE()) * G64 + VLOOKUP(H64,Cennik!$A$4:$B892, 2, FALSE()) * I64 + VLOOKUP(J64,Cennik!$A$4:$B892, 2, FALSE()) * K64 + VLOOKUP(L64,Cennik!$A$4:$B892, 2, FALSE()) * M64 + VLOOKUP(N64,Cennik!$A$4:$B892, 2, FALSE()) * O64 + VLOOKUP(P64,Cennik!$A$4:$B892, 2, FALSE()) * Q64 + VLOOKUP(R64,Cennik!$A$4:$B892, 2, FALSE()) * S64 + VLOOKUP(T64,Cennik!$A$4:$B892, 2, FALSE()) * U64 + VLOOKUP(V64,Cennik!$A$4:$B892, 2, FALSE()) * W64 + VLOOKUP(X64,Cennik!$A$4:$B892, 2, FALSE()) * Y64 + VLOOKUP(Z64,Cennik!$A$4:$B892, 2, FALSE()) * AA64 + VLOOKUP(AB64,Cennik!$A$4:$B892, 2, FALSE() * AC64),"Brak wartości") -> Brak wartości
A65: Ława | B65: 1 | C65: Ława to nie tylko miejsce do siedzenia, ale także miejsce, gdzie ludzie dzielą się swoimi historiami i doświadczeniami. | D65: BENCH_2_OC.ASC | E65: BENCH_2_OC.ASC | F65: Deska z miękiego drewna | G65: 5 | H65: Gwoździe | I65: 3 | J65: Smoła | K65: 1 | L65: - | N65: - | P65: - | R65: - | T65: - | V65: - | X65: - | Z65: - | AB65: - | AD65: 20 | AE65: MobInter | AF65: chair | AG65: TRUE | AH65: TRUE | AI65: =IFERROR(VLOOKUP(F65,Cennik!$A$4:$B892, 2, FALSE()) * G65 + VLOOKUP(H65,Cennik!$A$4:$B892, 2, FALSE()) * I65 + VLOOKUP(J65,Cennik!$A$4:$B892, 2, FALSE()) * K65 + VLOOKUP(L65,Cennik!$A$4:$B892, 2, FALSE()) * M65 + VLOOKUP(N65,Cennik!$A$4:$B892, 2, FALSE()) * O65 + VLOOKUP(P65,Cennik!$A$4:$B892, 2, FALSE()) * Q65 + VLOOKUP(R65,Cennik!$A$4:$B892, 2, FALSE()) * S65 + VLOOKUP(T65,Cennik!$A$4:$B892, 2, FALSE()) * U65 + VLOOKUP(V65,Cennik!$A$4:$B892, 2, FALSE()) * W65 + VLOOKUP(X65,Cennik!$A$4:$B892, 2, FALSE()) * Y65 + VLOOKUP(Z65,Cennik!$A$4:$B892, 2, FALSE()) * AA65 + VLOOKUP(AB65,Cennik!$A$4:$B892, 2, FALSE() * AC65),"Brak wartości") -> Brak wartości
A66: Prosta ławka | B66: 1 | C66: Prosta ławka może wydawać się niepozorna, ale czasem to właśnie na niej znajdujemy spokój i odpoczynek. | D66: BENCH_WOOD.ASC | E66: BENCH_WOOD.ASC | F66: Deska z miękiego drewna | G66: 5 | H66: Gwoździe | I66: 3 | J66: Smoła | K66: 1 | L66: - | N66: - | P66: - | R66: - | T66: - | V66: - | X66: - | Z66: - | AB66: - | AD66: 20 | AE66: MobInter | AF66: chair | AG66: TRUE | AH66: TRUE | AI66: =IFERROR(VLOOKUP(F66,Cennik!$A$4:$B892, 2, FALSE()) * G66 + VLOOKUP(H66,Cennik!$A$4:$B892, 2, FALSE()) * I66 + VLOOKUP(J66,Cennik!$A$4:$B892, 2, FALSE()) * K66 + VLOOKUP(L66,Cennik!$A$4:$B892, 2, FALSE()) * M66 + VLOOKUP(N66,Cennik!$A$4:$B892, 2, FALSE()) * O66 + VLOOKUP(P66,Cennik!$A$4:$B892, 2, FALSE()) * Q66 + VLOOKUP(R66,Cennik!$A$4:$B892, 2, FALSE()) * S66 + VLOOKUP(T66,Cennik!$A$4:$B892, 2, FALSE()) * U66 + VLOOKUP(V66,Cennik!$A$4:$B892, 2, FALSE()) * W66 + VLOOKUP(X66,Cennik!$A$4:$B892, 2, FALSE()) * Y66 + VLOOKUP(Z66,Cennik!$A$4:$B892, 2, FALSE()) * AA66 + VLOOKUP(AB66,Cennik!$A$4:$B892, 2, FALSE() * AC66),"Brak wartości") -> Brak wartości
A67: Bukowa ławka | B67: 2 | C67: Nie ma nic lepszego niż odpoczynek na dobrej ławce po długiej wędrówce. Ta ławka z pewnością spełnia ich oczekiwania. | D67: BENCH_BLACK_01_KOZA.ASC | E67: BENCH_BLACK_01_KOZA.ASC | F67: Deska z twardego drewna | G67: 8 | H67: Gwoździe | I67: 4 | J67: Smoła | K67: 2 | L67: - | N67: - | P67: - | R67: - | T67: - | V67: - | X67: - | Z67: - | AB67: - | AD67: 25 | AE67: MobInter | AF67: chair | AG67: TRUE | AH67: TRUE | AI67: =IFERROR(VLOOKUP(F67,Cennik!$A$4:$B892, 2, FALSE()) * G67 + VLOOKUP(H67,Cennik!$A$4:$B892, 2, FALSE()) * I67 + VLOOKUP(J67,Cennik!$A$4:$B892, 2, FALSE()) * K67 + VLOOKUP(L67,Cennik!$A$4:$B892, 2, FALSE()) * M67 + VLOOKUP(N67,Cennik!$A$4:$B892, 2, FALSE()) * O67 + VLOOKUP(P67,Cennik!$A$4:$B892, 2, FALSE()) * Q67 + VLOOKUP(R67,Cennik!$A$4:$B892, 2, FALSE()) * S67 + VLOOKUP(T67,Cennik!$A$4:$B892, 2, FALSE()) * U67 + VLOOKUP(V67,Cennik!$A$4:$B892, 2, FALSE()) * W67 + VLOOKUP(X67,Cennik!$A$4:$B892, 2, FALSE()) * Y67 + VLOOKUP(Z67,Cennik!$A$4:$B892, 2, FALSE()) * AA67 + VLOOKUP(AB67,Cennik!$A$4:$B892, 2, FALSE() * AC67),"Brak wartości") -> Brak wartości
A68: Bukowa ławka 2 | B68: 2 | C68: Nie ma nic lepszego niż odpoczynek na dobrej ławce po długiej wędrówce. Ta ławka z pewnością spełnia ich oczekiwania. | D68: BENCH_WOOD_BLACK_01_KOZA.ASC | E68: BENCH_WOOD_BLACK_01_KOZA.ASC | F68: Deska z twardego drewna | G68: 8 | H68: Gwoździe | I68: 4 | J68: Smoła | K68: 2 | L68: - | N68: - | P68: - | R68: - | T68: - | V68: - | X68: - | Z68: - | AB68: - | AD68: 25 | AE68: MobInter | AF68: chair | AG68: TRUE | AH68: TRUE | AI68: =IFERROR(VLOOKUP(F68,Cennik!$A$4:$B892, 2, FALSE()) * G68 + VLOOKUP(H68,Cennik!$A$4:$B892, 2, FALSE()) * I68 + VLOOKUP(J68,Cennik!$A$4:$B892, 2, FALSE()) * K68 + VLOOKUP(L68,Cennik!$A$4:$B892, 2, FALSE()) * M68 + VLOOKUP(N68,Cennik!$A$4:$B892, 2, FALSE()) * O68 + VLOOKUP(P68,Cennik!$A$4:$B892, 2, FALSE()) * Q68 + VLOOKUP(R68,Cennik!$A$4:$B892, 2, FALSE()) * S68 + VLOOKUP(T68,Cennik!$A$4:$B892, 2, FALSE()) * U68 + VLOOKUP(V68,Cennik!$A$4:$B892, 2, FALSE()) * W68 + VLOOKUP(X68,Cennik!$A$4:$B892, 2, FALSE()) * Y68 + VLOOKUP(Z68,Cennik!$A$4:$B892, 2, FALSE()) * AA68 + VLOOKUP(AB68,Cennik!$A$4:$B892, 2, FALSE() * AC68),"Brak wartości") -> Brak wartości
A69: Bukowy taboret | B69: 2 | C69: Wybierając krzesło, należy zwrócić uwagę na jego kształt i rozmiar, aby zapewnić optymalne warunki do siedzenia i uniknąć bólu pleców czy karku. | D69: CHAIR_BLACK_01_KOZA.ASC | E69: CHAIR_BLACK_01_KOZA.ASC | F69: Deska z twardego drewna | G69: 5 | H69: Gwoździe | I69: 3 | J69: Smoła | K69: 1 | L69: Żelazny pręt | M69: 1 | N69: - | P69: - | R69: - | T69: - | V69: - | X69: - | Z69: - | AB69: - | AD69: 15 | AE69: MobInter | AF69: chair | AG69: TRUE | AH69: TRUE | AI69: =IFERROR(VLOOKUP(F69,Cennik!$A$4:$B892, 2, FALSE()) * G69 + VLOOKUP(H69,Cennik!$A$4:$B892, 2, FALSE()) * I69 + VLOOKUP(J69,Cennik!$A$4:$B892, 2, FALSE()) * K69 + VLOOKUP(L69,Cennik!$A$4:$B892, 2, FALSE()) * M69 + VLOOKUP(N69,Cennik!$A$4:$B892, 2, FALSE()) * O69 + VLOOKUP(P69,Cennik!$A$4:$B892, 2, FALSE()) * Q69 + VLOOKUP(R69,Cennik!$A$4:$B892, 2, FALSE()) * S69 + VLOOKUP(T69,Cennik!$A$4:$B892, 2, FALSE()) * U69 + VLOOKUP(V69,Cennik!$A$4:$B892, 2, FALSE()) * W69 + VLOOKUP(X69,Cennik!$A$4:$B892, 2, FALSE()) * Y69 + VLOOKUP(Z69,Cennik!$A$4:$B892, 2, FALSE()) * AA69 + VLOOKUP(AB69,Cennik!$A$4:$B892, 2, FALSE() * AC69),"Brak wartości") -> Brak wartości
A70: Bukowe krzesło | B70: 2 | C70: Wybierając krzesło, należy zwrócić uwagę na jego kształt i rozmiar, aby zapewnić optymalne warunki do siedzenia i uniknąć bólu pleców czy karku. | D70: THRONENEW_BLACK_01_KOZA.ASC | E70: THRONENEW_BLACK_01_KOZA.ASC | F70: Deska z twardego drewna | G70: 5 | H70: Gwoździe | I70: 3 | J70: Smoła | K70: 1 | L70: Żelazny pręt | M70: 1 | N70: - | P70: - | R70: - | T70: - | V70: - | X70: - | Z70: - | AB70: - | AD70: 15 | AE70: MobInter | AF70: chair | AG70: TRUE | AH70: TRUE | AI70: =IFERROR(VLOOKUP(F70,Cennik!$A$4:$B892, 2, FALSE()) * G70 + VLOOKUP(H70,Cennik!$A$4:$B892, 2, FALSE()) * I70 + VLOOKUP(J70,Cennik!$A$4:$B892, 2, FALSE()) * K70 + VLOOKUP(L70,Cennik!$A$4:$B892, 2, FALSE()) * M70 + VLOOKUP(N70,Cennik!$A$4:$B892, 2, FALSE()) * O70 + VLOOKUP(P70,Cennik!$A$4:$B892, 2, FALSE()) * Q70 + VLOOKUP(R70,Cennik!$A$4:$B892, 2, FALSE()) * S70 + VLOOKUP(T70,Cennik!$A$4:$B892, 2, FALSE()) * U70 + VLOOKUP(V70,Cennik!$A$4:$B892, 2, FALSE()) * W70 + VLOOKUP(X70,Cennik!$A$4:$B892, 2, FALSE()) * Y70 + VLOOKUP(Z70,Cennik!$A$4:$B892, 2, FALSE()) * AA70 + VLOOKUP(AB70,Cennik!$A$4:$B892, 2, FALSE() * AC70),"Brak wartości") -> Brak wartości
A71: Krzesło 5 | B71: 2 | C71: Wybierając krzesło, należy zwrócić uwagę na jego kształt i rozmiar, aby zapewnić optymalne warunki do siedzenia i uniknąć bólu pleców czy karku. | D71: CHAIR_NW_NORMAL_01.ASC | E71: CHAIR_NW_NORMAL_01.ASC | F71: Deska z twardego drewna | G71: 5 | H71: Gwoździe | I71: 3 | J71: Smoła | K71: 1 | L71: Żelazny pręt | M71: 1 | N71: - | P71: - | R71: - | T71: - | V71: - | X71: - | Z71: - | AB71: - | AD71: 15 | AE71: MobInter | AF71: chair | AG71: TRUE | AH71: TRUE | AI71: =IFERROR(VLOOKUP(F71,Cennik!$A$4:$B892, 2, FALSE()) * G71 + VLOOKUP(H71,Cennik!$A$4:$B892, 2, FALSE()) * I71 + VLOOKUP(J71,Cennik!$A$4:$B892, 2, FALSE()) * K71 + VLOOKUP(L71,Cennik!$A$4:$B892, 2, FALSE()) * M71 + VLOOKUP(N71,Cennik!$A$4:$B892, 2, FALSE()) * O71 + VLOOKUP(P71,Cennik!$A$4:$B892, 2, FALSE()) * Q71 + VLOOKUP(R71,Cennik!$A$4:$B892, 2, FALSE()) * S71 + VLOOKUP(T71,Cennik!$A$4:$B892, 2, FALSE()) * U71 + VLOOKUP(V71,Cennik!$A$4:$B892, 2, FALSE()) * W71 + VLOOKUP(X71,Cennik!$A$4:$B892, 2, FALSE()) * Y71 + VLOOKUP(Z71,Cennik!$A$4:$B892, 2, FALSE()) * AA71 + VLOOKUP(AB71,Cennik!$A$4:$B892, 2, FALSE() * AC71),"Brak wartości") -> Brak wartości
A72: Krzesło 6 | B72: 2 | C72: Wybierając krzesło, należy zwrócić uwagę na jego kształt i rozmiar, aby zapewnić optymalne warunki do siedzenia i uniknąć bólu pleców czy karku. | D72: GSCHAIR1_GS01_KWIATEK.ASC | E72: GSCHAIR1_GS01_KWIATEK.ASC | F72: Deska z twardego drewna | G72: 5 | H72: Gwoździe | I72: 3 | J72: Smoła | K72: 1 | L72: Żelazny pręt | M72: 1 | N72: - | P72: - | R72: - | T72: - | V72: - | X72: - | Z72: - | AB72: - | AD72: 15 | AE72: MobInter | AF72: chair | AG72: TRUE | AH72: TRUE | AI72: =IFERROR(VLOOKUP(F72,Cennik!$A$4:$B892, 2, FALSE()) * G72 + VLOOKUP(H72,Cennik!$A$4:$B892, 2, FALSE()) * I72 + VLOOKUP(J72,Cennik!$A$4:$B892, 2, FALSE()) * K72 + VLOOKUP(L72,Cennik!$A$4:$B892, 2, FALSE()) * M72 + VLOOKUP(N72,Cennik!$A$4:$B892, 2, FALSE()) * O72 + VLOOKUP(P72,Cennik!$A$4:$B892, 2, FALSE()) * Q72 + VLOOKUP(R72,Cennik!$A$4:$B892, 2, FALSE()) * S72 + VLOOKUP(T72,Cennik!$A$4:$B892, 2, FALSE()) * U72 + VLOOKUP(V72,Cennik!$A$4:$B892, 2, FALSE()) * W72 + VLOOKUP(X72,Cennik!$A$4:$B892, 2, FALSE()) * Y72 + VLOOKUP(Z72,Cennik!$A$4:$B892, 2, FALSE()) * AA72 + VLOOKUP(AB72,Cennik!$A$4:$B892, 2, FALSE() * AC72),"Brak wartości") -> Brak wartości
A73: Krzesło 7 | B73: 2 | C73: Wybierając krzesło, należy zwrócić uwagę na jego kształt i rozmiar, aby zapewnić optymalne warunki do siedzenia i uniknąć bólu pleców czy karku. | D73: GSCHAIR1_GS03_KWIATEK.ASC | E73: GSCHAIR1_GS03_KWIATEK.ASC | F73: Deska z twardego drewna | G73: 5 | H73: Gwoździe | I73: 3 | J73: Smoła | K73: 1 | L73: Żelazny pręt | M73: 1 | N73: - | P73: - | R73: - | T73: - | V73: - | X73: - | Z73: - | AB73: - | AD73: 15 | AE73: MobInter | AF73: chair | AG73: TRUE | AH73: TRUE | AI73: =IFERROR(VLOOKUP(F73,Cennik!$A$4:$B892, 2, FALSE()) * G73 + VLOOKUP(H73,Cennik!$A$4:$B892, 2, FALSE()) * I73 + VLOOKUP(J73,Cennik!$A$4:$B892, 2, FALSE()) * K73 + VLOOKUP(L73,Cennik!$A$4:$B892, 2, FALSE()) * M73 + VLOOKUP(N73,Cennik!$A$4:$B892, 2, FALSE()) * O73 + VLOOKUP(P73,Cennik!$A$4:$B892, 2, FALSE()) * Q73 + VLOOKUP(R73,Cennik!$A$4:$B892, 2, FALSE()) * S73 + VLOOKUP(T73,Cennik!$A$4:$B892, 2, FALSE()) * U73 + VLOOKUP(V73,Cennik!$A$4:$B892, 2, FALSE()) * W73 + VLOOKUP(X73,Cennik!$A$4:$B892, 2, FALSE()) * Y73 + VLOOKUP(Z73,Cennik!$A$4:$B892, 2, FALSE()) * AA73 + VLOOKUP(AB73,Cennik!$A$4:$B892, 2, FALSE() * AC73),"Brak wartości") -> Brak wartości
A74: Dębowa ławka | B74: 3 | C74: Nie ma nic lepszego niż odpoczynek na dobrej ławce po długiej wędrówce. Ta ławka z pewnością spełnia ich oczekiwania. | D74: BENCH_BROWN_01_KOZA.ASC | E74: BENCH_BROWN_01_KOZA.ASC | F74: Deska z szlachetnego drewna | G74: 10 | H74: Gwoździe | I74: 4 | J74: Smoła | K74: 1 | L74: - | N74: - | P74: - | R74: - | T74: - | V74: - | X74: - | Z74: - | AB74: - | AD74: 30 | AE74: MobInter | AF74: chair | AG74: TRUE | AH74: TRUE | AI74: =IFERROR(VLOOKUP(F74,Cennik!$A$4:$B892, 2, FALSE()) * G74 + VLOOKUP(H74,Cennik!$A$4:$B892, 2, FALSE()) * I74 + VLOOKUP(J74,Cennik!$A$4:$B892, 2, FALSE()) * K74 + VLOOKUP(L74,Cennik!$A$4:$B892, 2, FALSE()) * M74 + VLOOKUP(N74,Cennik!$A$4:$B892, 2, FALSE()) * O74 + VLOOKUP(P74,Cennik!$A$4:$B892, 2, FALSE()) * Q74 + VLOOKUP(R74,Cennik!$A$4:$B892, 2, FALSE()) * S74 + VLOOKUP(T74,Cennik!$A$4:$B892, 2, FALSE()) * U74 + VLOOKUP(V74,Cennik!$A$4:$B892, 2, FALSE()) * W74 + VLOOKUP(X74,Cennik!$A$4:$B892, 2, FALSE()) * Y74 + VLOOKUP(Z74,Cennik!$A$4:$B892, 2, FALSE()) * AA74 + VLOOKUP(AB74,Cennik!$A$4:$B892, 2, FALSE() * AC74),"Brak wartości") -> Brak wartości
A75: Dębowa ławka 2 | B75: 3 | C75: Nie ma nic lepszego niż odpoczynek na dobrej ławce po długiej wędrówce. Ta ławka z pewnością spełnia ich oczekiwania. | D75: BENCH_WOOD_BROWN_01_KOZA.ASC | E75: BENCH_WOOD_BROWN_01_KOZA.ASC | F75: Deska z szlachetnego drewna | G75: 10 | H75: Gwoździe | I75: 4 | J75: Smoła | K75: 1 | L75: - | N75: - | P75: - | R75: - | T75: - | V75: - | X75: - | Z75: - | AB75: - | AD75: 30 | AE75: MobInter | AF75: chair | AG75: TRUE | AH75: TRUE | AI75: =IFERROR(VLOOKUP(F75,Cennik!$A$4:$B892, 2, FALSE()) * G75 + VLOOKUP(H75,Cennik!$A$4:$B892, 2, FALSE()) * I75 + VLOOKUP(J75,Cennik!$A$4:$B892, 2, FALSE()) * K75 + VLOOKUP(L75,Cennik!$A$4:$B892, 2, FALSE()) * M75 + VLOOKUP(N75,Cennik!$A$4:$B892, 2, FALSE()) * O75 + VLOOKUP(P75,Cennik!$A$4:$B892, 2, FALSE()) * Q75 + VLOOKUP(R75,Cennik!$A$4:$B892, 2, FALSE()) * S75 + VLOOKUP(T75,Cennik!$A$4:$B892, 2, FALSE()) * U75 + VLOOKUP(V75,Cennik!$A$4:$B892, 2, FALSE()) * W75 + VLOOKUP(X75,Cennik!$A$4:$B892, 2, FALSE()) * Y75 + VLOOKUP(Z75,Cennik!$A$4:$B892, 2, FALSE()) * AA75 + VLOOKUP(AB75,Cennik!$A$4:$B892, 2, FALSE() * AC75),"Brak wartości") -> Brak wartości
A76: Dębowy taboret | B76: 3 | C76: Wybierając krzesło, należy zwrócić uwagę na jego kształt i rozmiar, aby zapewnić optymalne warunki do siedzenia i uniknąć bólu pleców czy karku. | D76: CHAIR_BROWN_01_KOZA.ASC | E76: CHAIR_BROWN_01_KOZA.ASC | F76: Deska z szlachetnego drewna | G76: 7 | H76: Gwoździe | I76: 6 | J76: Smoła | K76: 1 | L76: - | N76: - | P76: - | R76: - | T76: - | V76: - | X76: - | Z76: - | AB76: - | AD76: 15 | AE76: MobInter | AF76: chair | AG76: TRUE | AH76: TRUE | AI76: =IFERROR(VLOOKUP(F76,Cennik!$A$4:$B892, 2, FALSE()) * G76 + VLOOKUP(H76,Cennik!$A$4:$B892, 2, FALSE()) * I76 + VLOOKUP(J76,Cennik!$A$4:$B892, 2, FALSE()) * K76 + VLOOKUP(L76,Cennik!$A$4:$B892, 2, FALSE()) * M76 + VLOOKUP(N76,Cennik!$A$4:$B892, 2, FALSE()) * O76 + VLOOKUP(P76,Cennik!$A$4:$B892, 2, FALSE()) * Q76 + VLOOKUP(R76,Cennik!$A$4:$B892, 2, FALSE()) * S76 + VLOOKUP(T76,Cennik!$A$4:$B892, 2, FALSE()) * U76 + VLOOKUP(V76,Cennik!$A$4:$B892, 2, FALSE()) * W76 + VLOOKUP(X76,Cennik!$A$4:$B892, 2, FALSE()) * Y76 + VLOOKUP(Z76,Cennik!$A$4:$B892, 2, FALSE()) * AA76 + VLOOKUP(AB76,Cennik!$A$4:$B892, 2, FALSE() * AC76),"Brak wartości") -> Brak wartości
A77: Dębowe krzesło | B77: 3 | C77: Wybierając krzesło, należy zwrócić uwagę na jego kształt i rozmiar, aby zapewnić optymalne warunki do siedzenia i uniknąć bólu pleców czy karku. | D77: THRONENEW_BROWN_01_KOZA.ASC | E77: THRONENEW_BROWN_01_KOZA.ASC | F77: Deska z szlachetnego drewna | G77: 7 | H77: Gwoździe | I77: 6 | J77: Smoła | K77: 1 | L77: - | N77: - | P77: - | R77: - | T77: - | V77: - | X77: - | Z77: - | AB77: - | AD77: 15 | AE77: MobInter | AF77: chair | AG77: TRUE | AH77: TRUE | AI77: =IFERROR(VLOOKUP(F77,Cennik!$A$4:$B892, 2, FALSE()) * G77 + VLOOKUP(H77,Cennik!$A$4:$B892, 2, FALSE()) * I77 + VLOOKUP(J77,Cennik!$A$4:$B892, 2, FALSE()) * K77 + VLOOKUP(L77,Cennik!$A$4:$B892, 2, FALSE()) * M77 + VLOOKUP(N77,Cennik!$A$4:$B892, 2, FALSE()) * O77 + VLOOKUP(P77,Cennik!$A$4:$B892, 2, FALSE()) * Q77 + VLOOKUP(R77,Cennik!$A$4:$B892, 2, FALSE()) * S77 + VLOOKUP(T77,Cennik!$A$4:$B892, 2, FALSE()) * U77 + VLOOKUP(V77,Cennik!$A$4:$B892, 2, FALSE()) * W77 + VLOOKUP(X77,Cennik!$A$4:$B892, 2, FALSE()) * Y77 + VLOOKUP(Z77,Cennik!$A$4:$B892, 2, FALSE()) * AA77 + VLOOKUP(AB77,Cennik!$A$4:$B892, 2, FALSE() * AC77),"Brak wartości") -> Brak wartości
A78: Czerwony taboret | B78: 3 | C78: Świetny taboret, idealny do ustawienia w jakiejś eleganckiej sceneri. | D78: CHAIR_GS04_KWIATEK.ASC | E78: CHAIR_GS04_KWIATEK.ASC | F78: Deska z szlachetnego drewna | G78: 7 | H78: Gwoździe | I78: 6 | J78: Smoła | K78: 1 | L78: - | N78: - | P78: - | R78: - | T78: - | V78: - | X78: - | Z78: - | AB78: - | AD78: 15 | AE78: MobInter | AF78: chair | AG78: TRUE | AH78: TRUE | AI78: =IFERROR(VLOOKUP(F78,Cennik!$A$4:$B892, 2, FALSE()) * G78 + VLOOKUP(H78,Cennik!$A$4:$B892, 2, FALSE()) * I78 + VLOOKUP(J78,Cennik!$A$4:$B892, 2, FALSE()) * K78 + VLOOKUP(L78,Cennik!$A$4:$B892, 2, FALSE()) * M78 + VLOOKUP(N78,Cennik!$A$4:$B892, 2, FALSE()) * O78 + VLOOKUP(P78,Cennik!$A$4:$B892, 2, FALSE()) * Q78 + VLOOKUP(R78,Cennik!$A$4:$B892, 2, FALSE()) * S78 + VLOOKUP(T78,Cennik!$A$4:$B892, 2, FALSE()) * U78 + VLOOKUP(V78,Cennik!$A$4:$B892, 2, FALSE()) * W78 + VLOOKUP(X78,Cennik!$A$4:$B892, 2, FALSE()) * Y78 + VLOOKUP(Z78,Cennik!$A$4:$B892, 2, FALSE()) * AA78 + VLOOKUP(AB78,Cennik!$A$4:$B892, 2, FALSE() * AC78),"Brak wartości") -> Brak wartości
A79: Niebieski taboret | B79: 3 | C79: Świetny taboret, idealny do ustawienia w jakiejś eleganckiej sceneri. | D79: CHAIR_GS05_KWIATEK.ASC | E79: CHAIR_GS05_KWIATEK.ASC | F79: Deska z szlachetnego drewna | G79: 7 | H79: Gwoździe | I79: 6 | J79: Smoła | K79: 1 | L79: - | N79: - | P79: - | R79: - | T79: - | V79: - | X79: - | Z79: - | AB79: - | AD79: 15 | AE79: MobInter | AF79: chair | AG79: TRUE | AH79: TRUE | AI79: =IFERROR(VLOOKUP(F79,Cennik!$A$4:$B892, 2, FALSE()) * G79 + VLOOKUP(H79,Cennik!$A$4:$B892, 2, FALSE()) * I79 + VLOOKUP(J79,Cennik!$A$4:$B892, 2, FALSE()) * K79 + VLOOKUP(L79,Cennik!$A$4:$B892, 2, FALSE()) * M79 + VLOOKUP(N79,Cennik!$A$4:$B892, 2, FALSE()) * O79 + VLOOKUP(P79,Cennik!$A$4:$B892, 2, FALSE()) * Q79 + VLOOKUP(R79,Cennik!$A$4:$B892, 2, FALSE()) * S79 + VLOOKUP(T79,Cennik!$A$4:$B892, 2, FALSE()) * U79 + VLOOKUP(V79,Cennik!$A$4:$B892, 2, FALSE()) * W79 + VLOOKUP(X79,Cennik!$A$4:$B892, 2, FALSE()) * Y79 + VLOOKUP(Z79,Cennik!$A$4:$B892, 2, FALSE()) * AA79 + VLOOKUP(AB79,Cennik!$A$4:$B892, 2, FALSE() * AC79),"Brak wartości") -> Brak wartości
A80: Fioletowy taboret | B80: 3 | C80: Świetny taboret, idealny do ustawienia w jakiejś eleganckiej sceneri. | D80: CHAIR_GS06_KWIATEK.ASC | E80: CHAIR_GS06_KWIATEK.ASC | F80: Deska z szlachetnego drewna | G80: 7 | H80: Gwoździe | I80: 6 | J80: Smoła | K80: 1 | L80: - | N80: - | P80: - | R80: - | T80: - | V80: - | X80: - | Z80: - | AB80: - | AD80: 15 | AE80: MobInter | AF80: chair | AG80: TRUE | AH80: TRUE | AI80: =IFERROR(VLOOKUP(F80,Cennik!$A$4:$B892, 2, FALSE()) * G80 + VLOOKUP(H80,Cennik!$A$4:$B892, 2, FALSE()) * I80 + VLOOKUP(J80,Cennik!$A$4:$B892, 2, FALSE()) * K80 + VLOOKUP(L80,Cennik!$A$4:$B892, 2, FALSE()) * M80 + VLOOKUP(N80,Cennik!$A$4:$B892, 2, FALSE()) * O80 + VLOOKUP(P80,Cennik!$A$4:$B892, 2, FALSE()) * Q80 + VLOOKUP(R80,Cennik!$A$4:$B892, 2, FALSE()) * S80 + VLOOKUP(T80,Cennik!$A$4:$B892, 2, FALSE()) * U80 + VLOOKUP(V80,Cennik!$A$4:$B892, 2, FALSE()) * W80 + VLOOKUP(X80,Cennik!$A$4:$B892, 2, FALSE()) * Y80 + VLOOKUP(Z80,Cennik!$A$4:$B892, 2, FALSE()) * AA80 + VLOOKUP(AB80,Cennik!$A$4:$B892, 2, FALSE() * AC80),"Brak wartości") -> Brak wartości
A81: Zielony taboret | B81: 3 | C81: Świetny taboret, idealny do ustawienia w jakiejś eleganckiej sceneri. | D81: CHAIR_GS07_KWIATEK.ASC | E81: CHAIR_GS07_KWIATEK.ASC | F81: Deska z szlachetnego drewna | G81: 7 | H81: Gwoździe | I81: 6 | J81: Smoła | K81: 1 | L81: - | N81: - | P81: - | R81: - | T81: - | V81: - | X81: - | Z81: - | AB81: - | AD81: 15 | AE81: MobInter | AF81: chair | AG81: TRUE | AH81: TRUE | AI81: =IFERROR(VLOOKUP(F81,Cennik!$A$4:$B892, 2, FALSE()) * G81 + VLOOKUP(H81,Cennik!$A$4:$B892, 2, FALSE()) * I81 + VLOOKUP(J81,Cennik!$A$4:$B892, 2, FALSE()) * K81 + VLOOKUP(L81,Cennik!$A$4:$B892, 2, FALSE()) * M81 + VLOOKUP(N81,Cennik!$A$4:$B892, 2, FALSE()) * O81 + VLOOKUP(P81,Cennik!$A$4:$B892, 2, FALSE()) * Q81 + VLOOKUP(R81,Cennik!$A$4:$B892, 2, FALSE()) * S81 + VLOOKUP(T81,Cennik!$A$4:$B892, 2, FALSE()) * U81 + VLOOKUP(V81,Cennik!$A$4:$B892, 2, FALSE()) * W81 + VLOOKUP(X81,Cennik!$A$4:$B892, 2, FALSE()) * Y81 + VLOOKUP(Z81,Cennik!$A$4:$B892, 2, FALSE()) * AA81 + VLOOKUP(AB81,Cennik!$A$4:$B892, 2, FALSE() * AC81),"Brak wartości") -> Brak wartości
A82: Znakomita ławka | B82: 3 | C82: Nie ma nic lepszego niż porządna drewniana ławka, która zachęca do odpoczynku i kontemplacji piękna przyrody. | D82: BENCH_CHURCH_1.ASC | E82: BENCH_CHURCH_1.ASC | F82: Deska z szlachetnego drewna | G82: 10 | H82: Bryłka Kamienia | I82: 20 | J82: Gwoździe | K82: 2 | L82: Smoła | M82: 1 | N82: - | P82: - | R82: - | T82: - | V82: - | X82: - | Z82: - | AB82: - | AD82: 30 | AE82: MobInter | AF82: chair | AG82: TRUE | AH82: TRUE | AI82: =IFERROR(VLOOKUP(F82,Cennik!$A$4:$B892, 2, FALSE()) * G82 + VLOOKUP(H82,Cennik!$A$4:$B892, 2, FALSE()) * I82 + VLOOKUP(J82,Cennik!$A$4:$B892, 2, FALSE()) * K82 + VLOOKUP(L82,Cennik!$A$4:$B892, 2, FALSE()) * M82 + VLOOKUP(N82,Cennik!$A$4:$B892, 2, FALSE()) * O82 + VLOOKUP(P82,Cennik!$A$4:$B892, 2, FALSE()) * Q82 + VLOOKUP(R82,Cennik!$A$4:$B892, 2, FALSE()) * S82 + VLOOKUP(T82,Cennik!$A$4:$B892, 2, FALSE()) * U82 + VLOOKUP(V82,Cennik!$A$4:$B892, 2, FALSE()) * W82 + VLOOKUP(X82,Cennik!$A$4:$B892, 2, FALSE()) * Y82 + VLOOKUP(Z82,Cennik!$A$4:$B892, 2, FALSE()) * AA82 + VLOOKUP(AB82,Cennik!$A$4:$B892, 2, FALSE() * AC82),"Brak wartości") -> Brak wartości
A83: Skórzany fotel | B83: 3 | C83: Nie ma nic lepszego niż odpoczynek na dobrej ławce po długiej wędrówce. Ta ławka z pewnością spełnia ich oczekiwania. | D83: THRONE_NW_CITY_02.ASC | E83: THRONE_NW_CITY_02.ASC | F83: Deska z szlachetnego drewna | G83: 10 | H83: Gwoździe | I83: 4 | J83: Smoła | K83: 1 | L83: - | N83: - | P83: - | R83: - | T83: - | V83: - | X83: - | Z83: - | AB83: - | AD83: 30 | AE83: MobInter | AF83: chair | AG83: TRUE | AH83: TRUE | AI83: =IFERROR(VLOOKUP(F83,Cennik!$A$4:$B892, 2, FALSE()) * G83 + VLOOKUP(H83,Cennik!$A$4:$B892, 2, FALSE()) * I83 + VLOOKUP(J83,Cennik!$A$4:$B892, 2, FALSE()) * K83 + VLOOKUP(L83,Cennik!$A$4:$B892, 2, FALSE()) * M83 + VLOOKUP(N83,Cennik!$A$4:$B892, 2, FALSE()) * O83 + VLOOKUP(P83,Cennik!$A$4:$B892, 2, FALSE()) * Q83 + VLOOKUP(R83,Cennik!$A$4:$B892, 2, FALSE()) * S83 + VLOOKUP(T83,Cennik!$A$4:$B892, 2, FALSE()) * U83 + VLOOKUP(V83,Cennik!$A$4:$B892, 2, FALSE()) * W83 + VLOOKUP(X83,Cennik!$A$4:$B892, 2, FALSE()) * Y83 + VLOOKUP(Z83,Cennik!$A$4:$B892, 2, FALSE()) * AA83 + VLOOKUP(AB83,Cennik!$A$4:$B892, 2, FALSE() * AC83),"Brak wartości") -> Brak wartości
A84: Hebanowa ławka | B84: 4 | C84: Siedząc na tej ławce, człowiek czuje się jak na tronie, otoczony luksusem i bogactwem. | D84: BENCH_ORANGE_01_KOZA.ASC | E84: BENCH_ORANGE_01_KOZA.ASC | F84: Deska z szlachetnego drewna | G84: 8 | H84: Gwoździe | I84: 6 | J84: Smoła | K84: 2 | L84: Wełniana tkanina | M84: 6 | N84: Stalowy pręt | O84: 2 | P84: Gruba skóra | Q84: 1 | R84: - | T84: - | V84: - | X84: - | Z84: - | AB84: - | AD84: 35 | AE84: MobInter | AF84: chair | AG84: TRUE | AH84: TRUE | AI84: =IFERROR(VLOOKUP(F84,Cennik!$A$4:$B892, 2, FALSE()) * G84 + VLOOKUP(H84,Cennik!$A$4:$B892, 2, FALSE()) * I84 + VLOOKUP(J84,Cennik!$A$4:$B892, 2, FALSE()) * K84 + VLOOKUP(L84,Cennik!$A$4:$B892, 2, FALSE()) * M84 + VLOOKUP(N84,Cennik!$A$4:$B892, 2, FALSE()) * O84 + VLOOKUP(P84,Cennik!$A$4:$B892, 2, FALSE()) * Q84 + VLOOKUP(R84,Cennik!$A$4:$B892, 2, FALSE()) * S84 + VLOOKUP(T84,Cennik!$A$4:$B892, 2, FALSE()) * U84 + VLOOKUP(V84,Cennik!$A$4:$B892, 2, FALSE()) * W84 + VLOOKUP(X84,Cennik!$A$4:$B892, 2, FALSE()) * Y84 + VLOOKUP(Z84,Cennik!$A$4:$B892, 2, FALSE()) * AA84 + VLOOKUP(AB84,Cennik!$A$4:$B892, 2, FALSE() * AC84),"Brak wartości") -> Brak wartości
A85: Hebanowa ławka 2 | B85: 4 | C85: Siedząc na tej ławce, człowiek czuje się jak na tronie, otoczony luksusem i bogactwem. | D85: BENCH_WOOD_ORANGE_01_KOZA.ASC | E85: BENCH_WOOD_ORANGE_01_KOZA.ASC | F85: Deska z szlachetnego drewna | G85: 8 | H85: Gwoździe | I85: 6 | J85: Smoła | K85: 2 | L85: Wełniana tkanina | M85: 6 | N85: Stalowy pręt | O85: 2 | P85: Gruba skóra | Q85: 1 | R85: - | T85: - | V85: - | X85: - | Z85: - | AB85: - | AD85: 35 | AE85: MobInter | AF85: chair | AG85: TRUE | AH85: TRUE | AI85: =IFERROR(VLOOKUP(F85,Cennik!$A$4:$B892, 2, FALSE()) * G85 + VLOOKUP(H85,Cennik!$A$4:$B892, 2, FALSE()) * I85 + VLOOKUP(J85,Cennik!$A$4:$B892, 2, FALSE()) * K85 + VLOOKUP(L85,Cennik!$A$4:$B892, 2, FALSE()) * M85 + VLOOKUP(N85,Cennik!$A$4:$B892, 2, FALSE()) * O85 + VLOOKUP(P85,Cennik!$A$4:$B892, 2, FALSE()) * Q85 + VLOOKUP(R85,Cennik!$A$4:$B892, 2, FALSE()) * S85 + VLOOKUP(T85,Cennik!$A$4:$B892, 2, FALSE()) * U85 + VLOOKUP(V85,Cennik!$A$4:$B892, 2, FALSE()) * W85 + VLOOKUP(X85,Cennik!$A$4:$B892, 2, FALSE()) * Y85 + VLOOKUP(Z85,Cennik!$A$4:$B892, 2, FALSE()) * AA85 + VLOOKUP(AB85,Cennik!$A$4:$B892, 2, FALSE() * AC85),"Brak wartości") -> Brak wartości
A86: Hebanowy taboret | B86: 4 | C86: Ten mebel może być doskonałym wyborem dla osób ceniących sobie stylowe i eleganckie rozwiązania, które jednocześnie są funkcjonalne i wygodne w użytkowaniu. | D86: CHAIR_ORANGE_01_KOZA.ASC | E86: CHAIR_ORANGE_01_KOZA.ASC | F86: Deska z szlachetnego drewna | G86: 5 | H86: Gwoździe | I86: 6 | J86: Smoła | K86: 2 | L86: Wełniana tkanina | M86: 6 | N86: Szlachetne drewno | O86: 1 | P86: - | R86: - | T86: - | V86: - | X86: - | Z86: - | AB86: - | AD86: 15 | AE86: MobInter | AF86: chair | AG86: TRUE | AH86: TRUE | AI86: =IFERROR(VLOOKUP(F86,Cennik!$A$4:$B892, 2, FALSE()) * G86 + VLOOKUP(H86,Cennik!$A$4:$B892, 2, FALSE()) * I86 + VLOOKUP(J86,Cennik!$A$4:$B892, 2, FALSE()) * K86 + VLOOKUP(L86,Cennik!$A$4:$B892, 2, FALSE()) * M86 + VLOOKUP(N86,Cennik!$A$4:$B892, 2, FALSE()) * O86 + VLOOKUP(P86,Cennik!$A$4:$B892, 2, FALSE()) * Q86 + VLOOKUP(R86,Cennik!$A$4:$B892, 2, FALSE()) * S86 + VLOOKUP(T86,Cennik!$A$4:$B892, 2, FALSE()) * U86 + VLOOKUP(V86,Cennik!$A$4:$B892, 2, FALSE()) * W86 + VLOOKUP(X86,Cennik!$A$4:$B892, 2, FALSE()) * Y86 + VLOOKUP(Z86,Cennik!$A$4:$B892, 2, FALSE()) * AA86 + VLOOKUP(AB86,Cennik!$A$4:$B892, 2, FALSE() * AC86),"Brak wartości") -> Brak wartości
A87: Hebanowe krzesło | B87: 4 | C87: Ten mebel może być doskonałym wyborem dla osób ceniących sobie stylowe i eleganckie rozwiązania, które jednocześnie są funkcjonalne i wygodne w użytkowaniu. | D87: THRONENEW_ORANGE_01_KOZA.ASC | E87: THRONENEW_ORANGE_01_KOZA.ASC | F87: Deska z szlachetnego drewna | G87: 5 | H87: Gwoździe | I87: 6 | J87: Smoła | K87: 2 | L87: Wełniana tkanina | M87: 6 | N87: Szlachetne drewno | O87: 1 | P87: - | R87: - | T87: - | V87: - | X87: - | Z87: - | AB87: - | AD87: 15 | AE87: MobInter | AF87: chair | AG87: TRUE | AH87: TRUE | AI87: =IFERROR(VLOOKUP(F87,Cennik!$A$4:$B892, 2, FALSE()) * G87 + VLOOKUP(H87,Cennik!$A$4:$B892, 2, FALSE()) * I87 + VLOOKUP(J87,Cennik!$A$4:$B892, 2, FALSE()) * K87 + VLOOKUP(L87,Cennik!$A$4:$B892, 2, FALSE()) * M87 + VLOOKUP(N87,Cennik!$A$4:$B892, 2, FALSE()) * O87 + VLOOKUP(P87,Cennik!$A$4:$B892, 2, FALSE()) * Q87 + VLOOKUP(R87,Cennik!$A$4:$B892, 2, FALSE()) * S87 + VLOOKUP(T87,Cennik!$A$4:$B892, 2, FALSE()) * U87 + VLOOKUP(V87,Cennik!$A$4:$B892, 2, FALSE()) * W87 + VLOOKUP(X87,Cennik!$A$4:$B892, 2, FALSE()) * Y87 + VLOOKUP(Z87,Cennik!$A$4:$B892, 2, FALSE()) * AA87 + VLOOKUP(AB87,Cennik!$A$4:$B892, 2, FALSE() * AC87),"Brak wartości") -> Brak wartości
A88: Stołek dworski | B88: 4 | C88: Ten mebel może być doskonałym wyborem dla osób ceniących sobie stylowe i eleganckie rozwiązania, które jednocześnie są funkcjonalne i wygodne w użytkowaniu. | D88: CHAIR_NW_EDEL_01.ASC | E88: CHAIR_NW_EDEL_01.ASC | F88: Deska z szlachetnego drewna | G88: 5 | H88: Gwoździe | I88: 6 | J88: Smoła | K88: 2 | L88: Wełniana tkanina | M88: 6 | N88: Szlachetne drewno | O88: 1 | P88: - | R88: - | T88: - | V88: - | X88: - | Z88: - | AB88: - | AD88: 15 | AE88: MobInter | AF88: chair | AG88: TRUE | AH88: TRUE | AI88: =IFERROR(VLOOKUP(F88,Cennik!$A$4:$B892, 2, FALSE()) * G88 + VLOOKUP(H88,Cennik!$A$4:$B892, 2, FALSE()) * I88 + VLOOKUP(J88,Cennik!$A$4:$B892, 2, FALSE()) * K88 + VLOOKUP(L88,Cennik!$A$4:$B892, 2, FALSE()) * M88 + VLOOKUP(N88,Cennik!$A$4:$B892, 2, FALSE()) * O88 + VLOOKUP(P88,Cennik!$A$4:$B892, 2, FALSE()) * Q88 + VLOOKUP(R88,Cennik!$A$4:$B892, 2, FALSE()) * S88 + VLOOKUP(T88,Cennik!$A$4:$B892, 2, FALSE()) * U88 + VLOOKUP(V88,Cennik!$A$4:$B892, 2, FALSE()) * W88 + VLOOKUP(X88,Cennik!$A$4:$B892, 2, FALSE()) * Y88 + VLOOKUP(Z88,Cennik!$A$4:$B892, 2, FALSE()) * AA88 + VLOOKUP(AB88,Cennik!$A$4:$B892, 2, FALSE() * AC88),"Brak wartości") -> Brak wartości
A89: Czerwony fotel | B89: 4 | C89: Nie ma nic lepszego niż usiąść na miękkim fotelu po ciężkim dniu. | D89: THRONE_NW_CITY_01.ASC | E89: THRONE_NW_CITY_01.ASC | F89: Deska z szlachetnego drewna | G89: 8 | H89: Twarde drewno | I89: 4 | J89: Gwoździe | K89: 2 | L89: Smoła | M89: 2 | N89: Wełniana tkanina | O89: 5 | P89: Gruba skóra | Q89: 2 | R89: - | T89: - | V89: - | X89: - | Z89: - | AB89: - | AD89: 40 | AE89: MobInter | AF89: chair | AG89: TRUE | AH89: TRUE | AI89: =IFERROR(VLOOKUP(F89,Cennik!$A$4:$B892, 2, FALSE()) * G89 + VLOOKUP(H89,Cennik!$A$4:$B892, 2, FALSE()) * I89 + VLOOKUP(J89,Cennik!$A$4:$B892, 2, FALSE()) * K89 + VLOOKUP(L89,Cennik!$A$4:$B892, 2, FALSE()) * M89 + VLOOKUP(N89,Cennik!$A$4:$B892, 2, FALSE()) * O89 + VLOOKUP(P89,Cennik!$A$4:$B892, 2, FALSE()) * Q89 + VLOOKUP(R89,Cennik!$A$4:$B892, 2, FALSE()) * S89 + VLOOKUP(T89,Cennik!$A$4:$B892, 2, FALSE()) * U89 + VLOOKUP(V89,Cennik!$A$4:$B892, 2, FALSE()) * W89 + VLOOKUP(X89,Cennik!$A$4:$B892, 2, FALSE()) * Y89 + VLOOKUP(Z89,Cennik!$A$4:$B892, 2, FALSE()) * AA89 + VLOOKUP(AB89,Cennik!$A$4:$B892, 2, FALSE() * AC89),"Brak wartości") -> Brak wartości
A90: Bogata ławka | B90: 4 | C90: Siedząc na tej ławce, człowiek czuje się jak na tronie, otoczony luksusem i bogactwem. | D90: BENCH_NW_CITY_02.ASC | E90: BENCH_NW_CITY_02.ASC | F90: Deska z szlachetnego drewna | G90: 8 | H90: Gwoździe | I90: 6 | J90: Smoła | K90: 2 | L90: Wełniana tkanina | M90: 6 | N90: Stalowy pręt | O90: 2 | P90: Gruba skóra | Q90: 1 | R90: - | T90: - | V90: - | X90: - | Z90: - | AB90: - | AD90: 35 | AE90: MobInter | AF90: chair | AG90: TRUE | AH90: TRUE | AI90: =IFERROR(VLOOKUP(F90,Cennik!$A$4:$B892, 2, FALSE()) * G90 + VLOOKUP(H90,Cennik!$A$4:$B892, 2, FALSE()) * I90 + VLOOKUP(J90,Cennik!$A$4:$B892, 2, FALSE()) * K90 + VLOOKUP(L90,Cennik!$A$4:$B892, 2, FALSE()) * M90 + VLOOKUP(N90,Cennik!$A$4:$B892, 2, FALSE()) * O90 + VLOOKUP(P90,Cennik!$A$4:$B892, 2, FALSE()) * Q90 + VLOOKUP(R90,Cennik!$A$4:$B892, 2, FALSE()) * S90 + VLOOKUP(T90,Cennik!$A$4:$B892, 2, FALSE()) * U90 + VLOOKUP(V90,Cennik!$A$4:$B892, 2, FALSE()) * W90 + VLOOKUP(X90,Cennik!$A$4:$B892, 2, FALSE()) * Y90 + VLOOKUP(Z90,Cennik!$A$4:$B892, 2, FALSE()) * AA90 + VLOOKUP(AB90,Cennik!$A$4:$B892, 2, FALSE() * AC90),"Brak wartości") -> Brak wartości
A91: Tron | B91: 5 | C91: Siedząc na tej ławce, człowiek czuje się jak na tronie, otoczony luksusem i bogactwem. | D91: GSKELTHRONE_VOLFZACKE.ASC | E91: GSKELTHRONE_VOLFZACKE.ASC | F91: Deska z szlachetnego drewna | G91: 8 | H91: Szlachetne drewno | I91: 2 | J91: Gwoździe | K91: 8 | L91: Smoła | M91: 3 | N91: Wełniana tkanina | O91: 5 | P91: Skóra trolla | Q91: 1 | R91: - | T91: - | V91: - | X91: - | Z91: - | AB91: - | AD91: 45 | AE91: MobInter | AF91: chair | AG91: TRUE | AH91: TRUE | AI91: =IFERROR(VLOOKUP(F91,Cennik!$A$4:$B892, 2, FALSE()) * G91 + VLOOKUP(H91,Cennik!$A$4:$B892, 2, FALSE()) * I91 + VLOOKUP(J91,Cennik!$A$4:$B892, 2, FALSE()) * K91 + VLOOKUP(L91,Cennik!$A$4:$B892, 2, FALSE()) * M91 + VLOOKUP(N91,Cennik!$A$4:$B892, 2, FALSE()) * O91 + VLOOKUP(P91,Cennik!$A$4:$B892, 2, FALSE()) * Q91 + VLOOKUP(R91,Cennik!$A$4:$B892, 2, FALSE()) * S91 + VLOOKUP(T91,Cennik!$A$4:$B892, 2, FALSE()) * U91 + VLOOKUP(V91,Cennik!$A$4:$B892, 2, FALSE()) * W91 + VLOOKUP(X91,Cennik!$A$4:$B892, 2, FALSE()) * Y91 + VLOOKUP(Z91,Cennik!$A$4:$B892, 2, FALSE()) * AA91 + VLOOKUP(AB91,Cennik!$A$4:$B892, 2, FALSE() * AC91),"Brak wartości") -> Brak wartości
A92: Brzozowa ławka | B92: 5 | C92: Siedząc na tej ławce, człowiek czuje się jak na tronie, otoczony luksusem i bogactwem. | D92: BENCH_YELLOW_01_KOZA.ASC | E92: BENCH_YELLOW_01_KOZA.ASC | F92: Deska z szlachetnego drewna | G92: 8 | H92: Szlachetne drewno | I92: 2 | J92: Gwoździe | K92: 8 | L92: Smoła | M92: 3 | N92: Wełniana tkanina | O92: 5 | P92: Skóra trolla | Q92: 1 | R92: - | T92: - | V92: - | X92: - | Z92: - | AB92: - | AD92: 45 | AE92: MobInter | AF92: chair | AG92: TRUE | AH92: TRUE | AI92: =IFERROR(VLOOKUP(F92,Cennik!$A$4:$B892, 2, FALSE()) * G92 + VLOOKUP(H92,Cennik!$A$4:$B892, 2, FALSE()) * I92 + VLOOKUP(J92,Cennik!$A$4:$B892, 2, FALSE()) * K92 + VLOOKUP(L92,Cennik!$A$4:$B892, 2, FALSE()) * M92 + VLOOKUP(N92,Cennik!$A$4:$B892, 2, FALSE()) * O92 + VLOOKUP(P92,Cennik!$A$4:$B892, 2, FALSE()) * Q92 + VLOOKUP(R92,Cennik!$A$4:$B892, 2, FALSE()) * S92 + VLOOKUP(T92,Cennik!$A$4:$B892, 2, FALSE()) * U92 + VLOOKUP(V92,Cennik!$A$4:$B892, 2, FALSE()) * W92 + VLOOKUP(X92,Cennik!$A$4:$B892, 2, FALSE()) * Y92 + VLOOKUP(Z92,Cennik!$A$4:$B892, 2, FALSE()) * AA92 + VLOOKUP(AB92,Cennik!$A$4:$B892, 2, FALSE() * AC92),"Brak wartości") -> Brak wartości
A93: Brzozowa ławka 2 | B93: 5 | C93: Ten mebel może być doskonałym wyborem dla osób ceniących sobie stylowe i eleganckie rozwiązania, które jednocześnie są funkcjonalne i wygodne w użytkowaniu. | D93: BENCH_WOOD_YELLOW_01_KOZA.ASC | E93: BENCH_WOOD_YELLOW_01_KOZA.ASC | F93: Deska z szlachetnego drewna | G93: 6 | H93: Szlachetne drewno | I93: 3 | J93: Gwoździe | K93: 8 | L93: Smoła | M93: 3 | N93: Wełniana tkanina | O93: 5 | P93: Skóra trolla | Q93: 1 | R93: - | T93: - | V93: - | X93: - | Z93: - | AB93: - | AD93: 45 | AE93: MobInter | AF93: chair | AG93: TRUE | AH93: TRUE | AI93: =IFERROR(VLOOKUP(F93,Cennik!$A$4:$B892, 2, FALSE()) * G93 + VLOOKUP(H93,Cennik!$A$4:$B892, 2, FALSE()) * I93 + VLOOKUP(J93,Cennik!$A$4:$B892, 2, FALSE()) * K93 + VLOOKUP(L93,Cennik!$A$4:$B892, 2, FALSE()) * M93 + VLOOKUP(N93,Cennik!$A$4:$B892, 2, FALSE()) * O93 + VLOOKUP(P93,Cennik!$A$4:$B892, 2, FALSE()) * Q93 + VLOOKUP(R93,Cennik!$A$4:$B892, 2, FALSE()) * S93 + VLOOKUP(T93,Cennik!$A$4:$B892, 2, FALSE()) * U93 + VLOOKUP(V93,Cennik!$A$4:$B892, 2, FALSE()) * W93 + VLOOKUP(X93,Cennik!$A$4:$B892, 2, FALSE()) * Y93 + VLOOKUP(Z93,Cennik!$A$4:$B892, 2, FALSE()) * AA93 + VLOOKUP(AB93,Cennik!$A$4:$B892, 2, FALSE() * AC93),"Brak wartości") -> Brak wartości
A94: Brzozowy taboret | B94: 5 | C94: Ten mebel może być doskonałym wyborem dla osób ceniących sobie stylowe i eleganckie rozwiązania, które jednocześnie są funkcjonalne i wygodne w użytkowaniu. | D94: CHAIR_YELLOW_01_KOZA.ASC | E94: CHAIR_YELLOW_01_KOZA.ASC | F94: Deska z szlachetnego drewna | G94: 6 | H94: Szlachetne drewno | I94: 3 | J94: Gwoździe | K94: 8 | L94: Smoła | M94: 3 | N94: Wełniana tkanina | O94: 5 | P94: Skóra trolla | Q94: 1 | R94: - | T94: - | V94: - | X94: - | Z94: - | AB94: - | AD94: 45 | AE94: MobInter | AF94: chair | AG94: TRUE | AH94: TRUE | AI94: =IFERROR(VLOOKUP(F94,Cennik!$A$4:$B892, 2, FALSE()) * G94 + VLOOKUP(H94,Cennik!$A$4:$B892, 2, FALSE()) * I94 + VLOOKUP(J94,Cennik!$A$4:$B892, 2, FALSE()) * K94 + VLOOKUP(L94,Cennik!$A$4:$B892, 2, FALSE()) * M94 + VLOOKUP(N94,Cennik!$A$4:$B892, 2, FALSE()) * O94 + VLOOKUP(P94,Cennik!$A$4:$B892, 2, FALSE()) * Q94 + VLOOKUP(R94,Cennik!$A$4:$B892, 2, FALSE()) * S94 + VLOOKUP(T94,Cennik!$A$4:$B892, 2, FALSE()) * U94 + VLOOKUP(V94,Cennik!$A$4:$B892, 2, FALSE()) * W94 + VLOOKUP(X94,Cennik!$A$4:$B892, 2, FALSE()) * Y94 + VLOOKUP(Z94,Cennik!$A$4:$B892, 2, FALSE()) * AA94 + VLOOKUP(AB94,Cennik!$A$4:$B892, 2, FALSE() * AC94),"Brak wartości") -> Brak wartości
A95: Brzozowe krzesło | B95: 5 | C95: Tron jest symbolem władzy, a jego właściciel musi być gotów do ponoszenia odpowiedzialności za swoje decyzje. | D95: THRONENEW_YELLOW_01_KOZA.ASC | E95: THRONENEW_YELLOW_01_KOZA.ASC | F95: Deska z szlachetnego drewna | G95: 10 | H95: Szlachetne drewno | I95: 2 | J95: Gwoździe | K95: 8 | L95: Smoła | M95: 3 | N95: Wełniana tkanina | O95: 5 | P95: Skóra trolla | Q95: 1 | R95: - | T95: - | V95: - | X95: - | Z95: - | AB95: - | AD95: 45 | AE95: MobInter | AF95: chair | AG95: TRUE | AH95: TRUE | AI95: =IFERROR(VLOOKUP(F95,Cennik!$A$4:$B892, 2, FALSE()) * G95 + VLOOKUP(H95,Cennik!$A$4:$B892, 2, FALSE()) * I95 + VLOOKUP(J95,Cennik!$A$4:$B892, 2, FALSE()) * K95 + VLOOKUP(L95,Cennik!$A$4:$B892, 2, FALSE()) * M95 + VLOOKUP(N95,Cennik!$A$4:$B892, 2, FALSE()) * O95 + VLOOKUP(P95,Cennik!$A$4:$B892, 2, FALSE()) * Q95 + VLOOKUP(R95,Cennik!$A$4:$B892, 2, FALSE()) * S95 + VLOOKUP(T95,Cennik!$A$4:$B892, 2, FALSE()) * U95 + VLOOKUP(V95,Cennik!$A$4:$B892, 2, FALSE()) * W95 + VLOOKUP(X95,Cennik!$A$4:$B892, 2, FALSE()) * Y95 + VLOOKUP(Z95,Cennik!$A$4:$B892, 2, FALSE()) * AA95 + VLOOKUP(AB95,Cennik!$A$4:$B892, 2, FALSE() * AC95),"Brak wartości") -> Brak wartości
F96: - | H96: - | J96: - | L96: - | N96: - | P96: - | R96: - | T96: - | V96: - | X96: - | Z96: - | AB96: -
F97: - | H97: - | J97: - | L97: - | N97: - | P97: - | R97: - | T97: - | V97: - | X97: - | Z97: - | AB97: -
F98: - | H98: - | J98: - | L98: - | N98: - | P98: - | R98: - | T98: - | V98: - | X98: - | Z98: - | AB98: -
A99: Pozbijana półka | B99: 1 | C99: Półka zrobiona z resztek, ale i tak wydaje się dość solidny. Może służyć do różnych celów. | D99: DT_SHELF_V1.3ds | E99: DT_SHELF_V1.3ds | F99: Deska z miękiego drewna | G99: 5 | H99: Pocięte miękkie drewno | I99: 5 | J99: Gwoździe | K99: 3 | L99: Smoła | M99: 1 | N99: - | P99: - | R99: - | T99: - | V99: - | X99: - | Z99: - | AB99: - | AD99: 20 | AE99: Vob | AF99: wardrobe | AG99: TRUE | AH99: TRUE | AI99: =IFERROR(VLOOKUP(F99,Cennik!$A$4:$B892, 2, FALSE()) * G99 + VLOOKUP(H99,Cennik!$A$4:$B892, 2, FALSE()) * I99 + VLOOKUP(J99,Cennik!$A$4:$B892, 2, FALSE()) * K99 + VLOOKUP(L99,Cennik!$A$4:$B892, 2, FALSE()) * M99 + VLOOKUP(N99,Cennik!$A$4:$B892, 2, FALSE()) * O99 + VLOOKUP(P99,Cennik!$A$4:$B892, 2, FALSE()) * Q99 + VLOOKUP(R99,Cennik!$A$4:$B892, 2, FALSE()) * S99 + VLOOKUP(T99,Cennik!$A$4:$B892, 2, FALSE()) * U99 + VLOOKUP(V99,Cennik!$A$4:$B892, 2, FALSE()) * W99 + VLOOKUP(X99,Cennik!$A$4:$B892, 2, FALSE()) * Y99 + VLOOKUP(Z99,Cennik!$A$4:$B892, 2, FALSE()) * AA99 + VLOOKUP(AB99,Cennik!$A$4:$B892, 2, FALSE() * AC99),"Brak wartości") -> Brak wartości
A100: Zbutwiały stół | B100: 1 | C100: Lekko zbutwiały, lecz butelki nadal mogą na nim leżeć. | D100: GS_FURNITURE_FANTASYTABLE_01_GALI.3DS | E100: GS_FURNITURE_FANTASYTABLE_01_GALI.3DS | F100: - | H100: - | J100: - | L100: - | N100: - | P100: - | R100: - | T100: - | V100: - | X100: - | Z100: - | AB100: - | AD100: 20 | AE100: Vob | AF100: wardrobe | AG100: FALSE | AH100: FALSE | AI100: BRAK
A101: Wisząca bukowa szafka | B101: 2 | C101: Ten mebel bukowy to najlepszy wybór dla każdego, kto ceni sobie solidność i prostotę. | D101: GS_FURNITURE_WARDROBE_01_KWIATEK.3DS | E101: GS_FURNITURE_WARDROBE_01_KWIATEK.3DS | F101: - | H101: - | J101: - | L101: - | N101: - | P101: - | R101: - | T101: - | V101: - | X101: - | Z101: - | AB101: - | AD101: 20 | AE101: Vob | AF101: wardrobe | AG101: TRUE | AH101: TRUE | AI101: BRAK
...

Sheet Config
A1: Stół | B1: Skryptowy vob | D1: Zawód | E1: Skryptowy Enum | F1: Tiery | H1: Narzędzie | I1: Instancja | K1: Flagi - Addon | L1: Podflagi - Addon | N1: ItemCategory | O1: ItemType | P1: ItemGroupType | Q1: PLIK | R1: stacking | S1: regen | T1: damage | U1: requirements | V1: def | W1: durability | X1: predefined | Y1: Column 2 | Z1: Crafty | AB1: VobType | AC1: category | AD1: Kolumna nr 1
A2: Piec runiczny | B2: RunicFurnace | D2: Krawiec | E2: TAILOR | F2: 5 | H2: Nożyce | I2: ITMI_GS_COM_18 | K2: ITEM_CAT_NONE | L2: ITEM_FLAG_DAG | N2: Weapon | O2: Accessory | P2: AdminShield | Q2: acsr1 | R2: FALSE | S2: FALSE | T2: FALSE | U2: FALSE | V2: FALSE | W2: FALSE | X2: local class LocalItemEquip extends Game.ItemTemplate._baseEquipSynchronizedModule { equipType = EquippedItems.AccessorySlot1 } local function registerItem(instance, options) { options.category <- "category" in options ? options.category : ItemCategory.AccessorySlot1; options.type <- "type" in options ? options.type : ItemType.Accessory; options.requirementModules <- "requirementModules" in options ? options.requirementModules : [Game.ItemTemplate.emptyRequirement(0)]; options.equipModule <- "equipModule" in options ? options.equipModule : LocalItemEquip; options.stackable <- "stackable" in options ? options.stackable : false; options.group <- "group" in options ? options.group : ItemGroupType.AdminAccessory; Game.ItemTemplate.registry.addItem(Game.ItemTemplate.myItem(instance, options), options); } | Z2: Zbrojmistrz/Płatnerz/Kowal | AB2: Vob | AC2: profession
A3: Stół do zaklinania | B3: EnchantingTable | D3: Kaletnik | E3: LEATHERWORKER | F3: 3 | H3: Nóż garbarski | I3: ITMW_GS_1H_80_1 | K3: ITEM_CAT_NF | L3: ITEM_FLAG_SWD | N3: Rune | O3: Bow | P3: AdminArmor | Q3: acsr2 | R3: FALSE | S3: FALSE | T3: FALSE | U3: FALSE | V3: FALSE | W3: FALSE | X3: local class LocalItemEquip extends Game.ItemTemplate._baseEquipSynchronizedModule { equipType = EquippedItems.AccessorySlot2 } local function registerItem(instance, options) { options.category <- "category" in options ? options.category : ItemCategory.AccessorySlot2; options.type <- "type" in options ? options.type : ItemType.Accessory; options.requirementModules <- "requirementModules" in options ? options.requirementModules : [Game.ItemTemplate.emptyRequirement(0)]; options.equipModule <- "equipModule" in options ? options.equipModule : LocalItemEquip; options.stackable <- "stackable" in options ? options.stackable : false; options.group <- "group" in options ? options.group : ItemGroupType.AdminAccessory; Game.ItemTemplate.registry.addItem(Game.ItemTemplate.myItem(instance, options), options); } | Z3: Kucharz | AB3: Mob | AC3: chest
A4: Stół runiczny | B4: RunicTable | D4: Kuśnierz | E4: FURRIER | F4: 5 | H4: Kilof | I4: ITHE_GS_41 | K4: ITEM_CAT_FF | L4: ITEM_FLAG_AXE | N4: Consumable | O4: Crossbow | P4: AdminHelmet | Q4: acsr3 | R4: FALSE | S4: FALSE | T4: FALSE | U4: FALSE | V4: FALSE | W4: FALSE | X4: local class LocalItemEquip extends Game.ItemTemplate._baseEquipSynchronizedModule { equipType = EquippedItems.AccessorySlot3 } local function registerItem(instance, options) { options.category <- "category" in options ? options.category : ItemCategory.AccessorySlot3; options.type <- "type" in options ? options.type : ItemType.Accessory; options.requirementModules <- "requirementModules" in options ? options.requirementModules : [Game.ItemTemplate.emptyRequirement(0)]; options.equipModule <- "equipModule" in options ? options.equipModule : LocalItemEquip; options.stackable <- "stackable" in options ? options.stackable : false; options.group <- "group" in options ? options.group : ItemGroupType.AdminAccessory; Game.ItemTemplate.registry.addItem(Game.ItemTemplate.myItem(instance, options), options); } | Z4: Farmer | AB4: MobInter | AC4: bed
A5: Młyn | B5: Mill | D5: Łuczarz | E5: BOWYER | F5: 5 | H5: Kołowrót | I5: ITMI_GS_COM_16 | K5: ITEM_CAT_MUN | L5: ITEM_FLAG_2HD_SWD | N5: Potion | O5: OneHanded | P5: AdminMask | Q5: acsr4 | R5: FALSE | S5: FALSE | T5: FALSE | U5: FALSE | V5: FALSE | W5: FALSE | X5: local class LocalItemEquip extends Game.ItemTemplate._baseEquipSynchronizedModule { equipType = EquippedItems.AccessorySlot4 } local function registerItem(instance, options) { options.category <- "category" in options ? options.category : ItemCategory.AccessorySlot4; options.type <- "type" in options ? options.type : ItemType.Accessory; options.requirementModules <- "requirementModules" in options ? options.requirementModules : [Game.ItemTemplate.emptyRequirement(0)]; options.equipModule <- "equipModule" in options ? options.equipModule : LocalItemEquip; options.stackable <- "stackable" in options ? options.stackable : false; options.group <- "group" in options ? options.group : ItemGroupType.AdminAccessory; Game.ItemTemplate.registry.addItem(Game.ItemTemplate.myItem(instance, options), options); } | Z5: Zbieracz | AB5: MobBed | AC5: chair
A6: Serowar | B6: Cheesemaker | D6: Górnik | E6: MINER | F6: 5 | H6: Pióro do pisania | I6: ITMI_GS_MAT_228 | K6: ITEM_CAT_ARMOR | L6: ITEM_FLAG_2HD_AXE | N6: Armor | O6: TwoHanded | P6: AdminBolt | Q6: amulets | R6: FALSE | S6: FALSE | T6: FALSE | U6: FALSE | V6: TRUE | W6: FALSE | X6: local function registerItem(instance, options) { options.requirementModules <- "requirementModules" in options ? options.requirementModules : [Game.ItemTemplate.emptyRequirement(0)]; options.equipModule <- "equipModule" in options ? options.equipModule : Game.ItemTemplate.amuletEquip; options.stackable <- "stackable" in options ? options.stackable : false; options.category <- "category" in options ? options.category : ItemCategory.Amulet; options.type <- "type" in options ? options.type : ItemType.Accessory; Game.ItemTemplate.registry.addItem(Game.ItemTemplate.myItem(instance, options), options); } | Z6: Alchemik | AB6: MobLadder | AC6: table
A7: Hodowla zwierząt: kury | B7: AnimalHusbandryChickens | D7: Hutnik | E7: SMELTER | F7: 5 | H7: Siekiera | I7: ITMW_GS_2H_57 | K7: ITEM_CAT_FOOD | L7: ITEM_FLAG_SHIELD | N7: Shield | O7: Armor | P7: AdminBelt | Q7: armors | R7: FALSE | S7: FALSE | T7: FALSE | U7: TRUE | V7: TRUE | W7: TRUE | X7: local function registerItem(instance, options) { options.requirementModules <- "requirementModules" in options ? options.requirementModules : [Game.ItemTemplate.emptyRequirement(0)]; options.equipModule <- "equipModule" in options ? options.equipModule : Game.ItemTemplate.armorEquip; options.stackable <- "stackable" in options ? options.stackable : false; options.category <- "category" in options ? options.category : ItemCategory.Armor; options.type <- "type" in options ? options.type : ItemType.Armor; options.group <- "group" in options ? options.group : ItemGroupType.AdminArmor; Game.ItemTemplate.registry.addItem(Game.ItemTemplate.myItem(instance, options), options); } | Z7: Łuczarz | AB7: MobDoor | AC7: door
A8: Hodowla zwierząt: owce | B8: AnimalHusbandrySheep | D8: Drwal | E8: LUMBERJACK | F8: 3 | H8: Piła | I8: ITMI_GS_COM_13 | K8: ITEM_CAT_DOCS | L8: ITEM_FLAG_BOW | N8: Helmet | O8: Skin | P8: AdminBag | Q8: backpack | R8: FALSE | S8: FALSE | T8: FALSE | U8: TRUE | V8: FALSE | W8: FALSE | X8: local class LocalBagEquip extends Game.ItemTemplate._baseEquipSynchronizedModule{ equipType = EquippedItems.Backpack } local function registerItem(instance, options) { options.category <- "category" in options ? options.category : ItemCategory.Backpack; options.type <- "type" in options ? options.type : ItemType.Accessory; options.requirementModules <- "requirementModules" in options ? options.requirementModules : [Game.ItemTemplate.emptyRequirement(0)]; options.equipModule <- "equipModule" in options ? options.equipModule : LocalBagEquip; options.stackable <- "stackable" in options ? options.stackable : false; options.group <- "group" in options ? options.group : ItemGroupType.AdminBackpack; Game.ItemTemplate.registry.addItem(Game.ItemTemplate.myItem(instance, options), options); } | Z8: Krawiec | AC8: another
A9: Hodowla zwierząt: krowy | B9: AnimalHusbandryCows | D9: Płatnerz | E9: ARMORSMITH | F9: 5 | H9: Młot kowalski | I9: ITMW_GS_1H_35_1 | K9: ITEM_CAT_POTION | L9: ITEM_FLAG_CROSSBOW | N9: Amulet | O9: Shield | P9: AdminBackpack | Q9: bag | R9: FALSE | S9: FALSE | T9: FALSE | U9: FALSE | V9: FALSE | W9: FALSE | X9: local class LocalBagEquip extends Game.ItemTemplate._baseEquipSynchronizedModule{ equipType = EquippedItems.Bag } local function registerItem(instance, options) { options.category <- "category" in options ? options.category : ItemCategory.Bag; options.type <- "type" in options ? options.type : ItemType.Accessory; options.requirementModules <- "requirementModules" in options ? options.requirementModules : [Game.ItemTemplate.emptyRequirement(0)]; options.equipModule <- "equipModule" in options ? options.equipModule : LocalBagEquip; options.stackable <- "stackable" in options ? options.stackable : false; options.group <- "group" in options ? options.group : ItemGroupType.AdminBag; Game.ItemTemplate.registry.addItem(Game.ItemTemplate.myItem(instance, options), options); } | Z9: Robotnik | AC9: wardrobe
A10: Mielarz | B10: Grinder | D10: Kowal | E10: BLACKSMITH | F10: 5 | H10: Chochla | I10: ITMI_GS_COM_23 | K10: ITEM_CAT_LIGHT | L10: ITEM_FLAG_RING | N10: Ring | O10: Rune | P10: AdminAccessory | Q10: ap_belt | R10: FALSE | S10: FALSE | T10: FALSE | U10: FALSE | V10: TRUE | W10: FALSE | X10: local class LocalItemEquip extends Game.ItemTemplate._baseEquipSynchronizedModule{ equipType = EquippedItems.Waist } local function registerItem(instance, options) { options.category <- "category" in options ? options.category : ItemCategory.Waist; options.type <- "type" in options ? options.type : ItemType.Accessory; options.requirementModules <- "requirementModules" in options ? options.requirementModules : [Game.ItemTemplate.emptyRequirement(0)]; options.equipModule <- "equipModule" in options ? options.equipModule : LocalItemEquip; options.stackable <- "stackable" in options ? options.stackable : false; options.group <- "group" in options ? options.group : ItemGroupType.AdminBelt; Game.ItemTemplate.registry.addItem(Game.ItemTemplate.myItem(instance, options), options); } | Z10: Myśliwy | AC10: decoration
A11: Deski do suszenia | B11: DryingBoards | D11: Zbrojmistrz | E11: WEAPONSMITH | F11: 5 | H11: Łopatka do ciast | I11: ITMI_GS_COM_20 | K11: ITEM_CAT_RUNE | L11: ITEM_FLAG_AMULET | N11: Belt | O11: SpeedPotion | P11: AdminWeaponCrossbow | Q11: gothic_belt | R11: FALSE | S11: FALSE | T11: FALSE | U11: TRUE | V11: TRUE | W11: FALSE | X11: local function registerItem(instance, options) { options.requirementModules <- "requirementModules" in options ? options.requirementModules : [Game.ItemTemplate.emptyRequirement(0)]; options.equipModule <- "equipModule" in options ? options.equipModule : Game.ItemTemplate.beltEquip; options.stackable <- "stackable" in options ? options.stackable : false; options.category <- "category" in options ? options.category : ItemCategory.Belt; options.type <- "type" in options ? options.type : ItemType.Accessory; Game.ItemTemplate.registry.addItem(Game.ItemTemplate.myItem(instance, options), options); } | Z11: Stoły Ogólnodostępne | AC11: structure
A12: Studnia | B12: Well | D12: Zaklinacz | E12: ENCHANTER | F12: 5 | H12: Patelnia | I12: ITMI_GS_COM_22 | K12: ITEM_CAT_MAGIC | L12: ITEM_FLAG_BELT | N12: Materials | O12: Common | P12: AdminWeaponBow | Q12: bolts | R12: FALSE | S12: FALSE | T12: FALSE | U12: FALSE | V12: FALSE | W12: FALSE | X12: local class LocalItemEquip extends Game.ItemTemplate._baseEquipSynchronizedModule{ equipType = EquippedItems.Bolts } local function registerItem(instance, options) { options.category <- "category" in options ? options.category : ItemCategory.Bolts; options.type <- "type" in options ? options.type : ItemType.Accessory; options.requirementModules <- "requirementModules" in options ? options.requirementModules : [Game.ItemTemplate.emptyRequirement(0)]; options.equipModule <- "equipModule" in options ? options.equipModule : LocalItemEquip; options.stackable <- "stackable" in options ? options.stackable : false; options.group <- "group" in options ? options.group : ItemGroupType.AdminAccessory; Game.ItemTemplate.registry.addItem(Game.ItemTemplate.myItem(instance, options), options); } | Z12: Zaklinacz | AC12: corpse
A13: Ognisko | B13: Campfire | D13: Kucharz | E13: COOK | F13: 3 | H13: Motyka | I13: ITMI_GS_COM_14 | K13: ITEM_CAT_ACSR1 | L13: ITEM_FLAG_DROPPED | N13: Common | O13: Materials | P13: AdminWeaponTwoHanded | Q13: bows | R13: FALSE | S13: FALSE | T13: TRUE | U13: TRUE | V13: FALSE | W13: FALSE | X13: local function registerItem(instance, options) { options.requirementModules <- "requirementModules" in options ? options.requirementModules : [Game.ItemTemplate.emptyRequirement(0)]; options.equipModule <- "equipModule" in options ? options.equipModule : Game.ItemTemplate.rangedWeaponEquip; options.stackable <- "stackable" in options ? options.stackable : false; options.category <- "category" in options ? options.category : ItemCategory.Weapon; options.type <- "type" in options ? options.type : ItemType.Bow; options.group <- "group" in options ? options.group : ItemGroupType.AdminWeaponBow; Game.ItemTemplate.registry.addItem(Game.ItemTemplate.myItem(instance, options), options); } | AC13: nature
A14: Krzak jagód polnych | B14: WildBerryBush | D14: Farmer | E14: FARMER | F14: 3 | H14: Sierp | I14: ITMW_GS_1H_55 | K14: ITEM_CAT_ACSR2 | L14: ITEM_FLAG_MI | N14: Backpack | O14: ? | P14: AdminWeaponOneHanded | Q14: common | R14: TRUE | S14: FALSE | T14: FALSE | U14: FALSE | V14: FALSE | W14: FALSE | X14: local function registerItem(instance, options = {}) { options.category <- "category" in options ? options.category : ItemCategory.Common Game.ItemTemplate.registry.addItem(Game.ItemTemplate.myItem(instance, options), options) } | AC14: pfx
A15: Jabłoń | B15: AppleTree | D15: Zbieracz | E15: GATHERER | F15: 3 | H15: Gałąź | I15: ITMI_GS_MAT_41 | K15: ITEM_CAT_CORPSE | L15: ITEM_FLAG_MULTI | N15: Bag | O15: Food | P15: AdminCommon | Q15: crossbows | R15: FALSE | S15: FALSE | T15: TRUE | U15: TRUE | V15: FALSE | W15: FALSE | X15: local function registerItem(instance, options) { options.requirementModules <- "requirementModules" in options ? options.requirementModules : [Game.ItemTemplate.emptyRequirement(0)]; options.equipModule <- "equipModule" in options ? options.equipModule : Game.ItemTemplate.rangedWeaponEquip; options.stackable <- "stackable" in options ? options.stackable : false; options.category <- "category" in options ? options.category : ItemCategory.Weapon; options.type <- "type" in options ? options.type : ItemType.Crossbow; options.group <- "group" in options ? options.group : ItemGroupType.AdminWeaponCrossbow; Game.ItemTemplate.registry.addItem(Game.ItemTemplate.myItem(instance, options), options); }
A16: Krzak jagód leśnych | B16: ForestBerryBush | D16: Alchemik | E16: ALCHEMIST | F16: 5 | H16: Wędka | I16: ITMW_GS_2H_31 | K16: ITEM_CAT_FURNITURE | L16: ITEM_FLAG_NFOCUS | N16: Bolts | O16: Corpse | P16: AdminMaterials | Q16: mask | R16: FALSE | S16: FALSE | T16: FALSE | U16: FALSE | V16: FALSE | W16: FALSE | X16: local class LocalItemEquip extends Game.ItemTemplate._baseEquipSynchronizedModule{ equipType = EquippedItems.Mask } local function registerItem(instance, options) { options.category <- "category" in options ? options.category : ItemCategory.Mask; options.type <- "type" in options ? options.type : ItemType.Accessory; options.requirementModules <- "requirementModules" in options ? options.requirementModules : [Game.ItemTemplate.emptyRequirement(0)]; options.equipModule <- "equipModule" in options ? options.equipModule : LocalItemEquip; options.stackable <- "stackable" in options ? options.stackable : false; options.group <- "group" in options ? options.group : ItemGroupType.AdminMask; Game.ItemTemplate.registry.addItem(Game.ItemTemplate.myItem(instance, options), options); }
A17: Gniazdo pająków | B17: SpiderWeb | D17: Myśliwy | E17: HUNTER | F17: 5 | H17: Alembik | I17: ITMI_GS_COM_17 | K17: ITEM_CAT_MASK | L17: ITEM_FLAG_CREATEAMMO | N17: RingLeft | O17: Potion | P17: ? | Q17: nakrycia_glowy | R17: FALSE | S17: FALSE | T17: FALSE | U17: FALSE | V17: FALSE | W17: TRUE | X17: local function registerItem(instance, options) { options.category <- "category" in options ? options.category : ItemCategory.Bolts; options.type <- "type" in options ? options.type : ItemType.Accessory; options.requirementModules <- "requirementModules" in options ? options.requirementModules : [Game.ItemTemplate.emptyRequirement(0)]; options.equipModule <- "equipModule" in options ? options.equipModule : Game.ItemTemplate.helmetEquip; options.stackable <- "stackable" in options ? options.stackable : false; options.group <- "group" in options ? options.group : ItemGroupType.AdminArmor; Game.ItemTemplate.registry.addItem(Game.ItemTemplate.myItem(instance, options), options); }
A18: Ul | B18: Beehive | H18: Brzytwa | I18: ITMI_GS_COM_19 | K18: ITEM_CAT_BACKPACK | L18: ITEM_FLAG_NSPLIT | N18: RingRight | O18: CraftingMaterial | P18: AdminCorpse | Q18: potions | R18: TRUE | S18: TRUE | T18: FALSE | U18: FALSE | V18: FALSE | W18: FALSE | X18: local function registerItem(instance, options) { options.category <- "category" in options ? options.category : ItemCategory.Consumable options.group <- "group" in options ? options.group : ItemGroupType.AdminWeaponBow Game.ItemTemplate.registry.addItem(Game.ItemTemplate.myItem(instance, options), options) }
A19: Łowisko | B19: FishingSpot | H19: Żuwaczka | I19: ITMI_GS_COM_21 | K19: ITEM_CAT_BELT | L19: ITEM_FLAG_DRINK | N19: Necklace | O19: Common | P19: AdminFood | Q19: rings | R19: FALSE | S19: FALSE | T19: FALSE | U19: FALSE | V19: TRUE | W19: FALSE | X19: local function registerItem(instance, options) { options.requirementModules <- "requirementModules" in options ? options.requirementModules : [Game.ItemTemplate.emptyRequirement(0)]; options.equipModule <- "equipModule" in options ? options.equipModule : Game.ItemTemplate.ringEquip; options.stackable <- "stackable" in options ? options.stackable : false; Game.ItemTemplate.registry.addItem(Game.ItemTemplate.myItem(instance, options), options); }
A20: Pień do przerobu drewna | B20: WoodProcessingLog | H20: Młotek ciesielski | I20: ITMI_GS_COM_15 | K20: ITEM_CAT_RINGLEFT | L20: ITEM_FLAG_TORCH | N20: Waist | O20: Furniture | P20: AdminPotion | Q20: runes | R20: FALSE | S20: FALSE | T20: TRUE | U20: TRUE | V20: FALSE | W20: FALSE | X20: local function registerItem(instance, options) { options.requirementModules <- "requirementModules" in options ? options.requirementModules : [Game.ItemTemplate.emptyRequirement(0)]; options.equipModule <- "equipModule" in options ? options.equipModule : Game.ItemTemplate.runesEquip; options.stackable <- "stackable" in options ? options.stackable : false; Game.ItemTemplate.registry.addItem(Game.ItemTemplate.myItem(instance, options), options); }
A21: Ruszt | B21: Grill | K21: ITEM_CAT_RINGRIGHT | L21: ITEM_FLAG_THROW | N21: AccessorySlot1 | O21: Projectile | P21: AdminCraftingMaterial | Q21: shields | R21: FALSE | S21: FALSE | T21: FALSE | U21: TRUE | V21: TRUE | W21: TRUE | X21: local function registerItem(instance, options) { options.requirementModules <- "requirementModules" in options ? options.requirementModules : [Game.ItemTemplate.emptyRequirement(0)]; options.equipModule <- "equipModule" in options ? options.equipModule : Game.ItemTemplate.shieldEquip; options.stackable <- "stackable" in options ? options.stackable : false; options.category <- "category" in options ? options.category : ItemCategory.Shield; options.type <- "type" in options ? options.type : ItemType.Shield; options.group <- "group" in options ? options.group : ItemGroupType.AdminShield; Game.ItemTemplate.registry.addItem(Game.ItemTemplate.myItem(instance, options), options); }
A22: Zmywak | B22: Washbasin | D22: - | E22: - | K22: ITEM_CAT_NECKLACE | L22: ITEM_FLAG_ACTIVE | N22: AccessorySlot2 | O22: Clothes | P22: AdminFurniture | Q22: weapons1h | R22: FALSE | S22: FALSE | T22: TRUE | U22: TRUE | V22: FALSE | W22: TRUE | X22: local function registerItem(instance, options) { options.strength <- "strength" in options ? options.strength : 0; options.requirementModules <- "requirementModules" in options ? options.requirementModules : [Game.ItemTemplate.StrengthRequirement(options.strength)] options.equipModule <- "equipModule" in options ? options.equipModule : Game.ItemTemplate.meleeWeaponEquip; options.stackable <- "stackable" in options ? options.stackable : false; options.category <- "category" in options ? options.category : ItemCategory.Weapon; options.type <- "type" in options ? options.type : ItemType.OneHanded; options.quickSlotEnabled <- "quickSlotEnabled" in options ? options.quickSlotEnabled : false; options.group <- "group" in options ? options.group : ItemGroupType.AdminWeaponOneHanded; Game.ItemTemplate.registry.addItem(Game.ItemTemplate.myItem(instance, options), options); }
A23: Patelnia nad ogniskiem | B23: FryingPan | K23: ITEM_CAT_ACSR3 | L23: ITEM_WEAR_NO | N23: AccessorySlot3 | O23: Mask | P23: AdminProjectile | Q23: weapons2h | R23: FALSE | S23: FALSE | T23: TRUE | U23: TRUE | V23: FALSE | W23: TRUE | X23: local function registerItem(instance, options) { options.strength <- "strength" in options ? options.strength : 0; options.requirementModules <- "requirementModules" in options ? options.requirementModules : [Game.ItemTemplate.StrengthRequirement(options.strength)] options.equipModule <- "equipModule" in options ? options.equipModule : Game.ItemTemplate.meleeWeaponEquip; options.stackable <- "stackable" in options ? options.stackable : false; options.category <- "category" in options ? options.category : ItemCategory.Weapon; options.type <- "type" in options ? options.type : ItemType.TwoHanded; options.group <- "group" in options ? options.group : ItemGroupType.AdminWeaponTwoHanded; Game.ItemTemplate.registry.addItem(Game.ItemTemplate.myItem(instance, options), options); }
A24: Wiadro z wodą | B24: WaterBucket | K24: ITEM_CAT_BELTY | L24: ITEM_WEAR_TORSO | N24: AccessorySlot4 | O24: Belts | P24: AdminRunes | Q24: materials | R24: TRUE | S24: FALSE | T24: FALSE | U24: FALSE | V24: FALSE | W24: FALSE
A25: Stół do patroszenia ryb | B25: FishCleaningTable | K25: ? | L25: ITEM_WEAR_HEAD | N25: Mask | Q25: ? | R25: FALSE | S25: FALSE | T25: FALSE | U25: FALSE | V25: FALSE | W25: FALSE
A26: Misa do wyciskania | B26: PressingBowl | K26: ITEM_CAT_ACSR4 | L26: ITEM_WEAR_LIGHT | N26: Common | Q26: consumable | R26: TRUE | S26: TRUE | T26: FALSE | U26: FALSE | V26: FALSE | W26: FALSE
A27: Stół do destylacji | B27: DistillationTable | K27: ITEM_CAT_BAG | L27: ITEM_FLAG_ROD | N27: Materials | Q27: corpse | R27: FALSE | S27: FALSE | T27: FALSE | U27: FALSE | V27: FALSE | W27: FALSE | X27: local function registerItem(instance, options = {}) { options.equipModule <- "equipModule" in options ? options.equipModule : Game.ItemTemplate.CorpseEquip; options.stackable <- "stackable" in options ? options.stackable : false; options.requirementModules <- "requirementModules" in options ? options.requirementModules : [Game.ItemTemplate.emptyRequirement(0)]; Game.ItemTemplate.registry.addItem(Game.ItemTemplate.myItem(instance, options), options) }
A28: Osełka | B28: Whetstone | K28: ITEM_CAT_BELTS | L28: ITEM_FLAG_2HD_OBUCH | N28: ? | Q28: furniture | R28: FALSE | S28: FALSE | T28: FALSE | U28: FALSE | V28: FALSE | W28: FALSE
A29: Stojak do skórowania zwierzyny | B29: SkinningRack | L29: ITEM_FLAG_SPEAR | N29: CraftingMaterial | Q29: projectile | R29: TRUE | S29: FALSE | T29: FALSE | U29: FALSE | V29: FALSE | W29: FALSE
A30: Stojak do garbowania skór | B30: TanningRack | L30: - | N30: Furniture | Q30: helmets | R30: FALSE | S30: FALSE | T30: FALSE | U30: TRUE | V30: TRUE | W30: TRUE | X30: local function registerItem(instance, options) { options.requirementModules <- "requirementModules" in options ? options.requirementModules : [Game.ItemTemplate.emptyRequirement(0)]; options.equipModule <- "equipModule" in options ? options.equipModule : Game.ItemTemplate.helmetEquip; options.stackable <- "stackable" in options ? options.stackable : false; options.category <- "category" in options ? options.category : ItemCategory.Helmet; options.type <- "type" in options ? options.type : ItemType.Helmet; options.group <- "group" in options ? options.group : ItemGroupType.AdminHelmet; Game.ItemTemplate.registry.addItem(Game.ItemTemplate.myItem(instance, options), options); }
A31: Warsztat do strzał | B31: ArrowWorkbench | L31: ITEM_FLAG_OBUCH | N31: Projectile | R31: FALSE | S31: FALSE | T31: FALSE | U31: FALSE | V31: FALSE | W31: FALSE
A32: Stanowisko skryby | B32: ScribeTable | L32: ? | N32: Belts | R32: FALSE | S32: FALSE | T32: FALSE | U32: FALSE | V32: FALSE | W32: FALSE
A33: Biedna kuchenka | B33: PoorStove | L33: ITEM_FLAG_BELTS | R33: FALSE | S33: FALSE | T33: FALSE | U33: FALSE | V33: FALSE | W33: FALSE
A34: Kocioł | B34: Cauldron | R34: FALSE | S34: FALSE | T34: FALSE | U34: FALSE | V34: FALSE | W34: FALSE
A35: Piec piekarski | B35: BakeryOven | V35: FALSE | W35: FALSE
A36: Stół farmera | B36: FarmerTable
A37: Manekin - Krawiec | B37: TailorDummy
A38: Stół gorzelniczy | B38: DistilleryTable
A39: Stojak do przerobu drewna | B39: WoodProcessingStand
A40: Bogata kuchenka | B40: RichStove
A41: Kowadło | B41: BlacksmithAnvil
A42: Piec kowalski | B42: BlacksmithFurnace
A43: Manekin - Kuśnierz | B43: FurrierDummy
A44: Stół płatnerza | B44: ArmorerTable
A45: Krosno | B45: Loom
A46: Warsztat łuczarza | B46: BowyerWorkshop
A47: Stół alchemiczny | B47: AlchemyTable
... A54: Drzewo | B54: Tree

Sheet Cennik
A1: Półprodukty | D1: Tutaj wpisuj nazwy arkuszy: | E1: Kucharz | F1: Farmer | G1: Robotnik | H1: Zbieracz | I1: Alchemik | J1: Myśliwy | K1: Hutnik | L1: Krawiec | M1: Zbrojmistrz/Płatnerz/Kowal | N1: Łuczarz | O1: Stolarz | P1: Sklep | Q1: Zaklinacz | R1: Runemaker | S1: Nazwa | T1: Nazwa | U1: Nazwa | V1: Nazwa | W1: Nazwa | X1: Nazwa | Y1: Nazwa
A2: Nazwa | B2: Koszt | C2: Waga | D2: Formuła dla podanego arkusza: | E2: {=VLOOKUP(D2, INDIRECT("'"&$E$1&"'!$A$3:$B"), 2, FALSE())} -> #REF! | F2: {=VLOOKUP(E2, INDIRECT("'"&$F$1&"'!$B$3:$E"), 4, FALSE())} -> #REF! | G2: {=VLOOKUP(F2, INDIRECT("'"&$G$1&"'!$A$3:$B"), 2, FALSE())} -> #REF! | H2: {=VLOOKUP(#REF!, INDIRECT("'"&$H$1&"'!$A$3:$B"), 2, FALSE())} -> #REF! | I2: {=VLOOKUP(H2, INDIRECT("'"&$I$1&"'!$A$3:$B"), 2, FALSE())} -> #REF! | J2: {=VLOOKUP(I2, INDIRECT("'"&$J$1&"'!$B$3:$e"), 2, FALSE())} -> #REF! | K2: {=VLOOKUP(J2, INDIRECT("'"&$K$1&"'!$A$3:$B"), 2, FALSE())} -> #REF! | L2: {=VLOOKUP(K2, INDIRECT("'"&$L$1&"'!$B$3:$D"), 2, FALSE())} -> #REF! | M2: {=VLOOKUP(L2, INDIRECT("'"&$M$1&"'!$A$3:$B"), 2, FALSE())} -> #REF! | N2: {=VLOOKUP(M2, INDIRECT("'"&$N$1&"'!$B$3:$E"), 4, FALSE())} -> #REF! | O2: {=VLOOKUP(633, INDIRECT("'"&$O$1&"'!$B$6:$E"), 2, FALSE())} -> #REF! | P2: {=VLOOKUP(O2, INDIRECT("'"&$P$1&"'!$B$3:$E"), 2, FALSE())} -> #REF! | Q2: {=VLOOKUP(P2, INDIRECT("'"&$Q$1&"'!$A$3:$B"), 3, FALSE())} -> #REF! | R2: {=VLOOKUP(R2, INDIRECT("'"&$R$1&"'!$B$3:$D"), 2, FALSE())} -> #REF! | S2: {=VLOOKUP(K2, INDIRECT("'"&$S$1&"'!$B$3:$D"), 2, FALSE())} -> #REF! | T2: {=VLOOKUP(S2, INDIRECT("'"&$T$1&"'!$A$3:$B"), 2, FALSE())} -> #REF! | U2: {=VLOOKUP(T2, INDIRECT("'"&$U$1&"'!$A$3:$B"), 2, FALSE())} -> #REF! | V2: {=VLOOKUP(U2, INDIRECT("'"&$V$1&"'!$A$3:$B"), 2, FALSE())} -> #REF! | W2: {=VLOOKUP(V2, INDIRECT("'"&$W$1&"'!$A$3:$B"), 2, FALSE())} -> #REF! | X2: {=VLOOKUP(W2, INDIRECT("'"&$X$1&"'!$A$3:$B"), 2, FALSE())} -> #REF! | Y2: {=VLOOKUP(X2, INDIRECT("'"&$Y$1&"'!$A$3:$B"), 2, FALSE())} -> #REF!
A3: Ogólnodostępne
A4: - | B4: 0
A5: Butelka | B5: 0
A6: Brudna miska | B6: 0
A7: Brudna butelka | B7: 0
A8: Stamina | B8: 0.35
A9: Woda święcona | B9: 0.2
A10: Woda | B10: 0.2
A11: Moneta | B11: 1
A12: Zniszczona Szkatułka | B12: 0
A13: Stara moneta | B13: 0.5
A14: Orkowa blacha | B14: 250
A15: Mięso chrząszcza | B15: 0.4
A16: Kucharz
A17: Półprodukty
A20: Półprodukty z półproduktów
A22: Pasztet z resztek | B22: =VLOOKUP(A22, INDIRECT("'"&$E$1&"'!$B$4:$K"), 10, FALSE()) -> #REF! | C22: 0.3
A23: Prażone owady | B23: =VLOOKUP(A23, INDIRECT("'"&$E$1&"'!$B$4:$K"), 10, FALSE()) -> #REF! | C23: 0.3
A24: Smażone skóry rybne | B24: =VLOOKUP(A24, INDIRECT("'"&$E$1&"'!$B$4:$K"), 10, FALSE()) -> #REF! | C24: 0.3
A25: Wiejska jajecznica | B25: =VLOOKUP(A25, INDIRECT("'"&$E$1&"'!$B$4:$K"), 10, FALSE()) -> #REF! | C25: 0.4
A26: Szczur na patyku | B26: =VLOOKUP(A26, INDIRECT("'"&$E$1&"'!$B$4:$K"), 10, FALSE()) -> #REF! | C26: 0.4
A27: Ryba w cieście piwnym | B27: =VLOOKUP(A27, INDIRECT("'"&$E$1&"'!$B$4:$K"), 10, FALSE()) -> #REF! | C27: 0.4
A28: Mięsny bigos | B28: =VLOOKUP(A28, INDIRECT("'"&$E$1&"'!$B$4:$K"), 10, FALSE()) -> #REF! | C28: 0.4
A29: Marynowane grzyby | B29: =VLOOKUP(A29, INDIRECT("'"&$E$1&"'!$B$4:$K"), 10, FALSE()) -> #REF! | C29: 0.4
A30: Marynowana rzepa | B30: =VLOOKUP(A30, INDIRECT("'"&$E$1&"'!$B$4:$K"), 10, FALSE()) -> #REF! | C30: 0.4
A31: Szaszłyk ze ścierwojada i dyni | B31: =VLOOKUP(A31, INDIRECT("'"&$E$1&"'!$B$4:$K"), 10, FALSE()) -> #REF! | C31: 0.5
A32: Ryba w occie z ognistym zielem | B32: =VLOOKUP(A32, INDIRECT("'"&$E$1&"'!$B$4:$K"), 10, FALSE()) -> #REF! | C32: 0.5
A33: Wędzona ryba ziołowa | B33: =VLOOKUP(A33, INDIRECT("'"&$E$1&"'!$B$4:$K"), 10, FALSE()) -> #REF! | C33: 0.5
... A67: Drożówka cynamonowa | B67: =VLOOKUP(A67, INDIRECT("'"&$E$1&"'!$B$4:$K"), 10, FALSE()) -> #REF! | C67: 0.6
A69: Farmer
A70: Półprodukty
